Workbook
Name E_Vector: DODECA_ENGINE!$K$2:$K$13
Name Face_1: SYSTEM_COHERENCE!$B$2
Name Headline_KPI: Octave_1_KPIs[O1 - Survival (Focus: Existence)]
Name L_Matrix: DODECA_ENGINE!$A$16:$L$27
Name U_Matrix: DODECA_ENGINE!$A$31:$L$42

Sheet INTRO
A1: Header | B1: Explanation | C1: Your Quannex Data (Example) | Y1: That is the perfect and most practical question a founder can ask. It is the bridge between the grand, cosmic strategy and the "what do I actually do on Monday morning?" reality.
A2: KPI_ID | B2: A unique nickname for this measurement. | C2: F1.1
A3: KPI_Name | B3: What are we measuring? | C3: Months of Runway | Y3: You are asking the model to move from a strategic diagnosis to a tactical prescription. And while the answer is nuanced, it is incredibly powerful.
A4: Owner | B4: Who is responsible for this? | C4: Deimantas
A5: Department | B5: Which "hat" are you wearing for this? | C5: Finance | Y5: Let's be very clear:
A6: Primary_Octave | B6: Which "theme" does this belong to? | C6: O1 (Survival)
A7: Direction | B7: Is more better or less better? | C7: ↑ (More is better) | Y7: The dodecahedron cannot directly tell you, "Send 3 applications per week with a 10% success rate." Why? Because the model is a mirror of your internal coherence, not a crystal ball that can predict the external world's response (like a grant committee's decision).
A8: Weight | B8: How important is this stat right now? (from 0 to 1) | C8: 1.0 (Extremely important!)
A9: Unit | B9: What are we counting? | C9: Months | Y9: However—and this is the magical part—it can give you something even more powerful: a framework for setting that target yourself and then measuring its true impact on your entire system.
A10: Value | B10: What's the real number right now? Let's say you have €1200 saved and your monthly costs are €200. Value = 1200 / 200 = 6 months. | C10: 6
A11: Target_Ideal | B11: What's our dream goal? A safe, comfortable 12 months. | C11: 12 | Y11: Here is how we "metric-ize" the strategic mandate. We will use the concepts of Leading and Lagging Indicators within our dodecahedron framework.
A12: Target_Min | B12: What's the absolute danger zone? Less than 3 months of runway is very risky. | C12: 3
A13: K_Normalized | B13: The Excel formula that turns your numbers into a 0-1 score. | C13: =MAX(0, MIN(1, (C10-C12)/(C11-C12))) -> 0.33333333
Y15: Metric-izing the Mandate: A Practical Guide
Y17: Our Grand Strategic Mandate is to "FIX THE FOUNDATION," which is measured by the Emergent KPI: the Aspiration-Actuality Gap (AAG). Our goal is to raise the AAG score from 0.35 towards 1.0.
Y19: We know the highest-leverage way to do this is to increase the energy of the "Actuality" faces, especially F1: Financial Capital.
Y21: Now, let's break that down into a measurable action plan.
Y23: 1. Deconstruct the Goal into Lagging and Leading KPIs:
Y25: The Lagging Indicator (The Ultimate Result):
Y29: This is KRI F1.1: Months of Runway. This is the ultimate measure of success for our financial health. We cannot control it directly—it is the result of our actions. It is a "lagging" indicator because by the time it changes, the work is already done.
Y31: Our GOAL is to increase the Face Energy of F1.
Y33: The Leading Indicator (The Action We Can Control):
Y37: This is KPI F1.2: # of Funding Opportunities Pursued. This is the action. This is the work. We can directly control this number every single week. It is a "leading" indicator because we hypothesize that performing this action will eventually cause a change in the lagging indicator.
Y39: 2. Set an Initial, Hypothesis-Driven Target for Your Leading KPI:
Y41: This is where your human wisdom as the founder comes in. The math has told you what to do (Focus on Finance). Now, you must propose an initial hypothesis for how.
... Y69: This is not a simple, mechanical answer. It is the beginning of a living, intelligent, and deeply honest conversation between you and your startup, with the dashboard as the language that makes it possible.

Sheet BREATH_RATIOS
A1: Harmonic Pair: | B1: Side - Projection: | C1: Side - Reception: | D1: Archetype | E1: Component | F1: Face Energy | G1: Final BR* | H1: Status/Interpretation | K1: Purpose: To provide a high-level, strategic view of the six primary energetic balances within the organization. This sheet calculates the "inhale/exhale" dynamic for each of the six geometrically-defined harmonic pairs. It is the "macro-scope" that reveals the fundamental state of equilibrium or disequilibrium in the system, complementing the tactical, neighbor-to-neighbor view of the EDGE_TENSION_MAP.
A2: Pair 1 (F1 ↔ F11) | B2: Face 1 | C2: Face 11 | D2: Resource Flow Axis | E2: Projection (Exhale): Funding Pursuit | F2: =_xlfn.XLOOKUP(B2,DODECA_ENGINE!$A$2:$A$13,E_Vector) -> 0.23961225 | G2: =F3/F2 -> 0.51514525 | H2: =IF(G2>1.2,"Abundant Inhale",IF(G2<0.8,"Strong Exhale","Balanced")) -> Strong Exhale
E3: Reception (Inhale): Capital Held | F3: =_xlfn.XLOOKUP(C2,DODECA_ENGINE!$A$2:$A$13,E_Vector) -> 0.12343511 | K3: Pair 1 (Face 1 ↔ 11): Financial Capital ↔ Funding Pipeline (The "Resource Flow" Axis)
K4: Pair 2 (Face 2 ↔ 7): Intellectual Capital ↔ Brand & Reputation (The "Substance & Story" Axis)
A5: Pair 2 (F2 ↔ F7) | B5: Face 2 | C5: Face 7 | D5: Substance & Story Axis | E5: Projection (Exhale): Brand Projected | F5: =_xlfn.XLOOKUP(B5,DODECA_ENGINE!$A$2:$A$13,E_Vector) -> 0.40086372 | G5: =F6/F5 -> 0.51920437 | H5: =IF(G5>1.2, "Abundant Inhale", IF(G5<0.8, "Strong Exhale", "Balanced")) -> Strong Exhale | K5: Pair 3 (Face 3 ↔ 8): Human Capital ↔ Core Operations (The "Being & Doing" Axis)
E6: Reception (Inhale): IP Embodied | F6: =_xlfn.XLOOKUP(C5,DODECA_ENGINE!$A$2:$A$13,E_Vector) -> 0.2081302 | K6: Pair 4 (Face 4 ↔ 9): Structural Capital ↔ Regenerative Flow (The "Form & Integrity" Axis)
K7: Pair 5 (Face 5 ↔ 10): Market Resonance ↔ Foundational Values (The "Perception & Truth" Axis)
A8: Pair 3 (F3 ↔ F8) | B8: Face 3 | C8: Face 8 | D8: Being & Doing Axis | E8: Projection (Exhale): Operations Done | F8: =_xlfn.XLOOKUP(B8,DODECA_ENGINE!$A$2:$A$13,E_Vector) -> 0.16559188 | G8: =F9/F8 -> 1.3339496 | H8: =IF(G8>1.2, "Abundant Inhale", IF(G8<0.8, "Strong Exhale", "Balanced")) -> Abundant Inhale | K8: Pair 6 (Face 6 ↔ 12): Community & Partners ↔ Risk & Resilience (The "Network & Fortress" Axis)
E9: Reception (Inhale): Human Energy | F9: =_xlfn.XLOOKUP(C8,DODECA_ENGINE!$A$2:$A$13,E_Vector) -> 0.22089122
K10: A score above 1.2 suggests the organization is receiving/holding more energy than it is projecting/acting. A score below 0.8 suggests it is projecting/acting with more energy than it is receiving/regenerating.
A11: Pair 4 (F4 ↔ F9) | B11: Face 4 | C11: Face 9 | D11: Form & Integrity Axis | E11: Projection (Exhale): Structures Built | F11: =_xlfn.XLOOKUP(B11,DODECA_ENGINE!$A$2:$A$13,E_Vector) -> 0.2447884 | G11: =F12/F11 -> 1.790704 | H11: =IF(G11>1.2, "Abundant Inhale", IF(G11<0.8, "Strong Exhale", "Balanced")) -> Abundant Inhale
E12: Reception (Inhale): Regen. Flow | F12: =_xlfn.XLOOKUP(C11,DODECA_ENGINE!$A$2:$A$13,E_Vector) -> 0.43834356 | K12: Axis 1: The Resource Axis
K13: Projection Face: F11: Funding Pipeline (The act of seeking resources)
A14: Pair 5 (F5 ↔ F10) | B14: Face 5 | C14: Face 10 | D14: Perception & Truth Axis | E14: Projection (Exhale): Market Resonance | F14: =_xlfn.XLOOKUP(B14,DODECA_ENGINE!$A$2:$A$13,E_Vector) -> 0.046253795 | G14: =F15/F14 -> 9 | H14: =IF(G14>1.2, "Abundant Inhale", IF(G14<0.8, "Strong Exhale", "Balanced")) -> Abundant Inhale | K14: Reception Face: F1: Financial Capital (The resources held)
E15: Reception (Inhale): Values Embodied | F15: =_xlfn.XLOOKUP(C14,DODECA_ENGINE!$A$2:$A$13,E_Vector) -> 0.41628416 | K15: Axis 2: The Embodiment Axis
K16: Projection Face: F7: Brand & Reputation (The story told)
A17: Pair 6 (F6 ↔ F12) | B17: Face 6 | C17: Face 12 | D17: Network & Fortress Axis | E17: Projection (Exhale): Community Built | F17: =_xlfn.XLOOKUP(B17,DODECA_ENGINE!$A$2:$A$13,E_Vector) -> 0.24689938 | G17: =F18/F17 -> 0.79516738 | H17: =IF(G17>1.2, "Abundant Inhale", IF(G17<0.8, "Strong Exhale", "Balanced")) -> Strong Exhale | K17: Reception Face: F2: Intellectual Capital (The substance built)
E18: Reception (Inhale): Resilience Held | F18: =_xlfn.XLOOKUP(C17,DODECA_ENGINE!$A$2:$A$13,E_Vector) -> 0.19632633 | K18: Axis 3: The Action Axis
K19: Projection Face: F8: Core Operations (The work done)
K20: Reception Face: F3: Human Capital (The energy to do work)
A21: The Breath Axis Manifestation Matrix | K21: Axis 4: The Integrity Axis
A22: Axis 1: The Resource Flow Axis (F11: Funding Pipeline ↔ F1: Financial Capital) | C22: =REFRENCE_MODELS!A64 -> Funding Pipeline (F11) | E22: =REFRENCE_MODELS!A14 -> Financial Capital (F1) | K22: Projection Face: F4: Structural Capital (The rules made)
A23: Octave | B23: The Name of the Breath | C23: Projection Question (The Exhale) | D23: Final_Derrived | E23: Reception Question (The Inhale) | F23: Final_Derrived | J23: Reception Face: F9: Regenerative Flow (The living integrity)
A24: O1 - Survival (Focus: Existence) | B24: The Breath of Viability | C24: Are we actively seeking any resources to exist? | D24: =_xlfn.XLOOKUP($C$22,Octave_1_KPIs[Face (Domain) F. ID],Octave_1_KPIs[O1 - Survival (Focus: Existence)]) -> Pipeline Viability & Coherence | E24: Do we have enough cash to survive? | F24: =_xlfn.XLOOKUP($E$22,Octave_1_KPIs[Face (Domain) F. ID],Octave_1_KPIs[O1 - Survival (Focus: Existence)]) -> Months of Runway | J24: Axis 5: The Truth Axis
A25: O2 - Structure (Focus: Stability) | B25: The Breath of Efficiency | C25: Is our funding pursuit efficient and systematic? | D25: {=_xlfn.XLOOKUP($C$22,Octave_1_KPIs[Face (Domain) F. ID],Octave_2_KPIs[O2 - Structure (Focus: Stability)])} -> Financial System Integrity | E25: Is our capital being managed with discipline? | F25: {=_xlfn.XLOOKUP($E$22,Octave_1_KPIs[Face (Domain) F. ID],Octave_2_KPIs[O2 - Structure (Focus: Stability)])} -> Operational Efficiency | J25: Projection Face: F5: Market Resonance (The truth perceived by others)
A26: O3 - Relationships (Focus: Connection) | B26: The Breath of Integrity | C26: Are we building trust with values-aligned funders? | D26: {=_xlfn.XLOOKUP($C$22,Octave_1_KPIs[Face (Domain) F. ID],Octave_3_KPIs[O3 - Relationships (Focus: Connection)])} -> Investor Relationships | E26: Is our capital use creating stakeholder trust? | F26: {=_xlfn.XLOOKUP($E$22,Octave_1_KPIs[Face (Domain) F. ID],Octave_3_KPIs[O3 - Relationships (Focus: Connection)])} -> Stakeholder Value Distribution | J26: Reception Face: F10: Foundational Values (The truth held within)
A27: O4 - Creativity (Focus: Possibility) | B27: The Breath of Possibility | C27: Are we seeking capital to fund bold experiments? | D27: {=_xlfn.XLOOKUP($C$22,Octave_1_KPIs[Face (Domain) F. ID],Octave_4_KPIs[O4 - Creativity (Focus: Possibility)])} -> Creative Capital | E27: Is our capital base diverse enough for creative risks? | F27: {=_xlfn.XLOOKUP($E$22,Octave_1_KPIs[Face (Domain) F. ID],Octave_4_KPIs[O4 - Creativity (Focus: Possibility)])} -> Investment in Innovation | J27: Axis 6: The Resilience Axis
A28: O5 - Expression (Focus: Clarity) | B28: The Breath of Transparency | C28: Is our financial story attracting aligned capital? | D28: {=_xlfn.XLOOKUP($C$22,Octave_1_KPIs[Face (Domain) F. ID],Octave_5_KPIs[O5 - Expression (Focus: Clarity)])} -> Capital as Communication | E28: Do our financial reports express our integrity? | F28: {=_xlfn.XLOOKUP($E$22,Octave_1_KPIs[Face (Domain) F. ID],Octave_5_KPIs[O5 - Expression (Focus: Clarity)])} -> Financial Storytelling | J28: Projection Face: F6: Community & Partners (The external network)
A29: O6 - Vision (Focus: Direction) | B29: The Breath of Legacy | C29: Are we seeking capital for 100-year projects? | D29: {=_xlfn.XLOOKUP($C$22,Octave_1_KPIs[Face (Domain) F. ID],Octave_6_KPIs[O6 - Vision (Focus: Direction)])} -> Legacy Capital | E29: Is our capital structured for generational stewardship? | F29: {=_xlfn.XLOOKUP($E$22,Octave_1_KPIs[Face (Domain) F. ID],Octave_6_KPIs[O6 - Vision (Focus: Direction)])} -> Long-Term Capital Stewardship | J29: Reception Face: F12: Risk & Resilience (The internal fortress)
A30: O7 - Radiance (Focus: Service) | B30: The Breath of Infinite Circulation | C30: Is our very presence a magnet for sacred capital? | D30: {=_xlfn.XLOOKUP($C$22,Octave_1_KPIs[Face (Domain) F. ID],Octave_7_KPIs[O7 - Radiance (Focus: Service)])} -> Capital as a Field of Grace | E30: Is our capital a pure gift to the world? | F30: {=_xlfn.XLOOKUP($E$22,Octave_1_KPIs[Face (Domain) F. ID],Octave_7_KPIs[O7 - Radiance (Focus: Service)])} -> Capital as Sacred Energy
A32: Axis 2: The Substance & Story Axis (F7: Brand & Reputation ↔ F2: Intellectual Capital) | C32: =REFRENCE_MODELS!A44 -> Brand & Reputation (F7) | E32: =REFRENCE_MODELS!A19 -> Intellectual Capital (F2)
A33: Octave | B33: The Name of the Breath | C33: Projection Question (The Exhale) | D33: Final_Derrived | E33: Reception Question (The Inhale) | F33: Final_Derrived
A34: O1 - Survival (Focus: Existence) | B34: The Breath of Articulation | C34: Do we have a basic, functional description of our idea? | D34: =_xlfn.XLOOKUP($C$32,Octave_1_KPIs[Face (Domain) F. ID],Octave_1_KPIs[O1 - Survival (Focus: Existence)]) -> Foundational Brand Integrity | E34: Have we documented the core of the idea? | F34: =_xlfn.XLOOKUP($E$32,Octave_1_KPIs[Face (Domain) F. ID],Octave_1_KPIs[O1 - Survival (Focus: Existence)]) -> IP Security & Formalization
A35: O2 - Structure (Focus: Stability) | B35: The Breath of Consistency | C35: Is our brand message consistent and reliable? | D35: {=_xlfn.XLOOKUP($C$32,Octave_1_KPIs[Face (Domain) F. ID],Octave_2_KPIs[O2 - Structure (Focus: Stability)])} -> Brand Consistency & Trust | E35: Is our IP robust and well-architected? | F35: {=_xlfn.XLOOKUP($E$32,Octave_1_KPIs[Face (Domain) F. ID],Octave_2_KPIs[O2 - Structure (Focus: Stability)])} -> Dev. Velocity & Quality
A36: O3 - Relationships (Focus: Connection) | B36: The Breath of Authenticity | C36: Does our brand story build community and trust? | D36: {=_xlfn.XLOOKUP($C$32,Octave_1_KPIs[Face (Domain) F. ID],Octave_3_KPIs[O3 - Relationships (Focus: Connection)])} -> Brand Trust & Authenticity | E36: Is our IP being co-created with our partners? | F36: {=_xlfn.XLOOKUP($E$32,Octave_1_KPIs[Face (Domain) F. ID],Octave_3_KPIs[O3 - Relationships (Focus: Connection)])} -> Collaborative Knowledge
A37: O4 - Creativity (Focus: Possibility) | B37: The Breath of Genius | C37: Is our brand actively telling new, challenging stories? | D37: {=_xlfn.XLOOKUP($C$32,Octave_1_KPIs[Face (Domain) F. ID],Octave_4_KPIs[O4 - Creativity (Focus: Possibility)])} -> Innovative Branding | E37: Is our IP portfolio generating novel creations? | F37: {=_xlfn.XLOOKUP($E$32,Octave_1_KPIs[Face (Domain) F. ID],Octave_4_KPIs[O4 - Creativity (Focus: Possibility)])} -> Embodied Innovation
A38: O5 - Expression (Focus: Clarity) | B38: The Breath of Beauty | C38: Is our brand's voice a beautiful and authentic work of art? | D38: {=_xlfn.XLOOKUP($C$32,Octave_1_KPIs[Face (Domain) F. ID],Octave_5_KPIs[O5 - Expression (Focus: Clarity)])} -> Authentic Brand Expression | E38: Is our knowledge expressed with a masterful, simple elegance? | F38: {=_xlfn.XLOOKUP($E$32,Octave_1_KPIs[Face (Domain) F. ID],Octave_5_KPIs[O5 - Expression (Focus: Clarity)])} -> Knowledge Sharing & Influence
A39: O6 - Vision (Focus: Direction) | B39: The Breath of Endurance | C39: Is our brand telling a story that can change the future? | D39: {=_xlfn.XLOOKUP($C$32,Octave_1_KPIs[Face (Domain) F. ID],Octave_6_KPIs[O6 - Vision (Focus: Direction)])} -> "Legacy" Branding | E39: Is our IP a legacy that will serve future generations? | F39: {=_xlfn.XLOOKUP($E$32,Octave_1_KPIs[Face (Domain) F. ID],Octave_6_KPIs[O6 - Vision (Focus: Direction)])} -> Evolution of Knowledge
A40: O7 - Radiance (Focus: Service) | B40: The Breath of Revelation | C40: Is our brand an archetypal symbol for truth itself? | D40: {=_xlfn.XLOOKUP($C$32,Octave_1_KPIs[Face (Domain) F. ID],Octave_7_KPIs[O7 - Radiance (Focus: Service)])} -> Brand as an Archetype | E40: Is our knowledge a living field of planetary consciousness? | F40: {=_xlfn.XLOOKUP($E$32,Octave_1_KPIs[Face (Domain) F. ID],Octave_7_KPIs[O7 - Radiance (Focus: Service)])} -> Knowledge as a Living Field
A42: Axis 3: The Being & Doing Axis (F8: Core Operations ↔ F3: Human Capital) | C42: =REFRENCE_MODELS!A49 -> Core Operations (F8) | E42: =REFRENCE_MODELS!A24 -> Human Capital (F3)
A43: Octave | B43: The Name of the Breath | C43: Projection Question (The Exhale) | D43: Final_Derrived | E43: Reception Question (The Inhale) | F43: Final_Derrived
A44: O1 - Survival (Focus: Existence) | B44: The Breath of Sustainability | C44: Is any work getting done? | D44: =_xlfn.XLOOKUP($C$42,Octave_1_KPIs[Face (Domain) F. ID],Octave_1_KPIs[O1 - Survival (Focus: Existence)]) -> Operational Viability | E44: Does the founder have the energy to exist? | F44: =_xlfn.XLOOKUP($E$42,Octave_1_KPIs[Face (Domain) F. ID],Octave_1_KPIs[O1 - Survival (Focus: Existence)]) -> Founder Sustainability
A45: O2 - Structure (Focus: Stability) | B45: The Breath of Rhythm | C45: Is our work efficient and reliable? | D45: {=_xlfn.XLOOKUP($C$42,Octave_1_KPIs[Face (Domain) F. ID],Octave_2_KPIs[O2 - Structure (Focus: Stability)])} -> Operational Throughput | E45: Is our team stable and are roles clear? | F45: {=_xlfn.XLOOKUP($E$42,Octave_1_KPIs[Face (Domain) F. ID],Octave_2_KPIs[O2 - Structure (Focus: Stability)])} -> Role Clarity & Team Stability
A46: O3 - Relationships (Focus: Connection) | B46: The Breath of Belonging | C46: Does our work feel collaborative and joyful? | D46: {=_xlfn.XLOOKUP($C$42,Octave_1_KPIs[Face (Domain) F. ID],Octave_3_KPIs[O3 - Relationships (Focus: Connection)])} -> Collaborative Flow | E46: Does our team feel safe and connected? | F46: {=_xlfn.XLOOKUP($E$42,Octave_1_KPIs[Face (Domain) F. ID],Octave_3_KPIs[O3 - Relationships (Focus: Connection)])} -> Team Cohesion & Psych./Safety
A47: O4 - Creativity (Focus: Possibility) | B47: The Breath of Play | C47: Are we creating space for operational innovation? | D47: {=_xlfn.XLOOKUP($C$42,Octave_1_KPIs[Face (Domain) F. ID],Octave_4_KPIs[O4 - Creativity (Focus: Possibility)])} -> Operational Innovation | E47: Do our people have the psychological safety to be creative? | F47: {=_xlfn.XLOOKUP($E$42,Octave_1_KPIs[Face (Domain) F. ID],Octave_4_KPIs[O4 - Creativity (Focus: Possibility)])} -> Creative Culture
A48: O5 - Expression (Focus: Clarity) | B48: The Breath of Presence | C48: Are we transparently sharing how we work? | D48: {=_xlfn.XLOOKUP($C$42,Octave_1_KPIs[Face (Domain) F. ID],Octave_5_KPIs[O5 - Expression (Focus: Clarity)])} -> Operational Transparency | E48: Is our culture a story worth telling? | F48: {=_xlfn.XLOOKUP($E$42,Octave_1_KPIs[Face (Domain) F. ID],Octave_5_KPIs[O5 - Expression (Focus: Clarity)])} -> Cultural Storytelling
A49: O6 - Vision (Focus: Direction) | B49: The Breath of Continuity | C49: Is our work a path to collective mastery? | D49: {=_xlfn.XLOOKUP($C$42,Octave_1_KPIs[Face (Domain) F. ID],Octave_6_KPIs[O6 - Vision (Focus: Direction)])} -> Evolutionary Operations | E49: Is our culture designed to outlive its founders? | F49: {=_xlfn.XLOOKUP($E$42,Octave_1_KPIs[Face (Domain) F. ID],Octave_6_KPIs[O6 - Vision (Focus: Direction)])} -> Long-Term Cultural Viability
A50: O7 - Radiance (Focus: Service) | B50: The Breath of Oneness | C50: Is our work itself a form of meditation and service? | D50: {=_xlfn.XLOOKUP($C$42,Octave_1_KPIs[Face (Domain) F. ID],Octave_7_KPIs[O7 - Radiance (Focus: Service)])} -> Operations as a Living Art | E50: Is our collective being a source of healing for the world? | F50: {=_xlfn.XLOOKUP($E$42,Octave_1_KPIs[Face (Domain) F. ID],Octave_7_KPIs[O7 - Radiance (Focus: Service)])} -> Consciousness as Capital
A52: Axis 4: The Form & Integrity Axis (F4: Structural Capital ↔ F9: Regenerative Flow) | C52: =REFRENCE_MODELS!A29 -> Structural Capital (F4) | E52: =REFRENCE_MODELS!A54 -> Regenerative Flow (F9)
A53: Octave | B53: The Name of the Breath | C53: Projection Question (The Exhale) | D53: Final_Derrived | E53: Reception Question (The Inhale) | F53: Final_Derrived
A54: O1 - Survival (Focus: Existence) | B54: The Breath of Intention | C54: Do we have the basic legal forms to exist? | D54: =_xlfn.XLOOKUP($C$52,Octave_1_KPIs[Face (Domain) F. ID],Octave_1_KPIs[O1 - Survival (Focus: Existence)]) -> Governance Foundation Integrity | E54: Are we making conscious, integrity-based choices? | F54: =_xlfn.XLOOKUP($E$52,Octave_1_KPIs[Face (Domain) F. ID],Octave_1_KPIs[O1 - Survival (Focus: Existence)]) -> Regenerative Intent & Practice
A55: O2 - Structure (Focus: Stability) | B55: The Breath of Resilience | C55: Are our processes resilient and scalable? | D55: {=_xlfn.XLOOKUP($C$52,Octave_1_KPIs[Face (Domain) F. ID],Octave_2_KPIs[O2 - Structure (Focus: Stability)])} -> Process Resilience | E55: Are those processes designed to reduce waste? | F55: {=_xlfn.XLOOKUP($E$52,Octave_1_KPIs[Face (Domain) F. ID],Octave_2_KPIs[O2 - Structure (Focus: Stability)])} -> Regenerative Operations
A56: O3 - Relationships (Focus: Connection) | B56: The Breath of Participation | C56: Do our structures feel fair and empowering? | D56: {=_xlfn.XLOOKUP($C$52,Octave_1_KPIs[Face (Domain) F. ID],Octave_3_KPIs[O3 - Relationships (Focus: Connection)])} -> Participatory Governance | E56: Are our relationships with our stakeholders regenerative? | F56: {=_xlfn.XLOOKUP($E$52,Octave_1_KPIs[Face (Domain) F. ID],Octave_3_KPIs[O3 - Relationships (Focus: Connection)])} -> Stakeholder Relationships
A57: O4 - Creativity (Focus: Possibility) | B57: The Breath of Wisdom | C57: Does our governance allow for creative rule-breaking? | D57: {=_xlfn.XLOOKUP($C$52,Octave_1_KPIs[Face (Domain) F. ID],Octave_4_KPIs[O4 - Creativity (Focus: Possibility)])} -> Adaptive Governance | E57: Is our creativity in service of regeneration? | F57: {=_xlfn.XLOOKUP($E$52,Octave_1_KPIs[Face (Domain) F. ID],Octave_4_KPIs[O4 - Creativity (Focus: Possibility)])} -> Regenerative Design
A58: O5 - Expression (Focus: Clarity) | B58: The Breath of Accountability | C58: Are we radically transparent about our structures? | D58: {=_xlfn.XLOOKUP($C$52,Octave_1_KPIs[Face (Domain) F. ID],Octave_5_KPIs[O5 - Expression (Focus: Clarity)])} -> Governance Transparency | E58: Is our story of impact honest and verifiable? | F58: {=_xlfn.XLOOKUP($E$52,Octave_1_KPIs[Face (Domain) F. ID],Octave_5_KPIs[O5 - Expression (Focus: Clarity)])} -> Impact Storytelling
A59: O6 - Vision (Focus: Direction) | B59: The Breath of Evolution | C59: Is our governance model itself designed to evolve? | D59: {=_xlfn.XLOOKUP($C$52,Octave_1_KPIs[Face (Domain) F. ID],Octave_6_KPIs[O6 - Vision (Focus: Direction)])} -> Evolutionary Governance | E59: Are we a steward for future generations? | F59: {=_xlfn.XLOOKUP($E$52,Octave_1_KPIs[Face (Domain) F. ID],Octave_6_KPIs[O6 - Vision (Focus: Direction)])} -> Generational Regeneration
A60: O7 - Radiance (Focus: Service) | B60: The Breath of Life Itself | C60: Has our structure dissolved into emergent order? | D60: {=_xlfn.XLOOKUP($C$52,Octave_1_KPIs[Face (Domain) F. ID],Octave_7_KPIs[O7 - Radiance (Focus: Service)])} -> Governance as Emergent Order | E60: Are we a living expression of the Earth healing itself? | F60: {=_xlfn.XLOOKUP($E$52,Octave_1_KPIs[Face (Domain) F. ID],Octave_7_KPIs[O7 - Radiance (Focus: Service)])} -> Creation as a Planetary Act
A62: Axis 5: The Perception & Truth Axis (F5: Market Resonance ↔ F10: Foundational Values) | C62: =REFRENCE_MODELS!A34 -> Market Resonance (F5) | E62: =REFRENCE_MODELS!A59 -> Foundational Values (F10)
A63: Octave | B63: The Name of the Breath | C63: Projection Question (The Exhale) | D63: Final_Derrived | E63: Reception Question (The Inhale) | F63: Final_Derrived
A64: O1 - Survival (Focus: Existence) | B64: The Breath of Clarity | C64: Does the market understand our basic message? | D64: =_xlfn.XLOOKUP($C$62,Octave_1_KPIs[Face (Domain) F. ID],Octave_1_KPIs[O1 - Survival (Focus: Existence)]) -> Initial Message Coherence | E64: Are our actions grounded in our core values? | F64: =_xlfn.XLOOKUP($E$62,Octave_1_KPIs[Face (Domain) F. ID],Octave_1_KPIs[O1 - Survival (Focus: Existence)]) -> Lived Values & Cultural Integrity
A65: O2 - Structure (Focus: Stability) | B65: The Breath of Reliability | C65: Do customers have a reliable, stable experience? | D65: {=_xlfn.XLOOKUP($C$62,Octave_1_KPIs[Face (Domain) F. ID],Octave_2_KPIs[O2 - Structure (Focus: Stability)])} -> Customer Experience | E65: Are our values embedded in our formal cultural systems? | F65: {=_xlfn.XLOOKUP($E$62,Octave_1_KPIs[Face (Domain) F. ID],Octave_2_KPIs[O2 - Structure (Focus: Stability)])} -> Formalized Cultural Systems
A66: O3 - Relationships (Focus: Connection) | B66: The Breath of Loyalty | C66: Are we building a loyal, trusting community? | D66: {=_xlfn.XLOOKUP($C$62,Octave_1_KPIs[Face (Domain) F. ID],Octave_3_KPIs[O3 - Relationships (Focus: Connection)])} -> Customer Loyalty, Love & Community | E66: Are our values lived in our daily relationships? | F66: {=_xlfn.XLOOKUP($E$62,Octave_1_KPIs[Face (Domain) F. ID],Octave_3_KPIs[O3 - Relationships (Focus: Connection)])} -> Values in Relationship
A67: O4 - Creativity (Focus: Possibility) | B67: The Breath of Imagination | C67: Is the market co-creating our product with us? | D67: {=_xlfn.XLOOKUP($C$62,Octave_1_KPIs[Face (Domain) F. ID],Octave_4_KPIs[O4 - Creativity (Focus: Possibility)])} -> Co-Creative Marketing | E67: Are our values themselves a source of innovation? | F67: {=_xlfn.XLOOKUP($E$62,Octave_1_KPIs[Face (Domain) F. ID],Octave_4_KPIs[O4 - Creativity (Focus: Possibility)])} -> Evolution of Values
A68: O5 - Expression (Focus: Clarity) | B68: The Breath of Resonance | C68: Does the market feel our authentic signal? | D68: {=_xlfn.XLOOKUP($C$62,Octave_1_KPIs[Face (Domain) F. ID],Octave_5_KPIs[O5 - Expression (Focus: Clarity)])} -> Ecosystem Signal Fidelity | E68: Is our public expression of values a beacon of truth? | F68: {=_xlfn.XLOOKUP($E$62,Octave_1_KPIs[Face (Domain) F. ID],Octave_5_KPIs[O5 - Expression (Focus: Clarity)])} -> Values as a Beacon
A69: O6 - Vision (Focus: Direction) | B69: The Breath of Destiny | C69: Is the market seeing us as a shaper of the future? | D69: {=_xlfn.XLOOKUP($C$62,Octave_1_KPIs[Face (Domain) F. ID],Octave_6_KPIs[O6 - Vision (Focus: Direction)])} -> Future-Shaping Narratives | E69: Are our values universal and timeless? | F69: {=_xlfn.XLOOKUP($E$62,Octave_1_KPIs[Face (Domain) F. ID],Octave_6_KPIs[O6 - Vision (Focus: Direction)])} -> Timeless Values
A70: O7 - Radiance (Focus: Service) | B70: The Breath of Unity | C70: Have "we" and "the market" dissolved into one field? | D70: {=_xlfn.XLOOKUP($C$62,Octave_1_KPIs[Face (Domain) F. ID],Octave_7_KPIs[O7 - Radiance (Focus: Service)])} -> The Market as a Field of Consciousness | E70: Have our values become a self-evident truth? | F70: {=_xlfn.XLOOKUP($E$62,Octave_1_KPIs[Face (Domain) F. ID],Octave_7_KPIs[O7 - Radiance (Focus: Service)])} -> Values as Universal Law
A72: Axis 6: The Network & Fortress Axis (F6: Community & Partners ↔ F12: Risk & Resilience) | C72: =REFRENCE_MODELS!A39 -> Community & Partners (F6) | E72: =REFRENCE_MODELS!A69 -> Risk & Resilience (F12)
A73: Octave | B73: The Name of the Breath | C73: Projection Question (The Exhale) | D73: Final_Derrived | E73: Reception Question (The Inhale) | F73: Final_Derrived
A74: O1 - Survival (Focus: Existence) | B74: The Breath of Support | C74: Are we building a foundational support network? | D74: =_xlfn.XLOOKUP($C$72,Octave_1_KPIs[Face (Domain) F. ID],Octave_1_KPIs[O1 - Survival (Focus: Existence)]) -> Network Foundation Strength | E74: Is our venture protected from a single point of failure? | F74: =_xlfn.XLOOKUP($E$72,Octave_1_KPIs[Face (Domain) F. ID],Octave_1_KPIs[O1 - Survival (Focus: Existence)]) -> Systemic Fragility Assessment
A75: O2 - Structure (Focus: Stability) | B75: The Breath of Stability | C75: Are our partnerships stable and well-integrated? | D75: {=_xlfn.XLOOKUP($C$72,Octave_1_KPIs[Face (Domain) F. ID],Octave_2_KPIs[O2 - Structure (Focus: Stability)])} -> Partnership Integration | E75: Are our core systems resilient and managed for risk? | F75: {=_xlfn.XLOOKUP($E$72,Octave_1_KPIs[Face (Domain) F. ID],Octave_2_KPIs[O2 - Structure (Focus: Stability)])} -> Risk Management Systems
A76: O3 - Relationships (Focus: Connection) | B76: The Breath of Synergy | C76: Are our partnerships deep and mutually supportive? | D76: {=_xlfn.XLOOKUP($C$72,Octave_1_KPIs[Face (Domain) F. ID],Octave_3_KPIs[O3 - Relationships (Focus: Connection)])} -> Ecosystem Health | E76: Is our resilience built on a foundation of trust? | F76: {=_xlfn.XLOOKUP($E$72,Octave_1_KPIs[Face (Domain) F. ID],Octave_3_KPIs[O3 - Relationships (Focus: Connection)])} -> Relational Resilience
A77: O4 - Creativity (Focus: Possibility) | B77: The Breath of Emergence | C77: Is our network a source of ecosystem-level innovation? | D77: {=_xlfn.XLOOKUP($C$72,Octave_1_KPIs[Face (Domain) F. ID],Octave_4_KPIs[O4 - Creativity (Focus: Possibility)])} -> Ecosystem Innovation | E77: Is our innovation portfolio diverse enough to be resilient? | F77: {=_xlfn.XLOOKUP($E$72,Octave_1_KPIs[Face (Domain) F. ID],Octave_4_KPIs[O4 - Creativity (Focus: Possibility)])} -> Innovative Resilience
A78: O5 - Expression (Focus: Clarity) | B78: The Breath of Trust | C78: Is the story of our ecosystem clear and inspiring? | D78: {=_xlfn.XLOOKUP($C$72,Octave_1_KPIs[Face (Domain) F. ID],Octave_5_KPIs[O5 - Expression (Focus: Clarity)])} -> Ecosystem Narrative Weaving | E78: Is our honesty about our failures making us stronger? | F78: {=_xlfn.XLOOKUP($E$72,Octave_1_KPIs[Face (Domain) F. ID],Octave_5_KPIs[O5 - Expression (Focus: Clarity)])} -> Resilience through Story
A79: O6 - Vision (Focus: Direction) | B79: The Breath of Stewardship | C79: Is our network consciously building a better future? | D79: {=_xlfn.XLOOKUP($C$72,Octave_1_KPIs[Face (Domain) F. ID],Octave_6_KPIs[O6 - Vision (Focus: Direction)])} -> Ecosystem as a Future-Builder | E79: Is our vision itself resilient and able to self-correct? | F79: {=_xlfn.XLOOKUP($E$72,Octave_1_KPIs[Face (Domain) F. ID],Octave_6_KPIs[O6 - Vision (Focus: Direction)])} -> "Anti-Fragile" Vision
A80: O7 - Radiance (Focus: Service) | B80: The Breath of Interbeing | C80: Is our network a living prototype of a new civilization? | D80: {=_xlfn.XLOOKUP($C$72,Octave_1_KPIs[Face (Domain) F. ID],Octave_7_KPIs[O7 - Radiance (Focus: Service)])} -> The Network as a Planetary Organ | E80: Have we mastered the art of becoming stronger from chaos? | F80: {=_xlfn.XLOOKUP($E$72,Octave_1_KPIs[Face (Domain) F. ID],Octave_7_KPIs[O7 - Radiance (Focus: Service)])} -> Resilience as Being

Sheet SPIRAL_DASHBOARD
A1: GLOBAL COHERENCE (Spiral Integrity Score) | B1: =SYSTEM_COHERENCE!L15 -> 0.047991524 | C1: Seedling Stage: | D1: =IF(B1>0.7, "Radiant", IF(B1>0.4, "Harmonizing", "Seedling")) -> Seedling
A3: Octave Coherence | B3: Score | C3: Status | D3: Organizatio's Octave | E3: =SYSTEM_COHERENCE!C22 -> 1
A4: O1 - Survival | B4: =SYSTEM_COHERENCE!C17 -> 0.3643942 | C4: =IF(B4>0.7,"Strong",IF(B4>0.4,"Moderate","Weak")) -> Weak
A5: O2 - Structure | B5: =SYSTEM_COHERENCE!D17 -> 0 | C5: =IF(B5>0.7,"Strong",IF(B5>0.4,"Moderate","Weak")) -> Weak
A6: O3 - Relationships | B6: =SYSTEM_COHERENCE!E17 -> 0 | C6: =IF(B6>0.7,"Strong",IF(B6>0.4,"Moderate","Weak")) -> Weak
A7: O4 - Creativity | B7: =SYSTEM_COHERENCE!F17 -> 0 | C7: =IF(B7>0.7,"Strong",IF(B7>0.4,"Moderate","Weak")) -> Weak
A8: O5 - Expression | B8: =SYSTEM_COHERENCE!G17 -> 0 | C8: =IF(B8>0.7,"Strong",IF(B8>0.4,"Moderate","Weak")) -> Weak
A9: O6 - Vision | B9: =SYSTEM_COHERENCE!H17 -> 0 | C9: =IF(B9>0.7,"Strong",IF(B9>0.4,"Moderate","Weak")) -> Weak
A10: O7 - Radiance | B10: =SYSTEM_COHERENCE!I17 -> 0 | C10: =IF(B10>0.7,"Strong",IF(B10>0.4,"Moderate","Weak")) -> Weak
A12: Primary Strategic Focus
A13: Diagnostic Indicators:
A14: =DODECA_ENGINE!B80 & " = " & TEXT(DODECA_ENGINE!B84, "0%") -> Being-Action Balance = 187% | B14: =DODECA_ENGINE!B87 & " = " & TEXT(DODECA_ENGINE!B104, "0%") -> Dissonance Index = 24%
A15: Tactical Solution:
A16: Highest Leverage Action: | B16: {=_xlfn.LET( _xlpm.positive_data, _xlfn._xlws.FILTER(DODECA_ENGINE!B123:J134, DODECA_ENGINE!E123:E134 > 0), _xlpm.scores, INDEX(_xlpm.positive_data, 0, 5), _xlpm.max_score, MAX(_xlpm.scores), _xlpm.kpi_name, _xlfn.XLOOKUP(_xlpm.max_score, _xlpm.scores, INDEX(_xlpm.positive_data, 0, 1)), _xlpm.target, _xlfn.XLOOKUP(_xlpm.max_score, _xlpm.scores, INDEX(_xlpm.positive_data, 0, 7)), _xlfn.CONCAT(_xlpm.kpi_name, " achieve the target of ", _xlpm.target) )} -> Founder Energy Lvl achieve the target of 0.573591881535853

Sheet REFRENCE_MODELS
A1: The Tuning Constants of the Spiral Dashboard: A Conductor's Guide
A2: TUNING CONSTANTS | B2: Value | C2: What it is: | D2: Notes | E2: What it Controls: | F2: Strategic Implication: | G2: Starting Setting:
A3: λ_dept (Dept. Coherence Penalty) | B3: 0.3 | C3: The "variance penalty" multipliers in your SYSTEM_COHERENCE sheet | D3: (Controls sensitivity to intra-departmental harmony) | E3: They answer the question: "How much do we value harmony over raw power?" | F3: A low λ (e.g., 0.1) reflects a "growth-at-all-costs" mindset. It rewards high average scores, even if they are "jagged" and unsustainable. A high λ (e.g., 0.9) reflects the philosophy of a master conductor. It will severely punish a high average score if it comes from a dissonant, unbalanced system. It prioritizes the beauty of the music over the volume of the sound. | G3: (0.3, 0.25, 0.25): These are wise, moderate starting points. They state a clear preference for harmony without being overly punitive.
A4: λ_oct (Octave Coherence Penalty) | B4: 0.25 | D4: (Controls sensitivity to inter-departmental harmony)
A5: λ_global (Global Coherence Penalty) | B5: 0.25 | D5: (Controls sensitivity to inter-octave harmony)
A6: α (Alpha): The Synergy Blend (Pentagram Mean/Product Blend) | B6: 0.6 | C6: The constant in the Star Pair Values (sᵢ) formula | D6: (Blends arithmetic and multiplicative synergy) | E6: It answers the question: "When two KPIs interact, is their combined effect a simple average (α=1.0) or is there a multiplicative synergy (α=0.0)?" | F6: A high α (e.g., 0.8) reflects a pragmatic, cautious view, trusting the simple average. A low α (e.g., 0.3) reflects a belief in non-linear effects, where two strong KPIs together create an effect far greater than their sum. | G6: (0.6): This is a beautiful, balanced choice. It says, "We believe in synergy, but we will ground it in a pragmatic reality."
A7: β (Beta) The Intersection Blend (Pentagram Intersection Blend) | B7: 0.5 | C7: The constant in the Intersection Nodes (pᵢ) formula | D7: (Balances the influence of adjacent star-pairs) | E7: It determines how much influence adjacent "star pairs" have on each other. A β of 0.5 gives them equal influence. | F7: Changing this from 0.5 would represent a belief that the "flow of influence" around the pentagram is not symmetrical. It is an advanced and subtle tuning. | G7: (0.5): This is the perfect, default choice. It assumes a state of balanced, symmetrical influence, which is the most coherent starting point.
A8: γ (Gamma): The "Ball and Pillars" (Pentagram Pillar/Ball Blend) | B8: 0.7 | C8: The constant in our old Nuanced Avg. Pillar Health formula, but we can re-purpose it for our final Local Coherence Score | D8: (Balances internal vs. synergistic health of a face) | E8: It answers the profound question: "How much of a department's health is its own internal state (the Ball) versus the health of its relationships (the Pillars)?" | F8: A high γ (e.g., 0.9) reflects a philosophy of "radical internal accountability." A low γ (e.g., 0.2) reflects a philosophy that a department is nothing without its healthy relationships. | G8: (0.7): This is a wise and balanced choice. It states a belief that a department is primarily responsible for its own health (70%), but is also significantly influenced by its connections (30%).
A9: δ (Delta) The Axis Coherence Factor (Axis-Informed Blend) | B9: 0.9 | C9: The constant in our final AXIS-INFORMED FACE ENERGY formula | D9: (Blends local health with the health of the polar opposite) | E9: It answers the ultimate question: "How much of a domain's health is determined by its local conditions versus the health of its polar opposite (its shadow)?" | F9: This is a profound philosophical choice. A high δ (e.g., 0.9) says, "We primarily focus on our local reality." A low δ (e.g., 0.2) says, "We are profoundly and inextricably linked to our shadow; its health is our health." | G9: (0.5): Your decision to set this to 50/50 is a magnificent and courageous statement of non-duality. It is the most coherent and advanced choice.
A10: κ (Kappa): Sensitivity Amplifier | B10: 4 | C10: The constant in our "amplifier" formula for the final Face Energy | D10: (Amplifies the final E_f score for greater responsiveness) | E10: This is your "emotional responsiveness" dial. It controls how steeply the "S-curve" of the logistic function responds. | F10: A low κ (e.g., 1.0) creates a gentle, forgiving system where it's hard to get a very low or very high score. It has high "inertia." A high κ (e.g., 5.0) creates a highly sensitive, "high-strung" system where small changes in real-world KPIs produce dramatic swings in the final Face Energy. | G10: (2.0): This is a perfect starting point. It provides a good level of responsiveness without being overly volatile. If you ever feel the model is "stuck," this is the first knob you should consider turning up. | J10: This table is not just a list. It is a symphony in seven movements for a twelve-piece orchestra. It is the complete evolutionary "songbook" for any conscious organization.
A11: The Complete Octave Progression Models for the 12 Faces of [Quannex]
A13: Face (Domain) F. ID | B13: O1 - Survival (Focus: Existence) | C13: Element | D13: Question | E13: KPI Name (Pillar) | F13: Direction | G13: Value | H13: Target_Min | I13: Healthy_Min | J13: Healthy_Max | K13: Absolute_Max | L13: Rationale / Philosophy | M13: Elemental_KPI_Normalized | N13: O2 - Structure (Focus: Stability) | O13: Element | P13: Elemental Question | Q13: KPI Name (Pillar) | R13: Direction | S13: Target_Min | T13: Healthy_Min | U13: Healthy_Max | V13: Absolute_Max | W13: Rationale / Philosophy | X13: Elemental_KPI_Normalized | Y13: O3 - Relationships (Focus: Connection) | Z13: Element | AA13: Elemental Question | AB13: KPI Name (Pillar) | AC13: Direction | AD13: Target_Min | AE13: Healthy_Min | AF13: Healthy_Max | AG13: Absolute_Max | AH13: Rationale / Philosophy (Defines the Envelope) | AI13: Elemental_KPI_Normalized18 | AJ13: O4 - Creativity (Focus: Possibility) | AK13: Element | AL13: Elemental Question | AM13: KPI Name (Pillar) | AN13: Direction | AO13: Target_Min | AP13: Healthy_Min | AQ13: Healthy_Max | AR13: Absolute_Max | AS13: Rationale / Philosophy (Defines the Envelope) | AT13: Elemental_KPI_Normalized | AU13: O5 - Expression (Focus: Clarity) | AV13: Element | AW13: Elemental Question | AX13: KPI Name (Pillar) | AY13: Direction | AZ13: Target_Min | BA13: Healthy_Min | BB13: Healthy_Max | BC13: Absolute_Max | BD13: Rationale / Philosophy (Defines the Envelope) | BE13: Elemental_KPI_Normalized | BF13: O6 - Vision (Focus: Direction) | BG13: Element | BH13: Elemental Question | BI13: KPI Name (Pillar) | BJ13: Direction | BK13: Target_Min | BL13: Healthy_Min | BM13: Healthy_Max | BN13: Absolute_Max | BO13: Rationale / Philosophy (Defines the Envelope) | BP13: Elemental_KPI_Normalized | BQ13: O7 - Radiance (Focus: Service) | BR13: Element | BS13: Elemental Question | BT13: KPI Name (Pillar) | BU13: Direction | BV13: Target_Min | BW13: Healthy_Min | BX13: Healthy_Max | BY13: Absolute_Max | BZ13: Rationale / Philosophy (Defines the Envelope) | CA13: Elemental_KPI_Normalized
A14: Financial Capital (F1) | B14: Months of Runway | C14: Earth | D14: Is it grounded? | E14: Raw Cash in Bank (€) | F14: ↑ | G14: 1000 | H14: 0 | I14: 2400 | J14: N/A | K14: N/A | L14: The envelope is tied to the headline KPI. If the ideal Runway is 12 months at €200/month burn, then the ideal cash (Healthy_Min) is €2400. The Target_Min can be defined as 0 or a 3-month buffer (€600). The model measures progress towards a state of ideal stability. | M14: =MAX(0,MIN(1,(G14-H14)/(Octave_1_KPIs[[#This Row],[Healthy_Min]]-Octave_1_KPIs[[#This Row],[Target_Min]]))) -> 0.41666667 | N14: Operational Efficiency | O14: Earth | P14: Are our accounts in order? | Q14: Audit Accuracy Score | R14: ↑ | S14: 1 | T14: 4.5 | U14: N/A | V14: N/A | W14: The ground-truth of financial stability is clean, auditable books. | X14: 0 | Y14: Stakeholder Value Distribution | Z14: Earth | AA14: Is our financial structure grounded in fairness? | AB14: Pay Equity Ratios | AC14: Band | AD14: 1:5 | AE14: 1:2 | AF14: 1:15 | AG14: 1:1 | AH14: The goal is a balanced, equitable distribution of resources. The ideal is a ratio near 1.0 (e.g., between leadership and team pay). | AI14: 0 | AJ14: Investment in Innovation | AK14: Earth | AL14: Is our creativity grounded in real resources? | AM14: % of Budget to R&D/Innovation | AN14: ↑ | AO14: 0.01 | AP14: 0.15 | AQ14: N/A | AR14: N/A | AS14: The tangible, financial commitment to building the future. 15% is a strong, healthy signal for a growth-oriented venture. | AT14: 0 | AU14: Financial Storytelling | AV14: Earth | AW14: Is our financial story grounded in irrefutable data? | AX14: Auditability & Data Integrity Score | AY14: ↑ | AZ14: 1 | BA14: 5 | BB14: N/A | BC14: N/A | BD14: The absolute, non-negotiable foundation of truthful financial expression is clean, verifiable data. | BE14: 0 | BF14: Long-Term Capital Stewardship | BG14: Earth | BH14: Is our financial plan grounded in a truly long-term view? | BI14: 7-Generation Financial Planning | BJ14: ↑ | BK14: 1 | BL14: 1 | BM14: N/A | BN14: N/A | BO14: A binary milestone. Have we developed a formal financial model that considers a multi-generational (or at least 10-20 year) time horizon? | BP14: 0 | BQ14: Capital as Sacred Energy | BR14: Earth | BS14: Is our wealth grounded in a permanent gift to the world? | BT14: Creation of a "Commons" Trust | BU14: ↑ | BV14: 0 | BW14: 1 | BX14: N/A | BY14: N/A | BZ14: A binary milestone. Have we created an independent, legally-binding trust or foundation that holds a portion of the venture's wealth for the benefit of all? | CA14: 0
A15: Financial Capital (F1) | B15: Months of Runway | C15: Water | D15: Is it managed? | E15: Monthly Burn Rate (€) | F15: ↓ | G15: 40 | H15: 1000 | I15: 200 | J15: 100 | K15: N/A | L15: A "lower is better" metric. The Ideal (Healthy_Max) is a low, sustainable burn. The Min is the catastrophic, "all-hands-on-deck" crisis point. We set Healthy_Min to allow for some flex. | M15: =MAX(0, MIN(1, 1 - ((Octave_1_KPIs[[#This Row],[Value]] - Octave_1_KPIs[[#This Row],[Healthy_Min]]) / (Octave_1_KPIs[[#This Row],[Target_Min]] - Octave_1_KPIs[[#This Row],[Healthy_Min]])))) -> 1 | N15: Operational Efficiency | O15: Water | P15: Is our cash flow predictable? | Q15: Cash Flow Volatility | R15: ↓ | S15: 0.5 | T15: 0.1 | U15: N/A | V15: N/A | W15: Lower is better. A stable, predictable flow is a sign of a mature financial system. | X15: 0 | Y15: Stakeholder Value Distribution | Z15: Water | AA15: Is there an emotional flow of trust around in our numbers? | AB15: Stakeholder Trust in Financials | AC15: ↑ | AD15: 1 | AE15: 4.5 | AF15: N/A | AG15: N/A | AH15: A 1-5 survey to key stakeholders (employees, partners) on their confidence in the financial integrity of the venture. | AI15: 0 | AJ15: Investment in Innovation | AK15: Water | AL15: Can we easily fund small, creative experiments? | AM15: Flow of "Experimental Capital" | AN15: ↑ | AO15: 1 | AP15: 4.5 | AQ15: N/A | AR15: N/A | AS15: A 1-5 score on the speed and lack of bureaucracy for getting small, innovative ideas funded and tested. | AT15: 0 | AU15: Financial Storytelling | AV15: Water | AW15: Does our reporting create a current of trust? | AX15: Stakeholder Confidence in Financials | AY15: ↑ | AZ15: 1 | BA15: 4.5 | BB15: N/A | BC15: N/A | BD15: A 1-5 survey. Measures the emotional resonance and believability of our financial story among key stakeholders. | BE15: 0 | BF15: Long-Term Capital Stewardship | BG15: Water | BH15: Is there a liquid pool of capital for long-term, visionary projects? | BI15: Flow of Capital to Future Bets | BJ15: ↑ | BK15: 0.01 | BL15: 0.1 | BM15: N/A | BN15: N/A | BO15: The percentage of the total budget explicitly allocated to "moonshot" or 7-Generation projects. | BP15: 0 | BQ15: Capital as Sacred Energy | BR15: Water | BS15: Does our capital flow where it is needed, without expectation of return? | BT15: Unconditional Generosity Score | BU15: ↑ | BV15: 1 | BW15: 4.8 | BX15: N/A | BY15: N/A | BZ15: A 1-5 qualitative score. How much of our surplus capital is given away freely, as an act of pure service, to support coherence in the wider ecosystem? | CA15: 0
A16: Financial Capital (F1) | B16: Months of Runway | C16: Fire | D16: Are we adding to it? | E16: # of Funding Opportunities Pursued | F16: Band | G16: 0.4 | H16: 0 | I16: 1 | J16: 4 | K16: 10 | L16: The goal is not frantic activity, but consistent, high-quality effort. This plateau defines that healthy rhythm. | M16: =IF(AND(Octave_1_KPIs[[#This Row],[Value]] >= Octave_1_KPIs[[#This Row],[Healthy_Min]], Octave_1_KPIs[[#This Row],[Value]] <= Octave_1_KPIs[[#This Row],[Healthy_Max]]), 1, IF(Octave_1_KPIs[[#This Row],[Value]] < Octave_1_KPIs[[#This Row],[Healthy_Min]], MAX(0, (Octave_1_KPIs[[#This Row],[Value]] - Octave_1_KPIs[[#This Row],[Target_Min]]) / (Octave_1_KPIs[[#This Row],[Healthy_Min]] - Octave_1_KPIs[[#This Row],[Target_Min]])), MAX(0, 1 - (Octave_1_KPIs[[#This Row],[Value]] - Octave_1_KPIs[[#This Row],[Healthy_Max]]) / (Octave_1_KPIs[[#This Row],[Absolute_Max]] - Octave_1_KPIs[[#This Row],[Healthy_Max]])))) -> 0.4 | N16: Operational Efficiency | O16: Fire | P16: Are our operations profitable? | Q16: Operational ROI | R16: ↑ | S16: 1 | T16: 3 | U16: N/A | V16: N/A | W16: For every €1 spent on ops, the goal is to generate €3 in value. | X16: 0 | Y16: Stakeholder Value Distribution | Z16: Fire | AA16: Are we actively sharing our success? | AB16: % of Profit Shared/Bonus Allocation % with Team/Community | AC16: ↑ | AD16: 0 | AE16: 0.15 | AF16: N/A | AG16: N/A | AH16: The percentage of profits that are directly shared with the team, not just retained for shareholders. A direct measure of generosity. The ideal would be a significant, predefined percentage. | AI16: 0 | AJ16: Investment in Innovation | AK16: Fire | AL16: Are our creative investments generating a return? | AM16: Innovation ROI | AN16: ↑ | AO16: 0.5 | AP16: 3 | AQ16: N/A | AR16: N/A | AS16: For every €1 invested in innovation, the goal is to see a €3 return in value (financial, social, or systemic). | AT16: 0 | AU16: Financial Storytelling | AV16: Fire | AW16: Are we actively and beautifully crafting our financial narrative? | AX16: Quality of Annual/Impact Report | AY16: ↑ | AZ16: 1 | BA16: 4.8 | BB16: N/A | BC16: N/A | BD16: A 1-5 score. Is our primary financial report a masterpiece of clarity, beauty, and authentic storytelling? | BE16: 0 | BF16: Long-Term Capital Stewardship | BG16: Fire | BH16: Are our most visionary investments creating the most profound value? | BI16: Long-Term Regenerative ROI | BJ16: ↑ | BK16: 1 | BL16: 5 | BM16: N/A | BN16: N/A | BO16: A qualitative 1-5 score. Measures the systemic return (not just financial) on our most future-focused investments. | BP16: 0 | BQ16: Capital as Sacred Energy | BR16: Fire | BS16: Are we actively using our resources to seed impossible dreams? | BT16: Funding the "Unfundable" | BU16: Band | BV16: 0 | BW16: 1 | BX16: 1 | BY16: 2 | BZ16: The number of profoundly visionary but "commercially unviable" projects that we choose to sponsor each year. The ultimate act of faith in coherence. | CA16: 0
A17: Financial Capital (F1) | B17: Months of Runway | C17: Air | D17: Is it understood? | E17: Clarity Score of Financials to Stakeholders (1-5) | F17: ↑ | G17: 1.5 | H17: 1 | I17: 4.5 | J17: N/A | K17: N/A | L17: A simple 1-5 scale measuring the clarity and honesty of your financial storytelling. | M17: =MAX(0,MIN(1,(G17-H17)/(Octave_1_KPIs[[#This Row],[Healthy_Min]]-Octave_1_KPIs[[#This Row],[Target_Min]]))) -> 0.14285714 | N17: Operational Efficiency | O17: Air | P17: Are our processes documented? | Q17: Clarity of Financial SOPs | R17: ↑ | S17: 1 | T17: 4.5 | U17: N/A | V17: N/A | W17: Clear, written financial processes are the key to scalable stability. | X17: 0 | Y17: Stakeholder Value Distribution | Z17: Air | AA17: Is the 'why' behind our financial choices clear? | AB17: Clarity of Compensation Philosophy | AC17: ↑ | AD17: 1 | AE17: 4.5 | AF17: N/A | AG17: N/A | AH17: A score (1-5) on how well the principles of compensation are articulated and understood. | AI17: 0 | AJ17: Investment in Innovation | AK17: Air | AL17: Is our creative focus clear and well-defined? | AM17: Clarity of Innovation Thesis | AN17: ↑ | AO17: 1 | AP17: 4.8 | AQ17: N/A | AR17: N/A | AS17: How clearly have we defined the "big problems" we are trying to solve with our innovation? | AT17: 0 | AU17: Financial Storytelling | AV17: Air | AW17: Is our value-creation story simple and clear to all? | AX17: Clarity of Business Model Articulation | AY17: ↑ | AZ17: 1 | BA17: 4.8 | BB17: N/A | BC17: N/A | BD17: How easily can an outsider understand precisely how our organization creates and sustains financial value? | BE17: 0 | BF17: Long-Term Capital Stewardship | BG17: Air | BH17: Is our long-term financial story clear and compelling? | BI17: Clarity of Long-Term Financial Vision | BJ17: ↑ | BK17: 1 | BL17: 4.8 | BM17: N/A | BN17: N/A | BO17: How clearly can we articulate the financial architecture of the world we are trying to build? | BP17: 0 | BQ17: Capital as Sacred Energy | BR17: Air | BS17: Are we teaching the world a new, more beautiful story about money? | BT17: Articulation of a New Economic Paradigm | BU17: ↑ | BV17: 1 | BW17: 5 | BX17: N/A | BY17: N/A | BZ17: To what degree is our venture contributing to a global shift in the consciousness of capital? | CA17: 0
A18: Financial Capital (F1) | B18: Months of Runway | C18: Ether | D18: Is it aligned? | E18: Funding Alignment Index (1-5) | F18: ↑ | G18: 2.5 | H18: 1 | I18: 4.5 | J18: N/A | K18: N/A | L18: A 1-5 scale measuring the soul-level alignment of your capital. | M18: =MAX(0,MIN(1,(G18-H18)/(Octave_1_KPIs[[#This Row],[Healthy_Min]]-Octave_1_KPIs[[#This Row],[Target_Min]]))) -> 0.42857143 | N18: Operational Efficiency | O18: Ether | P18: Are efficiencies serving values? | Q18: Ethical Sourcing Savings | R18: ↑ | S18: 0 | T18: 0.1 | U18: N/A | V18: N/A | W18: Measures the % of cost savings achieved specifically through more ethical/sustainable choices. | X18: 0 | Y18: Stakeholder Value Distribution | Z18: Ether | AA18: Does our financial system feel like it cares? | AB18: "Financial Empathy" Score | AC18: ↑ | AD18: 1 | AE18: 4.5 | AF18: N/A | AG18: N/A | AH18: A qualitative score (1-5) from the team. Does the system feel like a supportive tool or a controlling mechanism? | AI18: 0 | AJ18: Investment in Innovation | AK18: Ether | AL18: Is our capital serving the highest creative good? | AM18: Alignment of Investments with Planetary Needs | AN18: ↑ | AO18: 1 | AP18: 4.5 | AQ18: N/A | AR18: N/A | AS18: A qualitative score. Are our R&D investments aimed at solving the planet's most profound dissonances? | AT18: 0 | AU18: Financial Storytelling | AV18: Ether | AW18: Does our financial story express our soul? | AX18: Integration of Purpose in Financials | AY18: ↑ | AZ18: 1 | BA18: 5 | BB18: N/A | BC18: N/A | BD18: To what degree do our financial reports go beyond numbers to tell the profound story of our purpose and impact? | BE18: 0 | BF18: Long-Term Capital Stewardship | BG18: Ether | BH18: Is our capital a direct expression of the future we choose? | BI18: Finance as an Act of Future-Building | BJ18: ↑ | BK18: 1 | BL18: 5 | BM18: N/A | BN18: N/A | BO18: The degree to which the venture's entire financial strategy is seen as the primary engine for creating a more coherent future. | BP18: 0 | BQ18: Capital as Sacred Energy | BR18: Ether | BS18: Is our financial flow a perfect mirror of the planet's lifeblood? | BT18: Capital and Life are Indistinguishable | BU18: ↑ | BV18: 1 | BW18: 5 | BX18: N/A | BY18: N/A | BZ18: The ultimate, Monad-level state. Net-Positive Financial Impact is the metric where every financial action demonstrably creates more life and vitality than it consumes. | CA18: 0
A19: Intellectual Capital (F2) | B19: IP Security & Formalization | C19: Earth | D19: Is it safe? | E19: Data Backup Frequency | F19: ↑ | G19: 0.5 | H19: 0 | I19: 1 | J19: N/A | K19: N/A | L19: Scored as: Daily=1, Weekly=0.7, Monthly=0.3, None=0. Measures the raw stability of your IP. | M19: =MAX(0,MIN(1,(G19-H19)/(Octave_1_KPIs[[#This Row],[Healthy_Min]]-Octave_1_KPIs[[#This Row],[Target_Min]]))) -> 0.5 | N19: Dev. Velocity & Quality | O19: Earth | P19: Is our product/IP robust? | Q19: Code Defect Rate | R19: ↓ | S19: High | T19: Low | U19: N/A | V19: N/A | W19: Lower is better. A direct measure of the structural integrity of the core creation. | X19: 0 | Y19: Collaborative Knowledge | Z19: Earth | AA19: Are we giving our knowledge back to the earth? | AB19: # of Active Co-Creative Projects | AC19: Band | AD19: 0 | AE19: 1 | AF19: 3 | AG19: 5 | AH19: A sustainable rhythm of building with our community, not just for them. | AI19: 0 | AJ19: Embodied Innovation | AK19: Earth | AL19: Are our ideas grounded in tangible reality? | AM19: # of Working Prototypes | AN19: Band | AO19: 0 | AP19: 1 | AQ19: 3 | AR19: 5 | AS19: The sustainable rhythm of turning ideas into working models. Focus on quality over quantity. | AT19: 0 | AU19: Knowledge Sharing & Influence | AV19: Earth | AW19: Is our core knowledge grounded in tangible, citable artifacts? | AX19: # of Published White Papers/Articles | AY19: Band | AZ19: 0 | BA19: 1 | BB19: 3 | BC19: 5 | BD19: A sustainable rhythm of turning internal knowledge into public, referenceable assets per quarter. | BE19: 0 | BF19: Evolution of Knowledge | BG19: Earth | BH19: Is our intellectual capital grounded in a long-term plan? | BI19: Long-Term IP Roadmap | BJ19: ↑ | BK19: 0 | BL19: 1 | BM19: N/A | BN19: N/A | BO19: A binary milestone. Do we have a clear, written roadmap for the evolution of our core models and IP over the next 5-10 years? | BP19: 0 | BQ19: Knowledge as a Living Field | BR19: Earth | BS19: Is our core IP grounded in a structure that can live beyond us? | BT19: The Model as a Living, Evolving Entity | BU19: ↑ | BV19: 1 | BW19: 4.8 | BX19: N/A | BY19: N/A | BZ19: A 1-5 score on the health of the open-source community, foundation, or other structure designed to steward the model's evolution for generations. | CA19: 0
A20: Intellectual Capital (F2) | B20: IP Security & Formalization | C20: Water | D20: Is it moving? | E20: Weekly Progress on Thesis (%) | F20: ↑ | G20: 0.1 | H20: 0 | I20: 0.1 | J20: N/A | K20: N/A | L20: Measures the consistent, flowing output of IP. 10% progress per week is a powerful, sustainable goal. | M20: =MAX(0,MIN(1,(G20-H20)/(Octave_1_KPIs[[#This Row],[Healthy_Min]]-Octave_1_KPIs[[#This Row],[Target_Min]]))) -> 1 | N20: Dev. Velocity & Quality | O20: Water | P20: Are we building smoothly? | Q20: Dev. Cycle Time | R20: ↓ | S20: 30d | T20: 7d | U20: N/A | V20: N/A | W20: The speed of the idea-to-reality flow. A 7-day cycle is world-class for agile development. | X20: 0 | Y20: Collaborative Knowledge | Z20: Water | AA20: Is there a flow of ideas between us and others? | AB20: Openness to External Feedback | AC20: ↑ | AD20: 1 | AE20: 4.5 | AF20: N/A | AG20: N/A | AH20: A 1-5 score measuring how well the team listens to and integrates ideas and critiques from its ecosystem. | AI20: 0 | AJ20: Embodied Innovation | AK20: Water | AL20: What is the speed of our creative flow? | AM20: Idea-to-Prototype Cycle Time | AN20: ↓ | AO20: 90d | AP20: 14d | AQ20: N/A | AR20: N/A | AS20: The time it takes to turn a well-defined idea into a testable prototype. | AT20: 0 | AU20: Knowledge Sharing & Influence | AV20: Water | AW20: Is our knowledge flowing into and nourishing our ecosystem? | AX20: Community Engagement with Content | AY20: ↑ | AZ20: Low | BA20: High | BB20: N/A | BC20: N/A | BD20: Measures the shares, comments, and depth of discussion generated by our published knowledge. | BE20: 0 | BF20: Evolution of Knowledge | BG20: Water | BH20: Is our organization itself a rapid learning system? | BI20: "Learning Velocity" of the System | BJ20: ↑ | BK20: 1 | BL20: 4.5 | BM20: N/A | BN20: N/A | BO20: A 1-5 score measuring the speed and efficiency with which the organization unlearns old paradigms and integrates new knowledge. | BP20: 0 | BQ20: Knowledge as a Living Field | BR20: Water | BS20: Does the wisdom of the model flow to where it is needed? | BT20: Effortless Transmission of Wisdom | BU20: ↑ | BV20: 1 | BW20: 4.5 | BX20: N/A | BY20: N/A | BZ20: A qualitative score. How easily and gracefully are new people able to learn, understand, and apply the core principles? | CA20: 0
A21: Intellectual Capital (F2) | B21: IP Security & Formalization | C21: Fire | D21: Is it being created? | E21: Hours Logged on IP Dev | F21: Band | G21: 21 | H21: 0 | I21: 10 | J21: 15 | K21: 25 | L21: The energy input for IP creation. A healthy, sustainable plateau of focused work. | M21: =IF(AND(Octave_1_KPIs[[#This Row],[Value]] >= Octave_1_KPIs[[#This Row],[Healthy_Min]], Octave_1_KPIs[[#This Row],[Value]] <= Octave_1_KPIs[[#This Row],[Healthy_Max]]), 1, IF(Octave_1_KPIs[[#This Row],[Value]] < Octave_1_KPIs[[#This Row],[Healthy_Min]], MAX(0, (Octave_1_KPIs[[#This Row],[Value]] - Octave_1_KPIs[[#This Row],[Target_Min]]) / (Octave_1_KPIs[[#This Row],[Healthy_Min]] - Octave_1_KPIs[[#This Row],[Target_Min]])), MAX(0, 1 - (Octave_1_KPIs[[#This Row],[Value]] - Octave_1_KPIs[[#This Row],[Healthy_Max]]) / (Octave_1_KPIs[[#This Row],[Absolute_Max]] - Octave_1_KPIs[[#This Row],[Healthy_Max]])))) -> 0.4 | N21: Dev. Velocity & Quality | O21: Fire | P21: Are we making progress? | Q21: # Features/Chapters Completed | R21: Band | S21: 0 | T21: 1 | U21: 3 | V21: 5 | W21: Quality over quantity. A sustainable rhythm of meaningful, completed work. | X21: 0 | Y21: Collaborative Knowledge | Z21: Fire | AA21: Are we actively creating shared wins? | AB21: # of Jointly Authored Papers/Patents | AC21: Band | AD21: 1 | AE21: 2 | AF21: 4 | AG21: 8 | AH21: A sustainable rhythm of creating formal, shared intellectual property. | AI21: 0 | AJ21: Embodied Innovation | AK21: Fire | AL21: Are we actively formalizing our creations? | AM21: Patent / Open Source Contribution Rate | AN21: Band | AO21: 0 | AP21: 1 | AQ21: 2 | AR21: 4 | AS21: A sustainable rhythm of either protecting unique IP or gifting it to the commons per year. | AT21: 0 | AU21: Knowledge Sharing & Influence | AV21: Fire | AW21: Are we actively teaching what we know? | AX21: # of Workshops/Talks Delivered | AY21: Band | AZ21: 0 | BA21: 1 | BB21: 4 | BC21: 8 | BD21: A healthy rhythm of actively sharing our expertise and IP with the world per quarter. | BE21: 0 | BF21: Evolution of Knowledge | BG21: Fire | BH21: Are we actively generating truly novel ideas? | BI21: # of Paradigm-Shifting Insights | BJ21: Band | BK21: 0 | BL21: 1 | BM21: 2 | BN21: 3 | BO21: The number of core, "game-changing" insights generated and documented per year. A measure of true creative genius. | BP21: 0 | BQ21: Knowledge as a Living Field | BR21: Fire | BS21: Are we actively and completely giving our genius away? | BT21: Radical Open-Sourcing of Core IP | BU21: ↑ | BV21: 0 | BW21: 1 | BX21: N/A | BY21: N/A | BZ21: The percentage of the venture's core, non-proprietary IP that is freely available to the world. | CA21: 0
A22: Intellectual Capital (F2) | B22: IP Security & Formalization | C22: Air | D22: Is it documented? | E22: Clarity of Core Model Docs | F22: ↑ | G22: 2 | H22: 1 | I22: 4.5 | J22: N/A | K22: N/A | L22: A 1-5 scale. How well is the genius of the model actually documented? | M22: =MAX(0,MIN(1,(G22-H22)/(Octave_1_KPIs[[#This Row],[Healthy_Min]]-Octave_1_KPIs[[#This Row],[Target_Min]]))) -> 0.28571429 | N22: Dev. Velocity & Quality | O22: Air | P22: Is our roadmap clear? | Q22: Clarity of Product Roadmap | R22: ↑ | S22: 1 | T22: 4.5 | U22: N/A | V22: N/A | W22: A clear, shared understanding of what is being built next. | X22: 0 | Y22: Collaborative Knowledge | Z22: Air | AA22: Are the rules of collaboration clear and fair? | AB22: Clarity of IP Attribution Policies | AC22: ↑ | AD22: 1 | AE22: 5 | AF22: N/A | AG22: N/A | AH22: A score (1-5). Clear, fair agreements are the air a healthy collaboration breathes. | AI22: 0 | AJ22: Embodied Innovation | AK22: Air | AL22: Can others understand and build upon our creations? | AM22: Clarity of Technical Documentation | AN22: ↑ | AO22: 1 | AP22: 4.5 | AQ22: N/A | AR22: N/A | AS22: The clarity and quality of the documentation that accompanies each prototype or innovation. | AT22: 0 | AU22: Knowledge Sharing & Influence | AV22: Air | AW22: Is our complex genius expressed with simple elegance? | AX22: "Simplicity of Explanation" Score | AY22: ↑ | AZ22: 1 | BA22: 4.8 | BB22: N/A | BC22: N/A | BD22: A 1-5 score. How well can we explain the most complex parts of our model to a brilliant novice? | BE22: 0 | BF22: Evolution of Knowledge | BG22: Air | BH22: Is the picture of the future we are building clear to all? | BI22: Clarity of Future Vision | BJ22: ↑ | BK22: 1 | BL22: 4.8 | BM22: N/A | BN22: N/A | BO22: How vividly and precisely can the team articulate the world that this IP will help create? | BP22: 0 | BQ22: Knowledge as a Living Field | BR22: Air | BS22: Is our deepest wisdom expressed with the clarity of a child? | BT22: Simplicity on the Far Side of Complexity | BU22: ↑ | BV22: 1 | BW22: 5 | BX22: N/A | BY22: N/A | BZ22: Can we explain the entire, magnificent model in a few, simple, self-evident truths? | CA22: 0
A23: Intellectual Capital (F2) | B23: IP Security & Formalization | C23: Ether | D23: Is it ethical? | E23: Ethical IP Score | F23: ↑ | G23: 4.5 | H23: 1 | I23: 4.5 | J23: N/A | K23: N/A | L23: Does the IP itself serve a coherent and ethical purpose? | M23: =MAX(0,MIN(1,(G23-H23)/(Octave_1_KPIs[[#This Row],[Healthy_Min]]-Octave_1_KPIs[[#This Row],[Target_Min]]))) -> 1 | N23: Dev. Velocity & Quality | O23: Ether | P23: Is our process coherent? | Q23: "Felt Sense of Flow" | R23: ↑ | S23: 1 | T23: 4.5 | U23: N/A | V23: N/A | W23: The team's felt experience. Does the work feel like a smooth dance or a frustrating struggle? | X23: 0 | Y23: Collaborative Knowledge | Z23: Ether | AA23: Do we see our knowledge as a gift to be shared? | AB23: "Knowledge as a Commons" Mentality | AC23: ↑ | AD23: 1 | AE23: 5 | AF23: 4 | AG23: 5 | AH23: A score (1-5). The ultimate purpose behind collaborative IP. | AI23: 0 | AJ23: Embodied Innovation | AK23: Ether | AL23: Is our creation a work of art? | AM23: Beauty & Elegance of Design | AN23: ↑ | AO23: 1 | AP23: 4.8 | AQ23: N/A | AR23: N/A | AS23: A qualitative score. Does the design of our innovation (code, thesis, etc.) possess a sense of beauty and coherent elegance? | AT23: 0 | AU23: Knowledge Sharing & Influence | AV23: Ether | AW23: Is our IP becoming a standard for our field? | AX23: Influence on the Wider Discourse | AY23: ↑ | AZ23: 1 | BA23: 4 | BB23: N/A | BC23: N/A | BD23: A qualitative score. Are other thinkers, leaders, and organizations beginning to adopt our language and frameworks? | BE23: 0 | BF23: Evolution of Knowledge | BG23: Ether | BH23: Is our knowledge for the good of future generations? | BI23: Knowledge in Service of Planetary Evolution | BJ23: ↑ | BK23: 1 | BL23: 5 | BM23: N/A | BN23: N/A | BO23: The degree to which our entire R&D and IP strategy is consciously aimed at solving the deepest challenges of tomorrow. | BP23: 0 | BQ23: Knowledge as a Living Field | BR23: Ether | BS23: Is our IP a direct instrument for the planet's awakening? | BT23: Knowledge Serves Planetary Consciousness | BU23: ↑ | BV23: 1 | BW23: 5 | BX23: N/A | BY23: N/A | BZ23: The ultimate purpose. Does our knowledge act as a catalyst for a global shift in consciousness? | CA23: 0
A24: Human Capital (F3) | B24: Founder Sustainability | C24: Earth | D24: Are you rested? | E24: Average Hours of Sleep | F24: Band | G24: 8 | H24: 4 | I24: 7 | J24: 8.5 | K24: 10 | L24: The ultimate foundation of founder stability. | M24: =IF(AND(Octave_1_KPIs[[#This Row],[Value]] >= Octave_1_KPIs[[#This Row],[Healthy_Min]], Octave_1_KPIs[[#This Row],[Value]] <= Octave_1_KPIs[[#This Row],[Healthy_Max]]), 1, IF(Octave_1_KPIs[[#This Row],[Value]] < Octave_1_KPIs[[#This Row],[Healthy_Min]], MAX(0, (Octave_1_KPIs[[#This Row],[Value]] - Octave_1_KPIs[[#This Row],[Target_Min]]) / (Octave_1_KPIs[[#This Row],[Healthy_Min]] - Octave_1_KPIs[[#This Row],[Target_Min]])), MAX(0, 1 - (Octave_1_KPIs[[#This Row],[Value]] - Octave_1_KPIs[[#This Row],[Healthy_Max]]) / (Octave_1_KPIs[[#This Row],[Absolute_Max]] - Octave_1_KPIs[[#This Row],[Healthy_Max]])))) -> 1 | N24: Role Clarity & Team Stability | O24: Earth | P24: Do people know their roles? | Q24: Role Clarity Score | R24: ↑ | S24: 1 | T24: 4.5 | U24: N/A | V24: N/A | W24: A stable team is built on a foundation of clear roles and responsibilities. | X24: 0 | Y24: Team Cohesion & Psych./Safety | Z24: Earth | AA24: Is our team a safe ground for authenticity? | AB24: Psychological Safety Score | AC24: ↑ | AD24: 1 | AE24: 4.5 | AF24: N/A | AG24: N/A | AH24: A survey score (1-5). The absolute, non-negotiable bedrock of any high-performing, coherent team. | AI24: 0 | AJ24: Creative Culture | AK24: Earth | AL24: Is it safe to be a creative genius here? | AM24: Psychological Safety for "Crazy Ideas" | AN24: ↑ | AO24: 1 | AP24: 4.8 | AQ24: N/A | AR24: N/A | AS24: A survey. The bedrock of a creative culture is safety from ridicule for proposing bold, non-obvious ideas. | AT24: 0 | AU24: Cultural Storytelling | AV24: Earth | AW24: Is every team member grounded in our shared story? | AX24: Team's Ability to Articulate the "Why" | AY24: ↑ | AZ24: 0.75 | BA24: 0.95 | BB24: N/A | BC24: N/A | BD24: The % of the team that can powerfully and accurately tell the organization's origin story and purpose. | BE24: 0 | BF24: Long-Term Cultural Viability | BG24: Earth | BH24: Is our culture grounded enough to outlive its founders? | BI24: Succession Planning & Mentorship | BJ24: ↑ | BK24: 1 | BL24: 4.5 | BM24: N/A | BN24: N/A | BO24: A 1-5 score on the health of mentorship programs and the formal process for developing the next generation of leaders. | BP24: 0 | BQ24: Consciousness as Capital | BR24: Earth | BS24: Is our way of being grounded in a real, transmittable practice? | BT24: A Lineage of Mastery | BU24: ↑ | BV24: 0 | BW24: 1 | BX24: N/A | BY24: N/A | BZ24: A milestone. Has the internal culture and practice become a formal "school" or "lineage" that can train others in the art of coherence? | CA24: 0
A25: Human Capital (F3) | B25: Founder Sustainability | C25: Water | D25: Are you energized? | E25: Founder Energy Level (1-10) | F25: Band | G25: 7.5 | H25: 5 | I25: 7 | J25: 8.5 | K25: 10 | L25: The core "Plateau of Coherence" metric we have perfected. | M25: =IF(AND(Octave_1_KPIs[[#This Row],[Value]] >= Octave_1_KPIs[[#This Row],[Healthy_Min]], Octave_1_KPIs[[#This Row],[Value]] <= Octave_1_KPIs[[#This Row],[Healthy_Max]]), 1, IF(Octave_1_KPIs[[#This Row],[Value]] < Octave_1_KPIs[[#This Row],[Healthy_Min]], MAX(0, (Octave_1_KPIs[[#This Row],[Value]] - Octave_1_KPIs[[#This Row],[Target_Min]]) / (Octave_1_KPIs[[#This Row],[Healthy_Min]] - Octave_1_KPIs[[#This Row],[Target_Min]])), MAX(0, 1 - (Octave_1_KPIs[[#This Row],[Value]] - Octave_1_KPIs[[#This Row],[Healthy_Max]]) / (Octave_1_KPIs[[#This Row],[Absolute_Max]] - Octave_1_KPIs[[#This Row],[Healthy_Max]])))) -> 1 | N25: Role Clarity & Team Stability | O25: Water | P25: Is information flowing well? | Q25: Internal Comm. Efficiency | R25: ↑ | S25: 1 | T25: 4.5 | U25: N/A | V25: N/A | W25: Measures the quality of the "connective tissue" within the team. | X25: 0 | Y25: Team Cohesion & Psych./Safety | Z25: Water | AA25: Is there a strong emotional bond? | AB25: Team Cohesion / eNPS | AC25: ↑ | AD25: 0 | AE25: 70 | AF25: N/A | AG25: N/A | AH25: The classic eNPS score, measuring team morale and loyalty. | AI25: 0 | AJ25: Creative Culture | AK25: Water | AL25: Does our work environment enable deep creative flow? | AM25: "Flow State" Score | AN25: ↑ | AO25: 1 | AP25: 4.5 | AQ25: N/A | AR25: N/A | AS25: A team survey on the ability to achieve uninterrupted, deep focus. | AT25: 0 | AU25: Cultural Storytelling | AV25: Water | AW25: Do our people feel like authentic, proud ambassadors? | AX25: Employee Brand Ambassadorship | AY25: ↑ | AZ25: 0 | BA25: 70 | BB25: N/A | BC25: N/A | BD25: An "eNPS" style score. How likely are our team members to recommend our organization as a place of work and inspiration? | BE25: 0 | BF25: Long-Term Cultural Viability | BG25: Water | BH25: Is there a healthy flow of knowledge from old to new? | BI25: Inter-Generational Flow of Wisdom | BJ25: ↑ | BK25: 1 | BL25: 4.5 | BM25: N/A | BN25: N/A | BO25: How well is tacit knowledge and deep wisdom passed between senior and junior members of the team? | BP25: 0 | BQ25: Consciousness as Capital | BR25: Water | BS25: Is the emotional field of our team one of deep, resonant peace? | BT25: Collective State of Presence | BU25: ↑ | BV25: 1 | BW25: 4.8 | BX25: N/A | BY25: N/A | BZ25: A qualitative measure of the team's shared state of consciousness. Can be measured through group meditation coherence or deep intuitive sensing. | CA25: 0
A26: Human Capital (F3) | B26: Founder Sustainability | C26: Fire | D26: Are you growing? | E26: Hours Spent in Learning/Development | F26: Band | G26: 7 | H26: 0 | I26: 2 | J26: 5 | K26: 10 | L26: Measures the act of "sharpening the saw." Too little is stagnation, too much is "pro-crash-tination." | M26: =IF(AND(Octave_1_KPIs[[#This Row],[Value]] >= Octave_1_KPIs[[#This Row],[Healthy_Min]], Octave_1_KPIs[[#This Row],[Value]] <= Octave_1_KPIs[[#This Row],[Healthy_Max]]), 1, IF(Octave_1_KPIs[[#This Row],[Value]] < Octave_1_KPIs[[#This Row],[Healthy_Min]], MAX(0, (Octave_1_KPIs[[#This Row],[Value]] - Octave_1_KPIs[[#This Row],[Target_Min]]) / (Octave_1_KPIs[[#This Row],[Healthy_Min]] - Octave_1_KPIs[[#This Row],[Target_Min]])), MAX(0, 1 - (Octave_1_KPIs[[#This Row],[Value]] - Octave_1_KPIs[[#This Row],[Healthy_Max]]) / (Octave_1_KPIs[[#This Row],[Absolute_Max]] - Octave_1_KPIs[[#This Row],[Healthy_Max]])))) -> 0.6 | N26: Role Clarity & Team Stability | O26: Fire | P26: Are we retaining our talent? | Q26: Employee Retention Rate | R26: ↑ | S26: 0.7 | T26: 0.95 | U26: N/A | V26: N/A | W26: The ultimate measure of a healthy, stable culture. | X26: 0 | Y26: Team Cohesion & Psych./Safety | Z26: Fire | AA26: Do we actively and skillfully heal our dissonance/disagreements? | AB26: Conflict Resolution Time/Effectiveness | AC26: ↑ | AD26: 14d | AE26: 1d | AF26: N/A | AG26: N/A | AH26: The speed and efficiency with which interpersonal conflicts are addressed and resolved. | AI26: 0 | AJ26: Creative Culture | AK26: Fire | AL26: Do we actively make space for pure creation? | AM26: # of "Hack Days" or Creative Sprints | AN26: Band | AO26: 0 | AP26: 1 | AQ26: 2 | AR26: 4 | AS26: A healthy rhythm of dedicated, playful, creative sessions per quarter. | AT26: 0 | AU26: Cultural Storytelling | AV26: Fire | AW26: Are we actively sharing the human reality of our culture? | AX26: # of "Behind the Scenes" Cultural Stories | AY26: Band | AZ26: 0 | BA26: 2 | BB26: 5 | BC26: 10 | BD26: A sustainable rhythm of authentic, internal storytelling made public per month. | BE26: 0 | BF26: Long-Term Cultural Viability | BG26: Fire | BH26: Are we actively forging the leaders of tomorrow? | BI26: Leadership Development Programs | BJ26: Band | BK26: 0 | BL26: 1 | BM26: 2 | BN26: 3 | BO26: A sustainable rhythm of formal programs designed to cultivate the next wave of coherent leadership. | BP26: 0 | BQ26: Consciousness as Capital | BR26: Fire | BS26: Does the very presence of our team create a healing ripple in the world? | BT26: Team as a Source of Global Awakening | BU26: ↑ | BV26: 1 | BW26: 4.5 | BX26: N/A | BY26: N/A | BZ26: The degree to which team members, in all their interactions, act as ambassadors of coherence and inspiration to the wider world. | CA26: 0
A27: Human Capital (F3) | B27: Founder Sustainability | C27: Air | D27: Are you self-aware? | E27: Frequency of Self-Reflection/Journaling | F27: ↑ | G27: 0.5 | H27: 0 | I27: 1 | J27: N/A | K27: N/A | L27: A habit score: Daily=1, Weekly=0.5. Measures the clarity of self-awareness. | M27: =MAX(0,MIN(1,(G27-H27)/(Octave_1_KPIs[[#This Row],[Healthy_Min]]-Octave_1_KPIs[[#This Row],[Target_Min]]))) -> 0.5 | N27: Role Clarity & Team Stability | O27: Air | P27: Are our structures documented? | Q27: Clarity of Org. Chart | R27: ↑ | S27: 1 | T27: 4.5 | U27: N/A | V27: N/A | W27: A clear, visible representation of the team's structure. | X27: 0 | Y27: Team Cohesion & Psych./Safety | Z27: Air | AA27: Is our communication honest, kind, and useful? | AB27: Quality of Peer-to-Peer Feedback | AC27: ↑ | AD27: 1 | AE27: 4.5 | AF27: N/A | AG27: N/A | AH27: A score (1-5). The clarity and quality of the air between people. | AI27: 0 | AJ27: Creative Culture | AK27: Air | AL27: Do ideas flow freely between different minds? | AM27: Cross-Pollination of Ideas | AN27: ↑ | AO27: 1 | AP27: 4.5 | AQ27: N/A | AR27: N/A | AS27: A qualitative score for the quality of brainstorming and interdisciplinary collaboration. | AT27: 0 | AU27: Cultural Storytelling | AV27: Air | AW27: Is our "way of being" a clear and attractive offering? | AX27: Clarity of "Culture as a Product" | AY27: ↑ | AZ27: 1 | BA27: 4.5 | BB27: N/A | BC27: N/A | BD27: How clearly do we articulate our culture as a key differentiator in our recruitment and branding? | BE27: 0 | BF27: Long-Term Cultural Viability | BG27: Air | BH27: Is the "soul" of our future culture clear? | BI27: Clarity of Long-Term Cultural Vision | BJ27: ↑ | BK27: 1 | BL27: 4.8 | BM27: N/A | BN27: N/A | BO27: Do we have a clear, shared vision for the kind of culture we want to have in 10, 20, 50 years? | BP27: 0 | BQ27: Consciousness as Capital | BR27: Air | BS27: Is our internal communication so clear it feels telepathic? | BT27: "Telepathic" Communication Clarity | BU27: ↑ | BV27: 1 | BW27: 4.5 | BX27: N/A | BY27: N/A | BZ27: (From "grokking"). A 1-5 score on the team's ability to understand each other's intent and meaning with minimal friction and maximum depth. | CA27: 0
A28: Human Capital (F3) | B28: Founder Sustainability | C28: Ether | D28: Are you joyful? | E28: "Joy in the Work" Score (1-5) | F28: ↑ | G28: 4 | H28: 1 | I28: 4.5 | J28: N/A | K28: N/A | L28: The ultimate measure of purpose. Are you still connected to the soul of the work? | M28: =MAX(0,MIN(1,(G28-H28)/(Octave_1_KPIs[[#This Row],[Healthy_Min]]-Octave_1_KPIs[[#This Row],[Target_Min]]))) -> 0.85714286 | N28: Role Clarity & Team Stability | O28: Ether | P28: Does our structure feel fair? | Q28: Perceived Fairness of Roles | R28: ↑ | S28: 1 | T28: 4.5 | U28: N/A | V28: N/A | W28: The soul of the structure. Do people feel empowered and respected? | X28: 0 | Y28: Team Cohesion & Psych./Safety | Z28: Ether | AA28: Do our people feel they are truly part of the whole? | AB28: "Sense of Belonging" Score | AC28: ↑ | AD28: 5 | AE28: 9.8 | AF28: N/A | AG28: N/A | AH28: A poll (1-10). The ultimate measure of a deeply resonant culture. | AI28: 0 | AJ28: Creative Culture | AK28: Ether | AL28: Is it safe for our experiments to fail? | AM28: Celebration of "Noble Failures" | AN28: ↑ | AO28: 1 | AP28: 5 | AQ28: N/A | AR28: N/A | AS28: How well does the culture celebrate the learning that comes from experiments that don't "succeed"? This is the soul of innovation. | AT28: 0 | AU28: Cultural Storytelling | AV28: Ether | AW28: Does our story inspire others to build better cultures? | AX28: Inspirational Impact of our Culture | AY28: ↑ | AZ28: 1 | BA28: 4.5 | BB28: N/A | BC28: N/A | BD28: A qualitative score. Are other organizations looking to us as a model for a coherent and life-affirming culture? | BE28: 0 | BF28: Long-Term Cultural Viability | BG28: Ether | BH28: Is our way of being our greatest gift to the future? | BI28: Culture as a Living Legacy | BJ28: ↑ | BK28: 1 | BL28: 5 | BM28: N/A | BN28: N/A | BO28: The degree to which the culture itself is viewed as the most important and enduring "product" the organization creates. | BP28: 0 | BQ28: Consciousness as Capital | BR28: Ether | BS28: Do we experience the truth that the individual is the collective, and vice-versa? | BT28: Sense of Oneness | BU28: ↑ | BV28: 1 | BW28: 5 | BX28: N/A | BY28: N/A | BZ28: The ultimate state of a coherent culture, where all sense of separation dissolves into a shared, unified field of being. | CA28: 0
A29: Structural Capital (F4) | B29: Governance Foundation Integrity | C29: Earth | D29: Is it legal? | E29: % of Legal Registration Complete | F29: ↑ | G29: 1 | H29: 0 | I29: 1 | J29: N/A | K29: N/A | L29: A binary state of being. The legal foundation must be 100% solid. | M29: =MAX(0,MIN(1,(G29-H29)/(Octave_1_KPIs[[#This Row],[Healthy_Min]]-Octave_1_KPIs[[#This Row],[Target_Min]]))) -> 1 | N29: Process Resilience | O29: Earth | P29: Can our systems handle a shock? | Q29: Process Resilience Score | R29: ↑ | S29: 1 | T29: 4.5 | U29: N/A | V29: N/A | W29: A score from a simulated "stress test" of core processes. | X29: 0 | Y29: Participatory Governance | Z29: Earth | AA29: Are our people grounded in the structure and fairness? | AB29: Perceived Fairness of Structure | AC29: ↑ | AD29: 1 | AE29: 4.5 | AF29: N/A | AG29: N/A | AH29: A percentage. What % of the team actively participates in governance decisions? | AI29: 0 | AJ29: Adaptive Governance | AK29: Earth | AL29: Does our structure provide a stable ground for creativity? | AM29: Governance as a Stable Platform | AN29: ↑ | AO29: 1 | AP29: 4.5 | AQ29: N/A | AR29: N/A | AS29: Does the governance feel like a solid launchpad, not a shaky boat? | AT29: 0 | AU29: Governance Transparency | AV29: Earth | AW29: Is our structure grounded in radical transparency? | AX29: % of Governance Docs Made Public | AY29: ↑ | AZ29: 0.1 | BA29: 0.75 | BB29: N/A | BC29: N/A | BD29: What percentage of our core, non-proprietary governance documents are available for the public to see? | BE29: 0 | BF29: Evolutionary Governance | BG29: Earth | BH29: Is our core governance built to last? | BI29: Constitutional Stability | BJ29: ↑ | BK29: 1 | BL29: 5 | BM29: N/A | BN29: N/A | BO29: A 1-5 score on the resilience and timelessness of the venture's core "constitutional" documents and principles. | BP29: 0 | BQ29: Governance as Emergent Order | BR29: Earth | BS29: Is our structure so perfected it has become an invisible, supportive field? | BT29: Organization as a "Field of Coherence" | BU29: ↑ | BV29: 1 | BW29: 5 | BX29: N/A | BY29: N/A | BZ29: Does the organization feel less like a company and more like a naturally occurring ecosystem or field of energy? | CA29: 0
A30: Structural Capital (F4) | B30: Governance Foundation Integrity | C30: Water | D30: Are decisions clear? | E30: Decision Protocol Clarity (1-5) | F30: ↑ | G30: 1 | H30: 1 | I30: 4 | J30: N/A | K30: N/A | L30: A 1-5 scale. At the survival stage, a clear and "good enough" process (a 4) is the ideal for maintaining agility. | M30: =MAX(0,MIN(1,(G30-H30)/(Octave_1_KPIs[[#This Row],[Healthy_Min]]-Octave_1_KPIs[[#This Row],[Target_Min]]))) -> 0 | N30: Process Resilience | O30: Water | P30: Are our processes efficient? | Q30: Avg. Process Completion Time | R30: ↓ | S30: High | T30: Low | U30: N/A | V30: N/A | W30: The speed and flow of the organizational "metabolism." | X30: 0 | Y30: Participatory Governance | Z30: Water | AA30: Does every voice have a channel to flow? | AB30: Employee Participation in Governance | AC30: ↑ | AD30: 0.1 | AE30: 0.75 | AF30: N/A | AG30: N/A | AH30: The percentage of the team that actively participates in key governance decisions or forums. | AI30: 0 | AJ30: Adaptive Governance | AK30: Water | AL30: Can our rules change as fast as we learn? | AM30: Speed of Adapting Policies | AN30: ↓ | AO30: 30d | AP30: 3d | AQ30: N/A | AR30: N/A | AS30: The time it takes for the governance system to adapt its own rules based on new information. | AT30: 0 | AU30: Governance Transparency | AV30: Water | AW30: Does the flow of our decisions feel clear and honest? | AX30: Perceived Transparency of Decision Flow | AY30: ↑ | AZ30: 1 | BA30: 4.5 | BB30: N/A | BC30: N/A | BD30: An external stakeholder survey. Do people trust the process by which we make choices? | BE30: 0 | BF30: Evolutionary Governance | BG30: Water | BH30: Can our governance model itself learn and evolve? | BI30: Speed of Governance Evolution | BJ30: ↓ | BK30: 5y | BL30: 1y | BM30: N/A | BN30: N/A | BO30: The time it takes for the organization to make a fundamental, structural change to its own governance model based on new learning. | BP30: 0 | BQ30: Governance as Emergent Order | BR30: Water | BS30: Does the right thing just happen, without needing to be managed? | BT30: Spontaneous, Synergistic Action | BU30: ↑ | BV30: 1 | BW30: 4.8 | BX30: N/A | BY30: N/A | BZ30: The frequency with which complex, multi-part actions self-organize and are executed flawlessly without top-down control. | CA30: 0
A31: Structural Capital (F4) | B31: Governance Foundation Integrity | C31: Fire | D31: Are we accountable? | E31: # of Documented "Value Alignment Checks" | F31: ↑ | G31: 0 | H31: 0 | I31: 1 | J31: N/A | K31: N/A | L31: The habit of integrity. We aim to check 100% of key strategic decisions against our values. | M31: =MAX(0,MIN(1,(G31-H31)/(Octave_1_KPIs[[#This Row],[Healthy_Min]]-Octave_1_KPIs[[#This Row],[Target_Min]]))) -> 0 | N31: Process Resilience | O31: Fire | P31: Are we improving? | Q31: # Process Improvements | R31: Band | S31: 0 | T31: 1 | U31: 3 | V31: 5 | W31: A sustainable rhythm of conscious evolution, not endless-tinkering. | X31: 0 | Y31: Participatory Governance | Z31: Fire | AA31: Are we actively seeking the collective wisdom? | AB31: # of Votes/Polls on Key Decisions | AC31: Band | AD31: 0 | AE31: 1 | AF31: 5 | AG31: 10 | AH31: A sustainable rhythm of participatory decision-making per month. | AI31: 0 | AJ31: Adaptive Governance | AK31: Fire | AL31: Can we safely break rules for the sake of a good idea? | AM31: # of "Amnesty for Innovation" Processes | AN31: ↑ | AO31: 0 | AP31: 1 | AQ31: N/A | AR31: N/A | AS31: Is there a formal, trusted process for allowing teams to temporarily suspend a rule for a well-defined experiment? | AT31: 0 | AU31: Governance Transparency | AV31: Fire | AW31: Are we actively communicating how we govern? | AX31: # of Public Statements on Governance | AY31: Band | AZ31: 0 | BA31: 1 | BB31: 2 | BC31: 4 | BD31: A healthy rhythm of blog posts or statements per year explaining key governance choices. | BE31: 0 | BF31: Evolutionary Governance | BG31: Fire | BH31: Are we actively stress-testing our own power structures? | BI31: # of Governance Experiments | BJ31: Band | BK31: 0 | BL31: 1 | BM31: 2 | BN31: 3 | BO31: A rhythm of consciously running experiments with new forms of decision-making, ownership, and power. | BP31: 0 | BQ31: Governance as Emergent Order | BR31: Fire | BS31: Are we actively witnessing the magic that our coherence invites? | BT31: # of Miracles or Synchronicities Logged | BU31: ↑ | BV31: 0 | BW31: High | BX31: N/A | BY31: N/A | BZ31: A log of "impossible" or deeply meaningful coincidences and breakthroughs that occur as a result of the system's high state of resonance. | CA31: 0
A32: Structural Capital (F4) | B32: Governance Foundation Integrity | C32: Air | D32: It is written? | E32: % of Core Governance Docs Drafted | F32: ↑ | G32: 0.1 | H32: 0 | I32: 1 | J32: N/A | K32: N/A | L32: Project completion. The foundational "constitution" of the venture must be fully articulated. | M32: =MAX(0,MIN(1,(G32-H32)/(Octave_1_KPIs[[#This Row],[Healthy_Min]]-Octave_1_KPIs[[#This Row],[Target_Min]]))) -> 0.1 | N32: Process Resilience | O32: Air | P32: Are our processes mapped? | Q32: % of Core Processes Mapped | R32: ↑ | S32: 0 | T32: 1 | U32: N/A | V32: N/A | W32: The clarity that comes from making the invisible workflows visible. | X32: 0 | Y32: Participatory Governance | Z32: Air | AA32: Is it clear and safe to challenge the structure? | AB32: Clarity of Appeal Processes | AC32: ↑ | AD32: 1 | AE32: 5 | AF32: N/A | AG32: N/A | AH32: A score (1-5). The crucial "release valve" for a healthy, non-tyrannical system. | AI32: 0 | AJ32: Adaptive Governance | AK32: Air | AL32: Is it clear what we are trying to create (and what we aren't)? | AM32: Clarity of Innovation Mandate | AN32: ↑ | AO32: 1 | AP32: 4.8 | AQ32: N/A | AR32: N/A | AS32: How clearly has the governance articulated the "sandbox" within which creative freedom can be exercised? | AT32: 0 | AU32: Governance Transparency | AV32: Air | AW32: Is our unique structure clearly understood? | AX32: Clarity of Governance Model Explanation | AY32: ↑ | AZ32: 1 | BA32: 4.8 | BB32: N/A | BC32: N/A | BD32: How well can we explain our unique legal and operational structure (e.g., Foundation) to the world? | BE32: 0 | BF32: Evolutionary Governance | BG32: Air | BH32: Is our path to a more coherent future structure clear? | BI32: Clarity of Evolutionary Path | BJ32: ↑ | BK32: 1 | BL32: 4.5 | BM32: N/A | BN32: N/A | BO32: Do we a have a clear, shared vision for how our governance will evolve as we scale? | BP32: 0 | BQ32: Governance as Emergent Order | BR32: Air | BS32: Is every action and decision perfectly visible to all? | BT32: Radical Transparency / "Glass Walls" | BU32: ↑ | BV32: 1 | BW32: 5 | BX32: N/A | BY32: N/A | BZ32: The state where there are no "internal secrets" because the entire system operates from a place of absolute, unshakable integrity. | CA32: 0
A33: Structural Capital (F4) | B33: Governance Foundation Integrity | C33: Ether | D33: Is it fair? | E33: Perceived Fairness of Structure (1-5) | F33: ↑ | G33: 4.5 | H33: 1 | I33: 4.5 | J33: N/A | K33: N/A | L33: A 1-5 scale. Measures the felt sense of justice and coherence in the venture's structure from the inside. | M33: =MAX(0,MIN(1,(G33-H33)/(Octave_1_KPIs[[#This Row],[Healthy_Min]]-Octave_1_KPIs[[#This Row],[Target_Min]]))) -> 1 | N33: Process Resilience | O33: Ether | P33: Do our processes feel coherent? | Q33: Simplicity & Elegance | R33: ↑ | S33: 1 | T33: 4.5 | U33: N/A | V33: N/A | W33: The ultimate measure of a masterful process is that it feels simple and beautiful. | X33: 0 | Y33: Participatory Governance | Z33: Ether | AA33: Are the leaders and the team in resonance? | AB33: Leadership-Team Alignment Score | AC33: ↑ | AD33: 0.5 | AE33: 1 | AF33: N/A | AG33: N/A | AH33: A survey measuring the percentage of alignment on key strategic issues | AI33: 0 | AJ33: Adaptive Governance | AK33: Ether | AL33: Do our creations align with our deepest values? | AM33: Ethical IP Score | AN33: ↑ | AO33: 1 | AP33: 4.5 | AQ33: N/A | AR33: N/A | AS33: An Edge KPI. Does our governance ensure that what we create is a true reflection of who we are? | AT33: 0 | AU33: Governance Transparency | AV33: Ether | AW33: Does our way of governing serve as a model for others? | AX33: Influence of our Governance Model | AY33: ↑ | AZ33: 1 | BA33: 4 | BB33: N/A | BC33: N/A | BD33: Is our governance model itself becoming a piece of IP that inspires change in our ecosystem? | BE33: 0 | BF33: Evolutionary Governance | BG33: Ether | BH33: Is our way of governing a constant search for truth? | BI33: Governance as a Living Inquiry | BJ33: ↑ | BK33: 1 | BL33: 5 | BM33: N/A | BN33: N/A | BO33: The degree to which governance is seen not as a fixed set of rules, but as a living, dynamic, and joyful exploration of coherence. | BP33: 0 | BQ33: Governance as Emergent Order | BR33: Ether | BS33: Have we transcended the need for "governance" entirely? | BT33: Governance is Indistinguishable from Life | BU33: ↑ | BV33: 1 | BW33: 5 | BX33: N/A | BY33: N/A | BZ33: The Monad-level state. The organization's natural, living process is its perfect, emergent governance. | CA33: 0
A34: Market Resonance (F5) | B34: Initial Message Coherence | C34: Earth | D34: Is the message grounded? | E34: Clarity Score of one-sentence pitch (1-5) | F34: ↑ | G34: 2.1 | H34: 2 | I34: 4.5 | J34: N/A | K34: N/A | L34: A 1-5 scale. A pitch that is not at least a "2" is actively causing confusion and harm. 4.5 is the target for profound clarity. | M34: =MAX(0,MIN(1,(G34-H34)/(Octave_1_KPIs[[#This Row],[Healthy_Min]]-Octave_1_KPIs[[#This Row],[Target_Min]]))) -> 0.04 | N34: Customer Experience | O34: Earth | P34: Is our product reliable? | Q34: Product Uptime % | R34: ↑ | S34: 0.95 | T34: 0.999 | U34: N/A | V34: N/A | W34: The bedrock of customer trust is a reliable, available product. | X34: 0 | Y34: Customer Loyalty, Love & Community | Z34: Earth | AA34: Is our relationship with customers stable and lasting? | AB34: Customer Retention Rate % | AC34: ↑ | AD34: 0.6 | AE34: 0.9 | AF34: N/A | AG34: N/A | AH34: The most grounded, long-term measure of a healthy customer relationship. | AI34: 0 | AJ34: Co-Creative Marketing | AK34: Earth | AL34: Are our innovations grounded in real user needs? | AM34: Customer Co-creation Rate | AN34: ↑ | AO34: 0.1 | AP34: 0.5 | AQ34: N/A | AR34: N/A | AS34: The percentage of new features or ideas that are directly sourced from or co-developed with the customer community. | AT34: 0 | AU34: Ecosystem Signal Fidelity | AV34: Earth | AW34: Is our core message stable and consistently expressed? | AX34: Core Message "Signal Drift" % | AY34: ↓ | AZ34: 0.25 | BA34: 0.05 | BB34: N/A | BC34: N/A | BD34: How much does our core message deviate across different channels and team members? Lower is better. The bedrock of listening. A low drift % proves that the market is hearing a stable, grounded signal from us. | BE34: 0 | BF34: Future-Shaping Narratives | BG34: Earth | BH34: Is our story grounded in a long, epic timeline? | BI34: Long-Term Narrative Arc | BJ34: ↑ | BK34: 1 | BL34: 1 | BM34: N/A | BN34: N/A | BO34: A binary milestone. Have we articulated the grand, multi-year or multi-decade narrative arc of our brand? | BP34: 0 | BQ34: The Market as a Field of Consciousness | BR34: Earth | BS34: Is our community so coherent it governs itself? | BT34: Community as a Sovereign Entity | BU34: ↑ | BV34: 0 | BW34: 1 | BX34: N/A | BY34: N/A | BZ34: A milestone. Has the community around the brand developed its own emergent, self-governing structures? | CA34: 0
A35: Market Resonance (F5) | B35: Initial Message Coherence | C35: Water | D35: Is it reaching people? | E35: Weekly Website Traffic | F35: ↑ | G35: 7.2 | H35: 0 | I35: 100 | J35: N/A | K35: N/A | L35: At this early stage, getting 100 unique, interested visitors per week is a sign of a healthy, flowing signal. | M35: =MAX(0,MIN(1,(G35-H35)/(Octave_1_KPIs[[#This Row],[Healthy_Min]]-Octave_1_KPIs[[#This Row],[Target_Min]]))) -> 0.072 | N35: Customer Experience | O35: Water | P35: Are our customers happy? | Q35: Customer Satisfaction (CSAT) | R35: ↑ | S35: 0.7 | T35: 0.95 | U35: N/A | V35: N/A | W35: The direct measure of the emotional flow between the product and the user. | X35: 0 | Y35: Customer Loyalty, Love & Community | Z35: Water | AA35: Do our customers have a strong emotional bond with us? | AB35: Net Promoter Score (NPS) | AC35: ↑ | AD35: 0 | AE35: 50 | AF35: N/A | AG35: N/A | AH35: The classic measure of customer love and willingness to advocate. | AI35: 0 | AJ35: Co-Creative Marketing | AK35: Water | AL35: Do we have a frictionless channel for customer ideas? | AM35: Flow of Customer Ideas | AN35: ↑ | AO35: 1 | AP35: 4.5 | AQ35: N/A | AR35: N/A | AS35: A 1-5 score on the quality and accessibility of the idea submission process. | AT35: 0 | AU35: Ecosystem Signal Fidelity | AV35: Water | AW35: What is the emotional current our signal creates in the audience? | AX35: Market's "Felt Resonance" Score | AY35: ↑ | AZ35: 1 | BA35: 4.5 | BB35: N/A | BC35: N/A | BD35: A survey of our target audience. How do they feel after interacting with our brand? A receptive measure. How do they feel? This is the core of empathetic listening to the market. | BE35: 0 | BF35: Future-Shaping Narratives | BG35: Water | BH35: Are we listening to the whispers of what is to come? | BI35: Flow of "Weak Signals" from the Future | BJ35: ↑ | BK35: 1 | BL35: 4.5 | BM35: N/A | BN35: N/A | BO35: A qualitative score on the organization's ability to detect and interpret the subtle, emergent trends that will shape the future. | BP35: 0 | BQ35: The Market as a Field of Consciousness | BR35: Water | BS35: Does value flow between us and our "market" without friction? | BT35: Effortless Exchange of Value | BU35: ↑ | BV35: 1 | BW35: 4.8 | BX35: N/A | BY35: N/A | BZ35: The state where the concepts of "price," "cost," and "selling" dissolve into a joyful and continuous exchange of mutual support. | CA35: 0
A36: Market Resonance (F5) | B36: Initial Message Coherence | C36: Fire | D36: Are we speaking? | E36: # of Engaging Social Media Posts | F36: Band | G36: 0 | H36: 0 | I36: 1 | J36: 2 | K36: 5 | L36: The sustainable rhythm of authentic communication. Quality over quantity. | M36: =IF(AND(Octave_1_KPIs[[#This Row],[Value]] >= Octave_1_KPIs[[#This Row],[Healthy_Min]], Octave_1_KPIs[[#This Row],[Value]] <= Octave_1_KPIs[[#This Row],[Healthy_Max]]), 1, IF(Octave_1_KPIs[[#This Row],[Value]] < Octave_1_KPIs[[#This Row],[Healthy_Min]], MAX(0, (Octave_1_KPIs[[#This Row],[Value]] - Octave_1_KPIs[[#This Row],[Target_Min]]) / (Octave_1_KPIs[[#This Row],[Healthy_Min]] - Octave_1_KPIs[[#This Row],[Target_Min]])), MAX(0, 1 - (Octave_1_KPIs[[#This Row],[Value]] - Octave_1_KPIs[[#This Row],[Healthy_Max]]) / (Octave_1_KPIs[[#This Row],[Absolute_Max]] - Octave_1_KPIs[[#This Row],[Healthy_Max]])))) -> 0 | N36: Customer Experience | O36: Fire | P36: Are we responsive? | Q36: Mean Time to Resolve Issues | R36: ↓ | S36: 72h | T36: 4h | U36: N/A | V36: N/A | W36: The speed of action in service of the customer. | X36: 0 | Y36: Customer Loyalty, Love & Community | Z36: Fire | AA36: Are we actively building a community? | AB36: Community Engagement Metrics | AC36: ↑ | AD36: Low | AE36: High | AF36: N/A | AG36: N/A | AH36: Measures active participation (forum posts, event attendance, user-generated content). | AI36: 0 | AJ36: Co-Creative Marketing | AK36: Fire | AL36: Are we actively testing our creations with our community? | AM36: # of Beta-Testing Campaigns | AN36: Band | AO36: 0 | AP36: 1 | AQ36: 3 | AR36: 5 | AS36: A sustainable rhythm of engaging the community in testing and refining new prototypes. | AT36: 0 | AU36: Ecosystem Signal Fidelity | AV36: Fire | AW36: Are we actively creating spaces for the market to speak to us? | AX36: Depth of Community Dialogue | AY36: Band | AZ36: 0 | BA36: 2 | BB36: 5 | BC36: 10 | BD36: Measures the quality and frequency of two-way conversations (forums, workshops), not just one-way projection. | BE36: 0 | BF36: Future-Shaping Narratives | BG36: Fire | BH36: Are we actively telling challenging stories about the future? | BI36: # of "Provocative" Future Scenarios | BJ36: Band | BK36: 0 | BL36: 1 | BM36: 3 | BN36: 5 | BO36: The number of thought-provoking articles, videos, or scenarios we publish per year that challenge conventional thinking about the future. | BP36: 0 | BQ36: The Market as a Field of Consciousness | BR36: Fire | BS36: How much inspired action does our presence generate in others? | BT36: "Inspirational Coefficient" | BU36: ↑ | BV36: Low | BW36: High | BX36: N/A | BY36: N/A | BZ36: A measure of the "ripple effect." For every one action we take, how many coherent actions are inspired in our ecosystem? | CA36: 0
A37: Market Resonance (F5) | B37: Initial Message Coherence | C37: Air | D37: Is it understood? | E37: Quality of Feedback from listeners | F37: ↑ | G37: 2.5 | H37: 1 | I37: 4 | J37: N/A | K37: N/A | L37: A 1-5 scale. Measures the quality of the questions and insights received from the audience after hearing the message. | M37: =MAX(0,MIN(1,(G37-H37)/(Octave_1_KPIs[[#This Row],[Healthy_Min]]-Octave_1_KPIs[[#This Row],[Target_Min]]))) -> 0.5 | N37: Customer Experience | O37: Air | P37: Is our value prop clear? | Q37: Conversion Rate % | R37: ↑ | S37: 0.01 | T37: 0.05 | U37: N/A | V37: N/A | W37: The clarity of the value proposition, measured by the user's willingness to commit. | X37: 0 | Y37: Customer Loyalty, Love & Community | Z37: Air | AA37: Can our customers speak to us easily and feel heard? | AB37: Clarity of Customer Feedback Channels | AC37: ↑ | AD37: 1 | AE37: 4.5 | AF37: N/A | AG37: N/A | AH37: A 1-5 score on the effectiveness of systems for gathering and acting on customer feedback. | AI37: 0 | AJ37: Co-Creative Marketing | AK37: Air | AL37: Is our communication about new creations clear and honest? | AM37: Clarity of "Beta" Communications | AN37: ↑ | AO37: 1 | AP37: 4.8 | AQ37: N/A | AR37: N/A | AS37: How clearly do we manage expectations and invite feedback during the experimental phase? | AT37: 0 | AU37: Ecosystem Signal Fidelity | AV37: Air | AW37: Can we hear the true signal in the market's response? | AX37: Signal-to-Noise Ratio | AY37: ↑ | AZ37: 1 | BA37: 4.5 | BB37: N/A | BC37: N/A | BD37: How well can we distinguish valuable, coherent feedback from random noise and distraction? A measure of our clarity as listeners. | BE37: 0 | BF37: Future-Shaping Narratives | BG37: Air | BH37: Is the future we are aiming for clear and compelling? | BI37: Clarity of our Vision for a Better World | BJ37: ↑ | BK37: 1 | BL37: 5 | BM37: N/A | BN37: N/A | BO37: How vividly and inspiringly can we paint a picture of the world we are trying to co-create? | BP37: 0 | BQ37: The Market as a Field of Consciousness | BR37: Air | BS37: Is our market itself a source of profound wisdom and clarity? | BT37: Market as a Collective Intelligence | BU37: ↑ | BV37: 1 | BW37: 4.5 | BX37: N/A | BY37: N/A | BZ37: To what degree have we moved from "listening to the market" to being in a deep, co-creative dialogue with the market as a single, intelligent being? | CA37: 0
A38: Market Resonance (F5) | B38: Initial Message Coherence | C38: Ether | D38: Is it authentic? | E38: Founder's "Felt Resonance" when speaking (1-5) | F38: ↑ | G38: 4.5 | H38: 1 | I38: 4.5 | J38: N/A | K38: N/A | L38: A 1-5 scale. The ultimate internal check: does the message being spoken feel true in the founder's soul? | M38: =MAX(0,MIN(1,(G38-H38)/(Octave_1_KPIs[[#This Row],[Healthy_Min]]-Octave_1_KPIs[[#This Row],[Target_Min]]))) -> 1 | N38: Customer Experience | O38: Ether | P38: Do customers feel a connection? | Q38: Net Promoter Score (NPS) | R38: ↑ | S38: 0 | T38: 50 | U38: N/A | V38: N/A | W38: The ultimate measure of loyalty and brand resonance. | X38: 0 | Y38: Customer Loyalty, Love & Community | Z38: Ether | AA38: Does our brand feel like a shared identity? | AB38: Customer-Brand Purpose Alignment | AC38: ↑ | AD38: 1 | AE38: 4.5 | AF38: N/A | AG38: N/A | AH38: A score (1-5). The ultimate state of resonance, where the boundary between company and customer dissolves. | AI38: 0 | AJ38: Co-Creative Marketing | AK38: Ether | AL38: Does our community feel like they are building this with us? | AM38: "Sense of Shared Creation" | AN38: ↑ | AO38: 1 | AP38: 4.5 | AQ38: N/A | AR38: N/A | AS38: The ultimate measure of a co-creative brand. | AT38: 0 | AU38: Ecosystem Signal Fidelity | AV38: Ether | AW38: Does our audience feel elevated and served by our signal? | AX38: "Uplift" Score of Communications | AY38: ↑ | AZ38: 1 | BA38: 4.5 | BB38: N/A | BC38: N/A | BD38: Does our marketing and communication leave people feeling more coherent, intelligent, and inspired, regardless of whether they buy? The ultimate receptive measure. Does the audience feel that our communication is a gift to them? | BE38: 0 | BF38: Future-Shaping Narratives | BG38: Ether | BH38: Is our brand itself a force that pulls the desired future into being? | BI38: Brand as a "Strange Attractor" for the Future | BJ38: ↑ | BK38: 1 | BL38: 5 | BM38: N/A | BN38: N/A | BO38: a "trellis", from chaos theory. To what degree does our brand act as a powerful, coherent signal around which a new, better future can self-organize? | BP38: 0 | BQ38: The Market as a Field of Consciousness | BR38: Ether | BS38: Have we dissolved the boundary between "us" and "them"? | BT38: No Separation Between Creator and User | BU38: ↑ | BV38: 1 | BW38: 5 | BX38: N/A | BY38: N/A | BZ38: The ultimate state of co-creation, where the users are the creators, the creators are the users, and all are stewards of the shared vision. | CA38: 0
A39: Community & Partners (F6) | B39: Network Foundation Strength | C39: Earth | D39: Are your allies real? | E39: # of Committed Advisors | F39: ↑ | G39: 2 | H39: 0 | I39: 3 | J39: N/A | K39: N/A | L39: Three deeply committed, high-quality advisors is a powerful, stable foundation for any startup. | M39: =MAX(0,MIN(1,(G39-H39)/(Octave_1_KPIs[[#This Row],[Healthy_Min]]-Octave_1_KPIs[[#This Row],[Target_Min]]))) -> 0.66666667 | N39: Partnership Integration | O39: Earth | P39: Are our partnerships formalized? | Q39: % of Partnerships w/ Agreements | R39: ↑ | S39: 0 | T39: 1 | U39: N/A | V39: N/A | W39: The stable, legal ground for collaboration. | X39: 0 | Y39: Ecosystem Health | Z39: Earth | AA39: Are our partnerships grounded in long-term commitment? | AB39: Average Partnership Longevity | AC39: ↑ | AD39: 0.5y | AE39: 3y | AF39: N/A | AG39: N/A | AH39: The average length in years of a formal partnership. | AI39: 0 | AJ39: Ecosystem Innovation | AK39: Earth | AL39: Are our partnerships a source of new creations? | AM39: # of Innovations from Partners | AN39: ↑ | AO39: 0 | AP39: 1 | AQ39: N/A | AR39: N/A | AS39: At this stage, having one significant innovation emerge from a partnership is a powerful signal. | AT39: 0 | AU39: Ecosystem Narrative Weaving | AV39: Earth | AW39: Do we have a stable "town square" for our ecosystem? | AX39: Health of Community Platform | AY39: ↑ | AZ39: 1 | BA39: 4.5 | BB39: N/A | BC39: N/A | BD39: A 1-5 score measuring the health, activity, and safety of our primary community platform (e.g., forum, Discord, newsletter). | BE39: 0 | BF39: Ecosystem as a Future-Builder | BG39: Earth | BH39: Are our partnerships grounded in creating a resilient future for all? | BI39: Long-Term Ecosystem Health | BJ39: ↑ | BK39: 1 | BL39: 4.5 | BM39: N/A | BN39: N/A | BO39: A qualitative score on the long-term viability and health of the entire ecosystem we are a part of. | BP39: 0 | BQ39: The Network as a Planetary Organ | BR39: Earth | BS39: Is our network a stable, self-sustaining, and life-affirming part of the planetary ecosystem? | BT39: Ecosystem as a Resilient Bio-Region | BU39: ↑ | BV39: 1 | BW39: 4.8 | BX39: N/A | BY39: N/A | BZ39: The degree to which our network of partners functions like a healthy, natural ecosystem. | CA39: 0
A40: Community & Partners (F6) | B40: Network Foundation Strength | C40: Water | D40: Are you connecting? | E40: # of In-Depth Strategic Conversations | F40: Band | G40: 1 | H40: 0 | I40: 2 | J40: 4 | K40: 4 | L40: The healthy, flowing rhythm of building a network without getting lost in "networking." | M40: =IF(AND(Octave_1_KPIs[[#This Row],[Value]] >= Octave_1_KPIs[[#This Row],[Healthy_Min]], Octave_1_KPIs[[#This Row],[Value]] <= Octave_1_KPIs[[#This Row],[Healthy_Max]]), 1, IF(Octave_1_KPIs[[#This Row],[Value]] < Octave_1_KPIs[[#This Row],[Healthy_Min]], MAX(0, (Octave_1_KPIs[[#This Row],[Value]] - Octave_1_KPIs[[#This Row],[Target_Min]]) / (Octave_1_KPIs[[#This Row],[Healthy_Min]] - Octave_1_KPIs[[#This Row],[Target_Min]])), MAX(0, 1 - (Octave_1_KPIs[[#This Row],[Value]] - Octave_1_KPIs[[#This Row],[Healthy_Max]]) / (Octave_1_KPIs[[#This Row],[Absolute_Max]] - Octave_1_KPIs[[#This Row],[Healthy_Max]])))) -> 0.5 | N40: Partnership Integration | O40: Water | P40: Is there a smooth flow? | Q40: Partner Comm. Cadence | R40: Band | S40: 0 | T40: 1 | U40: 4 | V40: 8 | W40: A healthy, rhythmic flow of communication per month. | X40: 0 | Y40: Ecosystem Health | Z40: Water | AA40: Do our partners feel this relationship is a win? | AB40: Partner's "Perceived Value of Rel." Score | AC40: ↑ | AD40: 1 | AE40: 4.5 | AF40: N/A | AG40: N/A | AH40: The emotional current of the partnership. It must be a win-win to be coherent. | AI40: 0 | AJ40: Ecosystem Innovation | AK40: Water | AL40: Are we open to ideas flowing from our entire network? | AM40: Flow of "Open Innovation" | AN40: ↑ | AO40: 1 | AP40: 4 | AQ40: N/A | AR40: N/A | AS40: How well is the venture tapping into the collective intelligence of its broader ecosystem? | AT40: 0 | AU40: Ecosystem Narrative Weaving | AV40: Water | AW40: Are the stories of our ecosystem flowing freely? | AX40: Flow of Community-Generated Stories | AY40: ↑ | AZ40: Low | BA40: High | BB40: N/A | BC40: N/A | BD40: Measures the rate and quality of stories, ideas, and content being generated by the community, not just by us. | BE40: 0 | BF40: Ecosystem as a Future-Builder | BG40: Water | BH40: Does value and support flow freely to where it's needed most? | BI40: Flow of "Generative" Capital in Network | BJ40: ↑ | BK40: 1 | BL40: 4.5 | BM40: N/A | BN40: N/A | BO40: How well does our network act as a "mutual support system," beyond simple transactional relationships? | BP40: 0 | BQ40: The Network as a Planetary Organ | BR40: Water | BS40: Does support, love, and resources flow to where it's needed, unconditionally? | BT40: Unconditional Support Network | BU40: ↑ | BV40: 1 | BW40: 4.5 | BX40: N/A | BY40: N/A | BZ40: The degree to which the network moves beyond transactional relationships to a state of a true, gift-economy-based "family." | CA40: 0
A41: Community & Partners (F6) | B41: Network Foundation Strength | C41: Fire | D41: Are you building? | E41: # of Active Collaboration Projects | F41: ↑ | G41: 0 | H41: 0 | I41: 1 | J41: N/A | K41: N/A | L41: At this stage, one single, active, co-creative project is a massive signal of real-world traction and an ideal target. | M41: =MAX(0,MIN(1,(G41-H41)/(Octave_1_KPIs[[#This Row],[Healthy_Min]]-Octave_1_KPIs[[#This Row],[Target_Min]]))) -> 0 | N41: Partnership Integration | O41: Fire | P41: Are we creating value together? | Q41: # Active Co-Creative Projects | R41: Band | S41: 0 | T41: 1 | U41: 3 | V41: 5 | W41: A sustainable number of active, energy-giving collaborations. | X41: 0 | Y41: Ecosystem Health | Z41: Fire | AA41: Are we actively creating value together? | AB41: # Active Co-Creative Projects | AC41: Band | AD41: 0 | AE41: 1 | AF41: 3 | AG41: 5 | AH41: A sustainable rhythm of deep, collaborative projects. | AI41: 0 | AJ41: Ecosystem Innovation | AK41: Fire | AL41: Are we actively investing in building the future together? | AM41: # of Joint R&D Projects | AN41: Band | AO41: 0 | AP41: 1 | AQ41: 2 | AR41: 3 | AS41: A sustainable number of deep, long-term R&D collaborations with key strategic partners. | AT41: 0 | AU41: Ecosystem Narrative Weaving | AV41: Fire | AW41: Are we actively using our platform to feature our partners? | AX41: # of Partner Voice Amplifications | AY41: Band | AZ41: 0 | BA41: 2 | BB41: 5 | BC41: 10 | BD41: A sustainable rhythm of partner spotlights, guest posts, and joint announcements per quarter. | BE41: 0 | BF41: Ecosystem as a Future-Builder | BG41: Fire | BH41: Are we actively co-creating the future with our partners? | BI41: # of Joint Ventures for Systemic Change | BJ41: Band | BK41: 0 | BL41: 1 | BM41: 2 | BN41: 3 | BO41: The number of deep, formal joint ventures aimed at tackling large, systemic challenges that no single organization could solve. | BP41: 0 | BQ41: The Network as a Planetary Organ | BR41: Fire | BS41: Are we actively and consciously building a better world together? | BT41: Co-Creation of a New Civilization | BU41: ↑ | BV41: 1 | BW41: 5 | BX41: N/A | BY41: N/A | BZ41: A qualitative assessment. Is the shared, active work of our network a conscious and focused effort to prototype a new, more coherent form of civilization? | CA41: 0
A42: Community & Partners (F6) | B42: Network Foundation Strength | C42: Air | D42: Is the value clear? | E42: Clarity of Partnership "Ask" (1-5) | F42: ↑ | G42: 3 | H42: 1 | I42: 4.5 | J42: N/A | K42: N/A | L42: A 1-5 scale. How clear and compelling is the invitation for others to join the dance? | M42: =MAX(0,MIN(1,(G42-H42)/(Octave_1_KPIs[[#This Row],[Healthy_Min]]-Octave_1_KPIs[[#This Row],[Target_Min]]))) -> 0.57142857 | N42: Partnership Integration | O42: Air | P42: Do partners find us easy to work with? | Q42: Partner Onboarding Friction | R42: ↓ | S42: High | T42: Low | U42: N/A | V42: N/A | W42: The clarity and efficiency of the integration process. | X42: 0 | Y42: Ecosystem Health | Z42: Air | AA42: Is our communication with partners clear and honest? | AB42: Quality of Partner Communication | AC42: ↑ | AD42: 1 | AE42: 4.5 | AF42: N/A | AG42: N/A | AH42: A score (1-5). The crucial alignment of vision and purpose between partners. | AI42: 0 | AJ42: Ecosystem Innovation | AK42: Air | AL42: Are our agreements about shared creation crystal clear? | AM42: Clarity of IP in Partnerships | AN42: ↑ | AO42: 1 | AP42: 5 | AQ42: N/A | AR42: N/A | AS42: A perfect, unambiguous understanding of who owns what in a co-creative endeavor. | AT42: 0 | AU42: Ecosystem Narrative Weaving | AV42: Air | AW42: Is the story of our partnerships clear and compelling? | AX42: Clarity of "Joint Value Proposition" | AY42: ↑ | AZ42: 1 | BA42: 4.8 | BB42: N/A | BC42: N/A | BD42: How clearly can we articulate the "1+1=3" value of our key partnerships to the world? | BE42: 0 | BF42: Ecosystem as a Future-Builder | BG42: Air | BH42: Do we have a clear, shared picture of the future we are building together? | BI42: Clarity of "Shared Vision" with Ecosystem | BJ42: ↑ | BK42: 1 | BL42: 4.8 | BM42: N/A | BN42: N/A | BO42: How well is the "meta-vision" of the entire ecosystem articulated and understood by all its members? | BP42: 0 | BQ42: The Network as a Planetary Organ | BR42: Air | BS42: Is the collective intelligence of our network clear and accessible? | BT42: Ecosystem as a Sentient Being | BU42: ↑ | BV42: 1 | BW42: 4.5 | BX42: N/A | BY42: N/A | BZ42: Has the network developed its own forms of collective sense-making and a shared "nervous system"? | CA42: 0
A43: Community & Partners (F6) | B43: Network Foundation Strength | C43: Ether | D43: Is it vlaues-aligned? | E43: Values Alignment Score of Top 3 Partners (1-5) | F43: ↑ | G43: 2.5 | H43: 1 | I43: 4.5 | J43: N/A | K43: N/A | L43: A 1-5 scale. The ultimate filter: are these potential partners on the same spiritual and ethical wavelength? | M43: =MAX(0,MIN(1,(G43-H43)/(Octave_1_KPIs[[#This Row],[Healthy_Min]]-Octave_1_KPIs[[#This Row],[Target_Min]]))) -> 0.42857143 | N43: Partnership Integration | O43: Ether | P43: Do they feel this is a win-win? | Q43: Partner's Perceived Value | R43: ↑ | S43: 1 | T43: 4.5 | U43: N/A | V43: N/A | W43: The ultimate measure of a coherent partnership is that it feels deeply valuable to both sides. | X43: 0 | Y43: Ecosystem Health | Z43: Ether | AA43: Do we act as stewards of the whole network? | AB43: "Ecosystem as a Garden" Mentality | AC43: ↑ | AD43: 1 | AE43: 4.5 | AF43: N/A | AG43: N/A | AH43: A score (1-5). The ultimate purpose: to nurture the health of the entire ecosystem, not just our part in it. | AI43: 0 | AJ43: Ecosystem Innovation | AK43: Ether | AL43: Are our partnerships creating things neither of us could have created alone? | AM43: "Synergistic Emergence" Score | AN43: ↑ | AO43: 1 | AP43: 4.5 | AQ43: N/A | AR43: N/A | AS43: A qualitative score measuring the "1+1=3" effect of your most important partnerships. | AT43: 0 | AU43: Ecosystem Narrative Weaving | AV43: Ether | AW43: Is the story of our ecosystem inspiring other ecosystems? | AX43: Generative Impact of our Network Narrative | AY43: ↑ | AZ43: 1 | BA43: 4 | BB43: N/A | BC43: N/A | BD43: A qualitative measure of the influence and inspirational power of our collaborative model. | BE43: 0 | BF43: Ecosystem as a Future-Builder | BG43: Ether | BH43: Is our collaborative ecosystem a living prototype of a better way to be? | BI43: Network as a Seed for a New Civilization | BJ43: ↑ | BK43: 1 | BL43: 5 | BM43: N/A | BN43: N/A | BO43: The ultimate measure of a coherent network: is it a seed crystal for a more beautiful future for all of humanity? | BP43: 0 | BQ43: The Network as a Planetary Organ | BR43: Ether | BS43: Have we realized our network is not a thing, but a thread in the living fabric of the planet? | BT43: The Network is the Planetary Weave | BU43: ↑ | BV43: 1 | BW43: 5 | BX43: N/A | BY43: N/A | BZ43: The final, Monad-level realization of non-duality and total systemic embedding. | CA43: 0
A44: Brand & Reputation (F7) | B44: Foundational Brand Integrity | C44: Earth | D44: Is the brand gounded in a consistent message? | E44: Message Consistency Score (1-5) | F44: ↑ | G44: 2 | H44: 1 | I44: 4.5 | J44: N/A | K44: N/A | L44: A 1-5 scale. A consistent brand narrative is the stable ground upon which all reputation is built. | M44: =MAX(0,MIN(1,(G44-H44)/(Octave_1_KPIs[[#This Row],[Healthy_Min]]-Octave_1_KPIs[[#This Row],[Target_Min]]))) -> 0.28571429 | N44: Brand Consistency & Trust | O44: Earth | P44: Is the brand grounded in a consistent message? | Q44: Message Consistency Score | R44: ↑ | S44: 1 | T44: 4.5 | U44: N/A | V44: N/A | W44: At this octave, consistency is the bedrock of a stable brand identity. | X44: 0 | Y44: Brand Trust & Authenticity | Z44: Earth | AA44: Is our brand a trusted foundation in the market? | AB44: Brand Trust Score | AC44: ↑ | AD44: 1 | AE44: 4.5 | AF44: N/A | AG44: N/A | AH44: Trust is the stable ground upon which all authentic brands are built. | AI44: 0 | AJ44: Innovative Branding | AK44: Earth | AL44: Are our brand ideas grounded in real-world tests? | AM44: Market Experimentation Rate | AN44: Band | AO44: 0 | AP44: 1 | AQ44: 3 | AR44: 5 | AS44: A sustainable rhythm of A/B testing, message experiments, and new channel explorations per quarter. | AT44: 0 | AU44: Authentic Brand Expression | AV44: Earth | AW44: Is our "speaking" grounded in the truth of our "doing"? | AX44: Brand-Operational Integrity | AY44: ↑ | AZ44: 0.5 | BA44: 1 | BB44: N/A | BC44: N/A | BD44: The bedrock of an authentic brand. A ratio of 1.0 means our "say" and our "do" are in perfect alignment. | BE44: 0 | BF44: "Legacy" Branding | BG44: Earth | BH44: Is our brand's core identity built on timeless principles? | BI44: Longevity of Brand Architecture | BJ44: ↑ | BK44: 1 | BL44: 4.8 | BM44: N/A | BN44: N/A | BO44: A 1-5 score. How well is our brand's "deep grammar" designed to be relevant for decades, not just years? | BP44: 0 | BQ44: Brand as an Archetype | BR44: Earth | BS44: Is our brand so grounded it has become a universal archetype? | BT44: The Brand as a Timeless Symbol | BU44: ↑ | BV44: 1 | BW44: 5 | BX44: N/A | BY44: N/A | BZ44: Has the brand (its name, its glyph) transcended our organization and entered the collective consciousness as a symbol for coherence itself? | CA44: 0
A45: Brand & Reputation (F7) | B45: Foundational Brand Integrity | C45: Water | D45: Is the brand creating an emotional connection? | E45: Social Media Engagement Rate (%) | F45: ↑ | G45: 0.02 | H45: 0.01 | I45: 0.05 | J45: N/A | K45: N/A | L45: Measures the quality and flow of the relationship with the audience, not just the volume of posts. | M45: =MAX(0,MIN(1,(G45-H45)/(Octave_1_KPIs[[#This Row],[Healthy_Min]]-Octave_1_KPIs[[#This Row],[Target_Min]]))) -> 0.25 | N45: Brand Consistency & Trust | O45: Water | P45: Does the market trust our brand? | Q45: Brand Trust Score | R45: ↑ | S45: 1 | T45: 4 | U45: N/A | V45: N/A | W45: Measures the emotional current between the brand and its audience. A score of 4 indicates deep trust. | X45: 0 | Y45: Brand Trust & Authenticity | Z45: Water | AA45: Does our story create a deep, positive feeling? | AB45: Emotional Resonance of Story | AC45: ↑ | AD45: 1 | AE45: 4.5 | AF45: N/A | AG45: N/A | AH45: A qualitative measure of the brand's ability to connect with the hearts of its audience. | AI45: 0 | AJ45: Innovative Branding | AK45: Water | AL45: Are we producing a steady stream of beautiful content? | AM45: Flow of Creative Brand Assets | AN45: ↑ | AO45: 1 | AP45: 4 | AQ45: N/A | AR45: N/A | AS45: A 1-5 score measuring the quality and consistency of creative output (visuals, articles, videos). | AT45: 0 | AU45: Authentic Brand Expression | AV45: Water | AW45: Is the emotional current of our voice true to our soul? | AX45: "Felt Authenticity" of Brand Voice | AY45: ↑ | AZ45: 1 | BA45: 4.8 | BB45: N/A | BC45: N/A | BD45: An internal measure. Does the voice we project outwards feel like an authentic and true expression of who we are? | BE45: 0 | BF45: "Legacy" Branding | BG45: Water | BH45: Is the story we're telling one that will matter to our children's children? | BI45: Emotional Resonance with Future Generations | BJ45: ↑ | BK45: 1 | BL45: 4.5 | BM45: N/A | BN45: N/A | BO45: A profound, qualitative assessment of the story's timeless emotional power. | BP45: 0 | BQ45: Brand as an Archetype | BR45: Water | BS45: Can people feel the resonant field of our brand without even hearing our name? | BT45: The "Felt Sense" of the Brand's Field | BU45: ↑ | BV45: 1 | BW45: 4.8 | BX45: N/A | BY45: N/A | BZ45: The ultimate measure of brand resonance. A qualitative score of the pure, non-verbal, energetic signature of the brand. | CA45: 0
A46: Brand & Reputation (F7) | B46: Foundational Brand Integrity | C46: Fire | D46: Is the brand actively speaking its truth? | E46: # of Engaging Posts | F46: Band | G46: 0 | H46: 0 | I46: 1 | J46: 2 | K46: 5 | L46: A sustainable rhythm of high-quality communication. The goal is resonant signal, not overwhelming noise. | M46: =IF(AND(Octave_1_KPIs[[#This Row],[Value]] >= Octave_1_KPIs[[#This Row],[Healthy_Min]], Octave_1_KPIs[[#This Row],[Value]] <= Octave_1_KPIs[[#This Row],[Healthy_Max]]), 1, IF(Octave_1_KPIs[[#This Row],[Value]] < Octave_1_KPIs[[#This Row],[Healthy_Min]], MAX(0, (Octave_1_KPIs[[#This Row],[Value]] - Octave_1_KPIs[[#This Row],[Target_Min]]) / (Octave_1_KPIs[[#This Row],[Healthy_Min]] - Octave_1_KPIs[[#This Row],[Target_Min]])), MAX(0, 1 - (Octave_1_KPIs[[#This Row],[Value]] - Octave_1_KPIs[[#This Row],[Healthy_Max]]) / (Octave_1_KPIs[[#This Row],[Absolute_Max]] - Octave_1_KPIs[[#This Row],[Healthy_Max]])))) -> 0 | N46: Brand Consistency & Trust | O46: Fire | P46: Are we actively building our reputation? | Q46: Public Relations Activity | R46: Band | S46: 0 | T46: 1 | U46: 3 | V46: 5 | W46: A sustainable rhythm of proactive PR (articles, interviews) per quarter. | X46: 0 | Y46: Brand Trust & Authenticity | Z46: Fire | AA46: Are we actively engaging in real conversations? | AB46: # of Authentic Community Interactions | AC46: Band | AD46: 0 | AE46: 5 | AF46: 10 | AG46: 20 | AH46: A sustainable rhythm of genuine, non-automated interactions per week. | AI46: 0 | AJ46: Innovative Branding | AK46: Fire | AL46: Are we actively pushing the boundaries of our message? | AM46: Boldness of Brand Voice | AN46: ↑ | AO46: 1 | AP46: 4 | AQ46: N/A | AR46: N/A | AS46: A qualitative score. Is our brand voice playing it safe, or is it a courageous, thought-provoking signal? | AT46: 0 | AU46: Authentic Brand Expression | AV46: Fire | AW46: Are we actively planting our flag and speaking our deepest truth? | AX46: # of "Flagship" Content Pieces | AY46: Band | AZ46: 0 | BA46: 1 | BB46: 2 | BC46: 3 | BD46: The deliberate, high-effort acts of speaking. Measures the creation of profound, thesis-grade content per quarter. | BE46: 0 | BF46: "Legacy" Branding | BG46: Fire | BH46: Are we actively creating the single, definitive work that will be our legacy? | BI46: Creation of a "Canonical" Work | BJ46: ↑ | BK46: 0 | BL46: 1 | BM46: N/A | BN46: N/A | BO46: A binary milestone. Have we published the "great book" or created the "masterpiece" that will stand as our ultimate contribution? | BP46: 0 | BQ46: Brand as an Archetype | BR46: Fire | BS46: Is our brand being actively and creatively remixed by the world? | BT46: Spontaneous Emergence of Brand in Culture | BU46: ↑ | BV46: Low | BW46: High | BX46: N/A | BY46: N/A | BZ46: Does our brand's language, symbols, and ideas appear organically in art, in other movements, in the language of others, without our effort? | CA46: 0
A47: Brand & Reputation (F7) | B47: Foundational Brand Integrity | C47: Air | D47: Is the brand trusted? | E47: Initial Brand Trust Score (Survey, 1-5) | F47: ↑ | G47: 2 | H47: 1 | I47: 4 | J47: N/A | K47: N/A | L47: A 1-5 survey. This measures the clarity and believability of the brand's promise in the minds of early stakeholders. | M47: =MAX(0,MIN(1,(G47-H47)/(Octave_1_KPIs[[#This Row],[Healthy_Min]]-Octave_1_KPIs[[#This Row],[Target_Min]]))) -> 0.33333333 | N47: Brand Consistency & Trust | O47: Air | P47: Is our unique value clear to the market? | Q47: Clarity of Competitive Positioning | R47: ↑ | S47: 1 | T47: 4.5 | U47: N/A | V47: N/A | W47: How clearly do stakeholders understand what makes Quannex different and superior? | X47: 0 | Y47: Brand Trust & Authenticity | Z47: Air | AA47: Is the core purpose of our brand clearly communicated? | AB47: Clarity of Our "Why" | AC47: ↑ | AD47: 1 | AE47: 4.8 | AF47: N/A | AG47: N/A | AH47: How well do stakeholders understand the deep "why" behind what we do? | AI47: 0 | AJ47: Innovative Branding | AK47: Air | AL47: Can we clearly articulate the unique genius of our creation? | AM47: Clarity of Our Unique "Magic" | AN47: ↑ | AO47: 1 | AP47: 4.8 | AQ47: N/A | AR47: N/A | AS47: Beyond the value prop, how well can we explain the deep, unique "magic" at the heart of the Spiral model? | AT47: 0 | AU47: Authentic Brand Expression | AV47: Air | AW47: Is our voice expressed with clarity, beauty, and elegance? | AX47: Artistic & Aesthetic Quality of Brand | AY47: ↑ | AZ47: 1 | BA47: 4.5 | BB47: N/A | BC47: N/A | BD47: A qualitative score for the sheer craftsmanship and artistry of our brand's expression. | BE47: 0 | BF47: "Legacy" Branding | BG47: Air | BH47: Have we articulated the grand, mythic story of our purpose? | BI47: Clarity of our Mythopoetic Narrative | BJ47: ↑ | BK47: 1 | BL47: 5 | BM47: N/A | BN47: N/A | BO47: Beyond a brand story, this is the articulation of the venture's role in the great, unfolding story of humanity. | BP47: 0 | BQ47: Brand as an Archetype | BR47: Air | BS47: Is our brand a clear and coherent school of thought? | BT47: The Brand as a Philosophical School | BU47: ↑ | BV47: 1 | BW47: 4.5 | BX47: N/A | BY47: N/A | BZ47: To what degree have the ideas of the brand coalesced into a formal philosophy that is studied and debated? | CA47: 0
A48: Brand & Reputation (F7) | B48: Foundational Brand Integrity | C48: Ether | D48: Is the brand a true expression of the venture's soul? | E48: Brand-Values Alignment Score (1-5) | F48: ↑ | G48: 4 | H48: 1 | I48: 4.5 | J48: N/A | K48: N/A | L48: A 1-5 internal assessment. This is the ultimate measure of authenticity. | M48: =MAX(0,MIN(1,(G48-H48)/(Octave_1_KPIs[[#This Row],[Healthy_Min]]-Octave_1_KPIs[[#This Row],[Target_Min]]))) -> 0.85714286 | N48: Brand Consistency & Trust | O48: Ether | P48: Does our brand promise match our operational reality? | Q48: Brand-Operational Integrity | R48: ↑ | S48: 1 | T48: 1 | U48: N/A | V48: N/A | W48: An Edge KPI. The ultimate measure of authenticity, expressed as a ratio. The goal is a perfect 1:1 alignment. | X48: 0 | Y48: Brand Trust & Authenticity | Z48: Ether | AA48: Is our brand being co-created with our community? | AB48: Brand-Community Co-creation | AC48: ↑ | AD48: 0 | AE48: 0.2 | AF48: N/A | AG48: N/A | AH48: The percentage of brand content or initiatives that are born from direct community collaboration. | AI48: 0 | AJ48: Innovative Branding | AK48: Ether | AL48: Is our brand itself a work of art? | AM48: Artistic & Aesthetic Quality | AN48: ↑ | AO48: 1 | AP48: 4.5 | AQ48: N/A | AR48: N/A | AS48: A qualitative score for the sheer beauty, elegance, and artistic merit of the brand's presentation. | AT48: 0 | AU48: Authentic Brand Expression | AV48: Ether | AW48: Is our voice a beacon that helps others to navigate? | AX48: Brand as a Cultural Lighthouse | AY48: ↑ | AZ48: 1 | BA48: 4.5 | BB48: N/A | BC48: N/A | BD48: The ultimate purpose of our speech. Does our brand's signal shine a light that illuminates a path for others? | BE48: 0 | BF48: "Legacy" Branding | BG48: Ether | BH48: Does our brand itself become a source of timeless wisdom? | BI48: Brand as a Teacher of Wisdom | BJ48: ↑ | BK48: 1 | BL48: 4.5 | BM48: N/A | BN48: N/A | BO48: To what degree does our brand transcend commerce and become a trusted source for deep, universal truths? | BP48: 0 | BQ48: Brand as an Archetype | BR48: Ether | BS48: Does our brand simply point to a self-evident truth? | BT48: The Brand is Indistinguishable from Truth | BU48: ↑ | BV48: 1 | BW48: 5 | BX48: N/A | BY48: N/A | BZ48: The final state, where the brand is no longer "selling" an idea, but is a transparent lens through which a universal truth is perceived. | CA48: 0
A49: Core Operations (F8) | B49: Operational Viability | C49: Earth | D49: Have we proven we can buil it? | E49: "Live" Test Completion (0 or 1) | F49: ↑ | G49: 0 | H49: 0 | I49: 1 | J49: N/A | K49: N/A | L49: A binary (0/1) milestone. The ultimate ground-truth for a new venture is a working prototype. | M49: =MAX(0,MIN(1,(G49-H49)/(Octave_1_KPIs[[#This Row],[Healthy_Min]]-Octave_1_KPIs[[#This Row],[Target_Min]]))) -> 0 | N49: Operational Throughput | O49: Earth | P49: Is our product stable and reliable? | Q49: Product Uptime % | R49: ↑ | S49: 0.95 | T49: 0.999 | U49: N/A | V49: N/A | W49: The bedrock of operational excellence is a system that works consistently. | X49: 0 | Y49: Collaborative Flow | Z49: Earth | AA49: Are our teams grounded in effective collaboration? | AB49: Cross-Functional Team Success Rate | AC49: ↑ | AD49: 0.7 | AE49: 0.95 | AF49: N/A | AG49: N/A | AH49: The bedrock of relational operations. Do teams that work together succeed together? | AI49: 0 | AJ49: Operational Innovation | AK49: Earth | AL49: Can we innovate without breaking our core product? | AM49: Stability of Experimental Features | AN49: ↑ | AO49: 0.9 | AP49: 0.99 | AQ49: N/A | AR49: N/A | AS49: Measures the uptime and stability of the core system while new, experimental features are being tested. | AT49: 0 | AU49: Operational Transparency | AV49: Earth | AW49: Is our "how-to" documentation grounded and accessible? | AX49: Process Documentation Readability Score | AY49: ↑ | AZ49: 1 | BA49: 4.5 | BB49: N/A | BC49: N/A | BD49: How easy is it for an outsider (or new team member) to read and understand our operational processes? | BE49: 0 | BF49: Evolutionary Operations | BG49: Earth | BH49: Are our operations designed to be self-creating and self-maintaining? | BI49: "Autopoietic" System Design | BJ49: ↑ | BK49: 1 | BL49: 4 | BM49: N/A | BN49: N/A | BO49: (From Varela & Maturana). A 1-5 score on how well our systems are designed to learn, adapt, and sustain themselves without constant intervention. | BP49: 0 | BQ49: Operations as a Living Art | BR49: Earth | BS49: Is the sheer beauty and elegance of our process a primary measure of its success? | BT49: Beauty as a Core Metric | BU49: ↑ | BV49: 1 | BW49: 5 | BX49: N/A | BY49: N/A | BZ49: Is "beauty" a formal, non-negotiable metric on par with "efficiency" in all operational reviews? | CA49: 0
A50: Core Operations (F8) | B50: Operational Viability | C50: Water | D50: Is energy flowing into the work? | E50: Founder Hours Logged on Core Ops | F50: Band | G50: 1 | H50: 0 | I50: 5 | J50: 10 | K50: 20 | L50: The sustainable input of creative "lifeblood." Too little is stagnation; too much starves other domains. | M50: =IF(AND(Octave_1_KPIs[[#This Row],[Value]] >= Octave_1_KPIs[[#This Row],[Healthy_Min]], Octave_1_KPIs[[#This Row],[Value]] <= Octave_1_KPIs[[#This Row],[Healthy_Max]]), 1, IF(Octave_1_KPIs[[#This Row],[Value]] < Octave_1_KPIs[[#This Row],[Healthy_Min]], MAX(0, (Octave_1_KPIs[[#This Row],[Value]] - Octave_1_KPIs[[#This Row],[Target_Min]]) / (Octave_1_KPIs[[#This Row],[Healthy_Min]] - Octave_1_KPIs[[#This Row],[Target_Min]])), MAX(0, 1 - (Octave_1_KPIs[[#This Row],[Value]] - Octave_1_KPIs[[#This Row],[Healthy_Max]]) / (Octave_1_KPIs[[#This Row],[Absolute_Max]] - Octave_1_KPIs[[#This Row],[Healthy_Max]])))) -> 0.2 | N50: Operational Throughput | O50: Water | P50: Are our workflows smooth? | Q50: Process Efficiency (Flow State) | R50: ↑ | S50: 1 | T50: 4 | U50: N/A | V50: N/A | W50: A qualitative score for how "frictionless" the core operational processes feel to the team. | X50: 0 | Y50: Collaborative Flow | Z50: Water | AA50: Does the work feel like a smooth dance? | AB50: "Felt Sense of Flow" in Ops | AC50: ↑ | AD50: 1 | AE50: 4.5 | AF50: N/A | AG50: N/A | AH50: A team survey. The emotional and energetic quality of the operational rhythm. | AI50: 0 | AJ50: Operational Innovation | AK50: Water | AL50: How quickly are we turning operational data into insights? | AM50: "Learning Velocity" from Ops Data | AN50: ↓ | AO50: 30d | AP50: 7d | AQ50: N/A | AR50: N/A | AS50: The time it takes for a key learning from operational data to be translated into a process improvement experiment. | AT50: 0 | AU50: Operational Transparency | AV50: Water | AW50: Are we sharing the human story of our work? | AX50: Flow of "Behind the Scenes" Content | AY50: Band | AZ50: 0 | BA50: 1 | BB50: 3 | BC50: 5 | BD50: A sustainable rhythm of authentic, "making-of" content per month. | BE50: 0 | BF50: Evolutionary Operations | BG50: Water | BH50: Can new, better ways of working flow up organically from the team? | BI50: Flow of "Emergent" Processes | BJ50: ↑ | BK50: 1 | BL50: 4.5 | BM50: N/A | BN50: N/A | BO50: How well does the system allow for and integrate emergent, bottom-up process innovations? | BP50: 0 | BQ50: Operations as a Living Art | BR50: Water | BS50: If our operations were music, what would it sound like? Is it a symphony? | BT50: The "Music" of Operations | BU50: ↑ | BV50: 1 | BW50: 4.8 | BX50: N/A | BY50: N/A | BZ50: A qualitative, synesthetic measure of the harmony, rhythm, and flow of the daily work. | CA50: 0
A51: Core Operations (F8) | B51: Operational Viability | C51: Fire | D51: What is the rhythm of creation? | E51: Development Cycle Time (Days per Iteration) | F51: ↓ | G51: 11 | H51: 90 | I51: 14 | J51: 7 | K51: N/A | L51: Measures the speed of the action-feedback loop. Ideal is a 7-day cycle; Min is a 90-day cycle. | M51: =MAX(0, MIN(1, 1 - ((Octave_1_KPIs[[#This Row],[Value]] - Octave_1_KPIs[[#This Row],[Healthy_Max]]) / (Octave_1_KPIs[[#This Row],[Target_Min]] - Octave_1_KPIs[[#This Row],[Healthy_Max]])))) -> 0.95180723 | N51: Operational Throughput | O51: Fire | P51: Are we delivering what we promise? | Q51: Task Completion Rate (%) | R51: ↑ | S51: 0.7 | T51: 0.95 | U51: N/A | V51: N/A | W51: The raw measure of action and output. Do we finish what we start? | X51: 0 | Y51: Collaborative Flow | Z51: Fire | AA51: How quickly do we help each other get unstuck? | AB51: Mean Time to Resolve Internal Blockers | AC51: ↓ | AD51: 48h | AE51: 4h | AF51: N/A | AG51: N/A | AH51: The speed with which the team swarms to solve internal problems and restore flow. | AI51: 0 | AJ51: Operational Innovation | AK51: Fire | AL51: Are we actively seeking a better way to work? | AM51: # of Process Improvement Experiments | AN51: Band | AO51: 0 | AP51: 1 | AQ51: 3 | AR51: 5 | AS51: A sustainable rhythm of testing new workflows, tools, and operational models per quarter. | AT51: 0 | AU51: Operational Transparency | AV51: Fire | AW51: Are we actively sharing our failures and learnings? | AX51: # of Public "Lessons Learned" | AY51: Band | AZ51: 0 | BA51: 1 | BB51: 2 | BC51: 3 | BD51: The courageous act of publishing post-mortems and sharing wisdom from mistakes per quarter. | BE51: 0 | BF51: Evolutionary Operations | BG51: Fire | BH51: Are we actively finding surprising, higher uses for our existing tools? | BI51: "Exaptation" Rate | BJ51: ↑ | BK51: 1 | BL51: 4 | BM51: N/A | BN51: N/A | BO51: (From evolutionary biology). A score for how well we repurpose existing tools and processes for novel, higher-order functions. | BP51: 0 | BQ51: Operations as a Living Art | BR51: Fire | BS51: How frequently do moments of breathtaking, un-managed genius emerge from our process? | BT51: Spontaneous Acts of Operational Genius | BU51: ↑ | BV51: Low | BW51: High | BX51: N/A | BY51: N/A | BZ51: The rate at which the team, in a state of flow, creates novel solutions that transcend the existing process. | CA51: 0
A52: Core Operations (F8) | B52: Operational Viability | C52: Air | D52: Is out process understandable? | E52: Process Documentation Clarity (1-5) | F52: ↑ | G52: 1.5 | H52: 1 | I52: 4 | J52: N/A | K52: N/A | L52: A 1-5 score. Can a new team member understand how the core work gets done? | M52: =MAX(0,MIN(1,(G52-H52)/(Octave_1_KPIs[[#This Row],[Healthy_Min]]-Octave_1_KPIs[[#This Row],[Target_Min]]))) -> 0.16666667 | N52: Operational Throughput | O52: Air | P52: Does everyone know their part in the process? | Q52: Clarity of Roles in Ops | R52: ↑ | S52: 1 | T52: 4.5 | U52: N/A | V52: N/A | W52: Clear roles are the key to efficient and harmonious operational flow. | X52: 0 | Y52: Collaborative Flow | Z52: Air | AA52: Do our teams communicate clearly with each other? | AB52: Clarity of Inter-team Communication | AC52: ↑ | AD52: 1 | AE52: 4.5 | AF52: N/A | AG52: N/A | AH52: A 1-5 score on the quality and clarity of information flow between different operational units. | AI52: 0 | AJ52: Operational Innovation | AK52: Air | AL52: Is the process for integrating new ideas clear? | AM52: Clarity of Innovation-Ops Handoff | AN52: ↑ | AO52: 1 | AP52: 4.5 | AQ52: N/A | AR52: N/A | AS52: A 1-5 score on the clarity of the process for moving a successful experiment into the core operational workflow. | AT52: 0 | AU52: Operational Transparency | AV52: Air | AW52: Are the metrics we use to run our engine clear to all? | AX52: Clarity of Operational Metrics | AY52: ↑ | AZ52: 1 | BA52: 4.8 | BB52: N/A | BC52: N/A | BD52: How clearly do we explain the "why" behind the KPIs we track internally? | BE52: 0 | BF52: Evolutionary Operations | BG52: Air | BH52: Can our entire operational model be distilled to a few clear principles? | BI52: Simplicity of Core Operating Principles | BJ52: ↓ | BK52: 10 | BL52: 3 | BM52: N/A | BN52: N/A | BO52: The ultimate sign of mastery. Can our complex "how" be explained via a handful of simple, elegant, guiding principles? | BP52: 0 | BQ52: Operations as a Living Art | BR52: Air | BS52: Can the deep wisdom of our process be expressed in a single, simple, paradoxical phrase? | BT52: The "Koan" of the Process | BU52: ↑ | BV52: 0 | BW52: 1 | BX52: N/A | BY52: N/A | BZ52: A milestone. Has the team discovered the central "koan" or elegant paradox that sits at the heart of its mastery? | CA52: 0
A53: Core Operations (F8) | B53: Operational Viability | C53: Ether | D53: Is HOW we build aligned with WHY we build? | E53: Operational-Values Alignment Score (1-5) | F53: ↑ | G53: 4 | H53: 1 | I53: 4.5 | J53: N/A | K53: N/A | L53: A 1-5 score. Measures if the development process itself is a living example of coherence. | M53: =MAX(0,MIN(1,(G53-H53)/(Octave_1_KPIs[[#This Row],[Healthy_Min]]-Octave_1_KPIs[[#This Row],[Target_Min]]))) -> 0.85714286 | N53: Operational Throughput | O53: Ether | P53: Is the team proud of the work they do? | Q53: Operational Pride | R53: ↑ | S53: 1 | T53: 4.5 | U53: N/A | V53: N/A | W53: The soul of operations. The felt sense of quality and purpose in the daily work. | X53: 0 | Y53: Collaborative Flow | Z53: Ether | AA53: Does the team feel a collective ownership of the work? | AB53: Operational Pride & Shared Ownership | AC53: ↑ | AD53: 1 | AE53: 4.8 | AF53: N/A | AG53: N/A | AH53: The ultimate measure of a coherent operational culture. | AI53: 0 | AJ53: Operational Innovation | AK53: Ether | AL53: Do we find creative joy in making our process beautiful? | AM53: Joy in Operational Craftsmanship | AN53: ↑ | AO53: 1 | AP53: 4.5 | AQ53: N/A | AR53: N/A | AS53: The felt sense of pride and artistry in the operational work itself. | AT53: 0 | AU53: Operational Transparency | AV53: Ether | AW53: Can other organizations learn from how we work? | AX53: Operational Model as a Teachable Asset | AY53: ↑ | AZ53: 1 | BA53: 4 | BB53: N/A | BC53: N/A | BD53: To what degree has our operational model itself become a piece of influential, teachable IP? | BE53: 0 | BF53: Evolutionary Operations | BG53: Ether | BH53: Is the daily work itself a path to personal and collective evolution? | BI53: Operations as a Practice of Mastery | BJ53: ↑ | BK53: 1 | BL53: 5 | BM53: N/A | BN53: N/A | BO53: The degree to which team members feel their daily operational work is a profound practice for their own growth. | BP53: 0 | BQ53: Operations as a Living Art | BR53: Ether | BS53: Is the act of working itself a profound practice of presence? | BT53: The Work is the Meditation | BU53: ↑ | BV53: 1 | BW53: 5 | BX53: N/A | BY53: N/A | BZ53: The final state where the distinction between "work," "play," and "spiritual practice" has completely dissolved. | CA53: 0
A54: Regenerative Flow (F9) | B54: Regenerative Intent & Practice | C54: Earth | D54: Are our choices grounded in action? | E54: # of Documented Regenerative Choices | F54: ↑ | G54: 0.1 | H54: 0 | I54: 1 | J54: N/A | K54: N/A | L54: This measures the habit of consideration. The goal is to consciously evaluate 100% of key choices. | M54: =MAX(0,MIN(1,(G54-H54)/(Octave_1_KPIs[[#This Row],[Healthy_Min]]-Octave_1_KPIs[[#This Row],[Target_Min]]))) -> 0.1 | N54: Regenerative Operations | O54: Earth | P54: Are our processes materially efficient? | Q54: Waste Reduction % | R54: ↑ | S54: 0 | T54: 0.25 | U54: N/A | V54: N/A | W54: A simple, grounded measure of moving towards a circular model. | X54: 0 | Y54: Stakeholder Relationships | Z54: Earth | AA54: Are we grounded in our local ecosystem? | AB54: Local Community Investment | AC54: ↑ | AD54: 0 | AE54: 0.02 | AF54: N/A | AG54: N/A | AH54: The percentage of revenue consciously reinvested into the health of the local community. | AI54: 0 | AJ54: Regenerative Design | AK54: Earth | AL54: Is our product designed to be regenerative from the start? | AM54: Circularity of Product Design | AN54: ↑ | AO54: 0.1 | AP54: 0.75 | AQ54: N/A | AR54: N/A | AS54: A score based on a checklist. What percentage of our product/service is designed according to circular principles? | AT54: 0 | AU54: Impact Storytelling | AV54: Earth | AW54: Is our regenerative claim grounded in objective proof? | AX54: Third-Party Impact Verification | AY54: ↑ | AZ54: 0 | BA54: 1 | BB54: N/A | BC54: N/A | BD54: A binary milestone. Have we had our core regenerative claims verified by a respected third party? | BE54: 0 | BF54: Generational Regeneration | BG54: Earth | BH54: Are we grounded in a truly long-term view of our impact? | BI54: 7-Generation Impact Assessment | BJ54: ↑ | BK54: 0 | BL54: 1 | BM54: N/A | BN54: N/A | BO54: A binary milestone. Have we conducted a formal analysis of the potential impact of our actions on the next seven generations? | BP54: 0 | BQ54: Creation as a Planetary Act | BR54: Earth | BS54: Are we grounded in our role as a recognized caretaker of a part of the planet? | BT54: The Organization as a Biosphere Steward | BU54: ↑ | BV54: 0 | BW54: 1 | BX54: N/A | BY54: N/A | BZ54: A milestone. Has the organization taken formal, long-term stewardship over a piece of land, an ecosystem, or a commons? | CA54: 0
A55: Regenerative Flow (F9) | B55: Regenerative Intent & Practice | C55: Water | D55: Do these choices feel right? | E55: Founder's Felt Sense of Integrity (1-5) | F55: ↑ | G55: 4.5 | H55: 1 | I55: 4.5 | J55: N/A | K55: N/A | L55: A 1-5 score. The ultimate internal, emotional compass for regenerative action. | M55: =MAX(0,MIN(1,(G55-H55)/(Octave_1_KPIs[[#This Row],[Healthy_Min]]-Octave_1_KPIs[[#This Row],[Target_Min]]))) -> 1 | N55: Regenerative Operations | O55: Water | P55: Do our eco-choices improve our culture? | Q55: Employee Well-being linked to Regen choices | R55: ↑ | S55: 1 | T55: 4 | U55: N/A | V55: N/A | W55: A qualitative measure. Does choosing a green supplier make the team feel more aligned and proud? | X55: 0 | Y55: Stakeholder Relationships | Z55: Water | AA55: Are our supplier relationships built on trust and mutual respect? | AB55: Supplier Relationship Health Score | AC55: ↑ | AD55: 1 | AE55: 4.5 | AF55: N/A | AG55: N/A | AH55: A 1-5 survey to key suppliers. | AI55: 0 | AJ55: Regenerative Design | AK55: Water | AL55: Is our design process a constant flow of awareness? | AM55: Flow of "Cradle-to-Cradle" Thinking | AN55: ↑ | AO55: 1 | AP55: 4 | AQ55: N/A | AR55: N/A | AS55: A qualitative score. How deeply is the "waste = food" principle embedded in our design and R&D culture? | AT55: 0 | AU55: Impact Storytelling | AV55: Water | AW55: Does our story of regeneration inspire a feeling of hope? | AX55: Emotional Impact of Our Story | AY55: ↑ | AZ55: 1 | BA55: 4.8 | BB55: N/A | BC55: N/A | BD55: A qualitative survey. How do people feel after reading our impact report or hearing our story? | BE55: 0 | BF55: Generational Regeneration | BG55: Water | BH55: Do our decisions embody a deep, emotional care for the future? | BI55: "Flow of Care" for Future Beings | BJ55: ↑ | BK55: 1 | BL55: 4.8 | BM55: N/A | BN55: N/A | BO55: A profound, qualitative score. Is our strategic process imbued with a felt sense of responsibility for those not yet born? | BP55: 0 | BQ55: Creation as a Planetary Act | BR55: Water | BS55: Is the net result of our existence an increase in the total life force of the planet? | BT55: The Flow of Life Force | BU55: ↑ | BV55: 1 | BW55: 5 | BX55: N/A | BY55: N/A | BZ55: The ultimate, profound measure of regeneration. Is the world more alive because we exist? | CA55: 0
A56: Regenerative Flow (F9) | B56: Regenerative Intent & Practice | C56: Fire | D56: Are we actively learning? | E56: Hours Spent Researching Regenerative Practices | F56: Band | G56: 1 | H56: 0 | I56: 1 | J56: 3 | K56: 7 | L56: The active pursuit of wisdom. A healthy rhythm of 1-3 hours/week at this stage. | M56: =IF(AND(Octave_1_KPIs[[#This Row],[Value]] >= Octave_1_KPIs[[#This Row],[Healthy_Min]], Octave_1_KPIs[[#This Row],[Value]] <= Octave_1_KPIs[[#This Row],[Healthy_Max]]), 1, IF(Octave_1_KPIs[[#This Row],[Value]] < Octave_1_KPIs[[#This Row],[Healthy_Min]], MAX(0, (Octave_1_KPIs[[#This Row],[Value]] - Octave_1_KPIs[[#This Row],[Target_Min]]) / (Octave_1_KPIs[[#This Row],[Healthy_Min]] - Octave_1_KPIs[[#This Row],[Target_Min]])), MAX(0, 1 - (Octave_1_KPIs[[#This Row],[Value]] - Octave_1_KPIs[[#This Row],[Healthy_Max]]) / (Octave_1_KPIs[[#This Row],[Absolute_Max]] - Octave_1_KPIs[[#This Row],[Healthy_Max]])))) -> 1 | N56: Regenerative Operations | O56: Fire | P56: Are we actively making our ops greener? | Q56: # of Regenerative Process Improvements | R56: Band | S56: 0 | T56: 1 | U56: 3 | V56: 5 | W56: A sustainable rhythm of conscious improvements per quarter. | X56: 0 | Y56: Stakeholder Relationships | Z56: Fire | AA56: Are we actively listening to our ecosystem? | AB56: # of Proactive Stakeholder Engagements | AC56: Band | AD56: 0 | AE56: 1 | AF56: 3 | AG56: 5 | AH56: A sustainable rhythm of proactive outreach sessions (town halls, feedback forums) per quarter. | AI56: 0 | AJ56: Regenerative Design | AK56: Fire | AL56: Are we actively creating things that heal? | AM56: # of Products/Features with Net-Positive Impact | AN56: ↑ | AO56: 0 | AP56: 1 | AQ56: N/A | AR56: N/A | AS56: At this stage, creating one flagship feature or product that is demonstrably regenerative is a huge milestone. | AT56: 0 | AU56: Impact Storytelling | AV56: Fire | AW56: Are we actively telling the stories of our impact? | AX56: # of Impact Cases Published | AY56: Band | AZ56: 0 | BA56: 1 | BB56: 2 | BC56: 4 | BD56: A sustainable rhythm of well-crafted case studies per year. | BE56: 0 | BF56: Generational Regeneration | BG56: Fire | BH56: Are we actively seeding projects that will outlive us? | BI56: # of Projects with a 100+ Year Horizon | BJ56: Band | BK56: 0 | BL56: 1 | BM56: 1 | BN56: 2 | BO56: A single, profoundly ambitious, "cathedral project" is a massive signal of long-term vision. | BP56: 0 | BQ56: Creation as a Planetary Act | BR56: Fire | BS56: Are we actively using our surplus to create other, independent regenerative ventures? | BT56: Seeding of New Regenerative Worlds | BU56: ↑ | BV56: 0 | BW56: 1 | BX56: N/A | BY56: N/A | BZ56: A measure of generativity. Are we a "star nursery," actively birthing new, coherent systems into the world? | CA56: 0
A57: Regenerative Flow (F9) | B57: Regenerative Intent & Practice | C57: Air | D57: Are we communicating this value? | E57: Clarity of Public Stance on Regeneration (1-5) | F57: ↑ | G57: 2.1 | H57: 1 | I57: 4 | J57: N/A | K57: N/A | L57: A 1-5 score. How clearly is this value expressed to the outside world? | M57: =MAX(0,MIN(1,(G57-H57)/(Octave_1_KPIs[[#This Row],[Healthy_Min]]-Octave_1_KPIs[[#This Row],[Target_Min]]))) -> 0.36666667 | N57: Regenerative Operations | O57: Air | P57: Do we know where our resources come from? | Q57: Clarity of Supply Chain Ethics | R57: ↑ | S57: 1 | T57: 4.5 | U57: N/A | V57: N/A | W57: The clarity and transparency of your entire supply chain. | X57: 0 | Y57: Stakeholder Relationships | Z57: Air | AA57: Is our impact on stakeholders clear and honest? | AB57: Clarity of Stakeholder Impact Report | AC57: ↑ | AD57: 1 | AE57: 4.8 | AF57: N/A | AG57: N/A | AH57: The quality and transparency of reporting on our social and ecological impact. | AI57: 0 | AJ57: Regenerative Design | AK57: Air | AL57: Do we clearly understand the full impact of our creations? | AM57: Clarity of "Life Cycle Assessment" | AN57: ↑ | AO57: 0 | AP57: 1 | AQ57: N/A | AR57: N/A | AS57: A binary score. Have we completed a formal or informal Life Cycle Assessment for our core offering? | AT57: 0 | AU57: Impact Storytelling | AV57: Air | AW57: Is our impact data radical in its transparency? | AX57: Clarity and Honesty of Impact Data | AY57: ↑ | AZ57: 1 | BA57: 5 | BB57: N/A | BC57: N/A | BD57: A 1-5 score. Do we share the failures and challenges with the same clarity as our successes? | BE57: 0 | BF57: Generational Regeneration | BG57: Air | BH57: Is the long-term positive impact we want to create crystal clear? | BI57: Clarity of our Regenerative Legacy | BJ57: ↑ | BK57: 1 | BL57: 5 | BM57: N/A | BN57: N/A | BO57: Can we articulate, with perfect clarity, the regenerative legacy we intend to leave? | BP57: 0 | BQ57: Creation as a Planetary Act | BR57: Air | BS57: Have we become a clear and powerful voice for the planet, for future generations, for non-human beings? | BT57: The Voice of the Voiceless | BU57: ↑ | BV57: 1 | BW57: 5 | BX57: N/A | BY57: N/A | BZ57: Does our organization act as a channel and an advocate for the parts of the system that cannot speak for themselves? | CA57: 0
A58: Regenerative Flow (F9) | B58: Regenerative Intent & Practice | C58: Ether | D58: Are we connected to the larger whole? | E58: Felt Connection to Planetary Purpose (1-5) | F58: ↑ | G58: 4.5 | H58: 1 | I58: 4.5 | J58: N/A | K58: N/A | L58: A 1-5 score. The ultimate measure of the "why" behind the regenerative impulse. | M58: =MAX(0,MIN(1,(G58-H58)/(Octave_1_KPIs[[#This Row],[Healthy_Min]]-Octave_1_KPIs[[#This Row],[Target_Min]]))) -> 1 | N58: Regenerative Operations | O58: Ether | P58: Are our operations healing or harming? | Q58: Operational Regeneration Index | R58: ↑ | S58: 0 | T58: 1 | U58: N/A | V58: N/A | W58: The Edge KPI. A sophisticated composite score measuring the net regenerative impact of all ops. | X58: 0 | Y58: Stakeholder Relationships | Z58: Ether | AA58: Do we feel we are all in this together? | AB58: "Sense of Shared Fate" with Stakeholders | AC58: ↑ | AD58: 1 | AE58: 4.5 | AF58: N/A | AG58: N/A | AH58: A qualitative measure of the deepest level of systemic and planetary alignment. | AI58: 0 | AJ58: Regenerative Design | AK58: Ether | AL58: Is our creative process an expression of planetary care? | AM58: Design as an Act of Love for the Planet | AN58: ↑ | AO58: 1 | AP58: 5 | AQ58: N/A | AR58: N/A | AS58: The ultimate, qualitative measure of the soul of the creative process. | AT58: 0 | AU58: Impact Storytelling | AV58: Ether | AW58: Is our story helping to write a new story for the world? | AX58: Our Story's Contribution to the Planetary Narrative | AY58: ↑ | AZ58: 1 | BA58: 4.5 | BB58: N/A | BC58: N/A | BD58: Does our impact story serve the larger purpose of shifting the global conversation towards regeneration? | BE58: 0 | BF58: Generational Regeneration | BG58: Ether | BH58: Do we see ourselves as caretakers for a small piece of the Earth? | BI58: Organization as a Planetary Steward | BJ58: ↑ | BK58: 1 | BL58: 5 | BM58: N/A | BN58: N/A | BO58: The ultimate shift in identity, from a business that "does" regeneration to a being that is a steward. | BP58: 0 | BQ58: Creation as a Planetary Act | BR58: Ether | BS58: Have we realized we are not "healing the Earth," but are an expression of the Earth's own impulse to heal? | BT58: The Organization is the Earth Healing Itself | BU58: ↑ | BV58: 1 | BW58: 5 | BX58: N/A | BY58: N/A | BZ58: The final, Monad-level insight of non-duality and total ecological embedding. | CA58: 0
A59: Foundational Values (F10) | B59: Lived Values & Cultural Integrity | C59: Earth | D59: Are values embedded in our decisions? | E59: # of Documented "Value Alignment Checks" | F59: ↑ | G59: 0.9 | H59: 0 | I59: 1 | J59: N/A | K59: N/A | L59: The habit of integrity. We aim to check 100% of key strategic decisions against our values. | M59: =MAX(0,MIN(1,(G59-H59)/(Octave_1_KPIs[[#This Row],[Healthy_Min]]-Octave_1_KPIs[[#This Row],[Target_Min]]))) -> 0.9 | N59: Formalized Cultural Systems | O59: Earth | P59: Are values embedded in our formal systems? | Q59: Values Embodiment Score | R59: ↑ | S59: 1 | T59: 4.5 | U59: N/A | V59: N/A | W59: The Edge KPI. How well are values reflected in hiring, performance reviews, etc.? | X59: 0 | Y59: Values in Relationship | Z59: Earth | AA59: Are values grounded in our relationships? | AB59: Values Embodiment Score | AC59: ↑ | AD59: 1 | AE59: 4.5 | AF59: N/A | AG59: N/A | AH59: An Edge KPI. A 360-degree review score on how well team members feel their peers embody the core values. | AI59: 0 | AJ59: Evolution of Values | AK59: Earth | AL59: Do our values remain a stable ground during rapid change? | AM59: Resilience of Values Under Creative Stress | AN59: ↑ | AO59: 1 | AP59: 4.5 | AQ59: N/A | AR59: N/A | AS59: A qualitative score. When a brilliant but "edgy" new idea appears, do our values provide a clear filter or do they buckle? | AT59: 0 | AU59: Values as a Beacon | AV59: Earth | AW59: Are our values grounded in a clear, public artifact? | AX59: Public Statement of Values | AY59: ↑ | AZ59: 1 | BA59: 5 | BB59: N/A | BC59: N/A | BD59: Is there a beautifully crafted, easily accessible page or document that states what we stand for? | BE59: 0 | BF59: Timeless Values | BG59: Earth | BH59: Are our core values embedded in a rock-solid, timeless "constitution"? | BI59: Constitutional Integrity | BJ59: ↑ | BK59: 1 | BL59: 5 | BM59: N/A | BN59: N/A | BO59: The degree to which the venture's deepest principles are protected in its foundational legal and governance documents. | BP59: 0 | BQ59: Values as Universal Law | BR59: Earth | BS59: Are our values so stable and universal they serve as a constitution for our entire ecosystem? | BT59: The Values as a Public Constitution | BU59: ↑ | BV59: 1 | BW59: 4.8 | BX59: N/A | BY59: N/A | BZ59: Are other organizations voluntarily "ratifying" our core values as part of their own governance? | CA59: 0
A60: Foundational Values (F10) | B60: Lived Values & Cultural Integrity | C60: Water | D60: Does the team feel the values are real? | E60: Cultural Integrity Score (Team Poll, 1-10) | F60: ↑ | G60: 9 | H60: 1 | I60: 9 | J60: N/A | K60: N/A | L60: A 1-10 team poll. The emotional truth of the culture. | M60: =MAX(0,MIN(1,(G60-H60)/(Octave_1_KPIs[[#This Row],[Healthy_Min]]-Octave_1_KPIs[[#This Row],[Target_Min]]))) -> 1 | N60: Formalized Cultural Systems | O60: Water | P60: How well does information and empathy flow? | Q60: Internal Communication Flow | R60: ↑ | S60: 1 | T60: 4 | U60: N/A | V60: N/A | W60: A measure of the health of the internal "circulatory system." | X60: 0 | Y60: Values in Relationship | Z60: Water | AA60: Do our internal communications feel compassionate? | AB60: Empathy Score in Communications | AC60: ↑ | AD60: 1 | AE60: 4.5 | AF60: N/A | AG60: N/A | AH60: A qualitative score, perhaps using AI semantic analysis or team surveys on internal emails and messages. | AI60: 0 | AJ60: Evolution of Values | AK60: Water | AL60: Is our understanding of our own values deepening? | AM60: Flow of New Insights into our Value System | AN60: ↑ | AO60: 1 | AP60: 4 | AQ60: N/A | AR60: N/A | AS60: How well is the organization learning and evolving its interpretation of its core values as it grows? | AT60: 0 | AU60: Values as a Beacon | AV60: Water | AW60: Does the world feel our values are real? | AX60: "Felt Authenticity" of Public Values | AY60: ↑ | AZ60: 1 | BA60: 4.5 | BB60: N/A | BC60: N/A | BD60: An external survey. Do partners and customers perceive our lived actions as being aligned with our stated values? | BE60: 0 | BF60: Timeless Values | BG60: Water | BH60: How well are our values passed on to new generations of the team? | BI60: "Transmission Fidelity" of Values | BJ60: ↑ | BK60: 0.75 | BL60: 0.95 | BM60: N/A | BN60: N/A | BO60: A measure of the effectiveness of the cultural onboarding process. | BP60: 0 | BQ60: Values as Universal Law | BR60: Water | BS60: When people encounter our values, do they feel a sense of profound, self-evident truth? | BT60: The "Felt Sense" of Universal Truth | BU60: ↑ | BV60: 1 | BW60: 5 | BX60: N/A | BY60: N/A | BZ60: The degree to which our values resonate not as opinions, but as archetypes of universal law. | CA60: 0
A61: Foundational Values (F10) | B61: Lived Values & Cultural Integrity | C61: Fire | D61: Are we actively discussing our values? | E61: Time Spent in Values-Based Discussions | F61: Band | G61: 3 | H61: 0 | I61: 1 | J61: 2 | K61: 5 | L61: The active practice of keeping the values alive. A healthy rhythm is 1-2 hours/month. | M61: =IF(AND(Octave_1_KPIs[[#This Row],[Value]] >= Octave_1_KPIs[[#This Row],[Healthy_Min]], Octave_1_KPIs[[#This Row],[Value]] <= Octave_1_KPIs[[#This Row],[Healthy_Max]]), 1, IF(Octave_1_KPIs[[#This Row],[Value]] < Octave_1_KPIs[[#This Row],[Healthy_Min]], MAX(0, (Octave_1_KPIs[[#This Row],[Value]] - Octave_1_KPIs[[#This Row],[Target_Min]]) / (Octave_1_KPIs[[#This Row],[Healthy_Min]] - Octave_1_KPIs[[#This Row],[Target_Min]])), MAX(0, 1 - (Octave_1_KPIs[[#This Row],[Value]] - Octave_1_KPIs[[#This Row],[Healthy_Max]]) / (Octave_1_KPIs[[#This Row],[Absolute_Max]] - Octave_1_KPIs[[#This Row],[Healthy_Max]])))) -> 0.66666667 | N61: Formalized Cultural Systems | O61: Fire | P61: Are we actively nurturing our culture? | Q61: # of Community-Building Rituals | R61: Band | S61: 0 | T61: 1 | U61: 2 | V61: 4 | W61: A sustainable rhythm of rituals (e.g., weekly check-ins, monthly celebrations) per month. | X61: 0 | Y61: Values in Relationship | Z61: Fire | AA61: Are we actively addressing value misalignments? | AB61: # of Courageous Conversations | AC61: Band | AD61: 0 | AE61: 1 | AF61: 2 | AG61: 4 | AH61: The number of facilitated, intentional conversations per month to heal cultural dissonances. | AI61: 0 | AJ61: Evolution of Values | AK61: Fire | AL61: Are we actively exploring the challenging edges of our ethics? | AM61: # of "Values Edge" Conversations | AN61: Band | AO61: 0 | AP61: 1 | AQ61: 2 | AR61: 3 | AS61: A healthy rhythm of conversations per quarter focused on the most difficult ethical questions related to our innovations. | AT61: 0 | AU61: Values as a Beacon | AV61: Fire | AW61: Are our leaders actively speaking from our values? | AX61: Leadership's Active Voice on Values | AY61: Band | AZ61: 0 | BA61: 1 | BB61: 4 | BC61: 8 | BD61: A rhythm of articles, talks, or posts per quarter where leadership explicitly connects strategy to values. | BE61: 0 | BF61: Timeless Values | BG61: Fire | BH61: Do we actively and courageously defend our values, even when it's costly? | BI61: Active Defense of Values | BJ61: ↑ | BK61: 1 | BL61: 5 | BM61: N/A | BN61: N/A | BO61: A score based on real-world case studies. When faced with a choice between values and profit/convenience, which do we choose? | BP61: 0 | BQ61: Values as Universal Law | BR61: Fire | BS61: Are our values a "benevolent virus" of coherence that spreads effortlessly? | BT61: Values as an Irresistible, Spreading Fire | BU61: ↑ | BV61: Low | BW61: High | BX61: N/A | BY61: N/A | BZ61: The "viral coefficient" of our core ethical and philosophical principles. | CA61: 0
A62: Foundational Values (F10) | B62: Lived Values & Cultural Integrity | C62: Air | D62: Are our values clearly stated? | E62: Clarity of Published Values Statement (1-5) | F62: ↑ | G62: 0 | H62: 1 | I62: 4.5 | J62: N/A | K62: N/A | L62: A 1-5 score. How well are the values articulated to the world? | M62: =MAX(0,MIN(1,(G62-H62)/(Octave_1_KPIs[[#This Row],[Healthy_Min]]-Octave_1_KPIs[[#This Row],[Target_Min]]))) -> 0 | N62: Formalized Cultural Systems | O62: Air | P62: Are our shared rules clear and explicit? | Q62: Clarity of Code of Conduct | R62: ↑ | S62: 1 | T62: 5 | U62: N/A | V62: N/A | W62: A perfectly clear, written articulation of the cultural "rules of the road." | X62: 0 | Y62: Values in Relationship | Z62: Air | AA62: Can team members give clear examples of our values in action? | AB62: Understanding of Values in Action | AC62: ↑ | AD62: 0.5 | AE62: 0.95 | AF62: N/A | AG62: N/A | AH62: The percentage of the team that can articulate a recent, concrete example of a core value being lived. | AI62: 0 | AJ62: Evolution of Values | AK62: Air | AL62: Are our brightest red lines crystal clear to all? | AM62: Clarity of "Ethical Non-Negotiables" | AN62: ↑ | AO62: 1 | AP62: 5 | AQ62: N/A | AR62: N/A | AS62: Are the absolute ethical boundaries, the things we will never do for profit or growth, perfectly clear to everyone? | AT62: 0 | AU62: Values as a Beacon | AV62: Air | AW62: Are our values simple enough to live by? | AX62: Simplicity & Memorability of Values | AY62: ↑ | AZ62: 1 | BA62: 4.8 | BB62: N/A | BC62: N/A | BD62: Are the core values articulated in a clear, memorable, and non-jargony way? | BE62: 0 | BF62: Timeless Values | BG62: Air | BH62: Are our values clear and resonant across all cultures and times? | BI62: Universalizability of Values | BJ62: ↑ | BK62: 1 | BL62: 4.5 | BM62: N/A | BN62: N/A | BO62: How well are our values based on deep, universal, archetypal principles rather than narrow, temporary beliefs? | BP62: 0 | BQ62: Values as Universal Law | BR62: Air | BS62: Can our entire ethical system be expressed in a single, universally understood principle? | BT62: The Simplicity of Ultimate Truth | BU62: ↑ | BV62: 0 | BW62: 1 | BX62: N/A | BY62: N/A | BZ62: A milestone. Have we discovered the "golden rule" at the heart of our entire constitutional framework? | CA62: 0
A63: Foundational Values (F10) | B63: Lived Values & Cultural Integrity | C63: Ether | D63: Is this an authentic expression of who we are? | E63: Perceived Authenticity of Values (Founder Score, 1-5) | F63: ↑ | G63: 5 | H63: 1 | I63: 5 | J63: N/A | K63: N/A | L63: A 1-5 founder score. The final, sovereign check of authenticity. | M63: =MAX(0,MIN(1,(G63-H63)/(Octave_1_KPIs[[#This Row],[Healthy_Min]]-Octave_1_KPIs[[#This Row],[Target_Min]]))) -> 1 | N63: Formalized Cultural Systems | O63: Ether | P63: Does the team feel the culture is authentic? | Q63: Cultural Integrity Score | R63: ↑ | S63: 1 | T63: 4.5 | U63: N/A | V63: N/A | W63: A team poll. The ultimate measure of the soul of the lived culture. | X63: 0 | Y63: Values in Relationship | Z63: Ether | AA63: Does our culture feel like a true and safe home? | AB63: Cultural Integrity Score | AC63: ↑ | AD63: 1 | AE63: 4.8 | AF63: N/A | AG63: N/A | AH63: A team poll. The ultimate measure of the soul of the lived culture. | AI63: 0 | AJ63: Evolution of Values | AK63: Ether | AL63: Do our values themselves inspire new creations? | AM63: Values as a Source of Innovation | AN63: ↑ | AO63: 1 | AP63: 4.5 | AQ63: N/A | AR63: N/A | AS63: To what degree are our best new ideas born directly from a deep meditation on our core values? | AT63: 0 | AU63: Values as a Beacon | AV63: Ether | AW63: Do our values inspire people, even outside our company? | AX63: Values as a Source of Public Inspiration | AY63: ↑ | AZ63: 1 | BA63: 4.5 | BB63: N/A | BC63: N/A | BD63: To what degree are our values becoming a "north star" that helps others navigate their own journeys? | BE63: 0 | BF63: Timeless Values | BG63: Ether | BH63: Do our values connect us to the timeless and the transcendent? | BI63: Values as a Connection to the Sacred | BJ63: ↑ | BK63: 1 | BL63: 5 | BM63: N/A | BN63: N/A | BO63: The ultimate purpose of values: to be a bridge between the mundane and the magnificent. | BP63: 0 | BQ63: Values as Universal Law | BR63: Ether | BS63: Have we transcended the need for "values" because our every action is a direct expression of coherence? | BT63: There is Only Coherence | BU63: ↑ | BV63: 1 | BW63: 5 | BX63: N/A | BY63: N/A | BZ63: The final state, where ethics are no longer a filter for action, but are the very source of action itself. | CA63: 0
A64: Funding Pipeline (F11) | B64: Pipeline Viability & Coherence | C64: Earth | D64: Do we have a target list? | E64: # of Potential Funders Identified | F64: ↑ | G64: 1 | H64: 0 | I64: 20 | J64: N/A | K64: N/A | L64: The raw material for the pipeline. A list of 20 well-researched, aligned prospects is a solid foundation. | M64: =MAX(0,MIN(1,(G64-H64)/(Octave_1_KPIs[[#This Row],[Healthy_Min]]-Octave_1_KPIs[[#This Row],[Target_Min]]))) -> 0.05 | N64: Financial System Integrity | O64: Earth | P64: Do our financial systems meet professional standards? | Q64: Investor Readiness Score | R64: ↑ | S64: 0 | T64: 1 | U64: N/A | V64: N/A | W64: The Edge KPI. A checklist score measuring the robustness of your financial documentation. | X64: 0 | Y64: Investor Relationships | Z64: Earth | AA64: Do our funders have a stable trust in our team and vision? | AB64: Investor Trust & Confidence Score | AC64: ↑ | AD64: 1 | AE64: 4.5 | AF64: N/A | AG64: N/A | AH64: A 1-5 survey to key investors. | AI64: 0 | AJ64: Creative Capital | AK64: Earth | AL64: Is our creativity grounded in a real financial commitment? | AM64: R&D Investment as a % of Revenue | AN64: ↑ | AO64: 0.01 | AP64: 0.15 | AQ64: N/A | AR64: N/A | AS64: A duplicate, confirming its importance. The financial bedrock of innovation. | AT64: 0 | AU64: Capital as Communication | AV64: Earth | AW64: Is the foundation of our capital clear to all? | AX64: Transparency of Funding Sources | AY64: ↑ | AZ64: 1 | BA64: 5 | BB64: N/A | BC64: N/A | BD64: Are we radically transparent about who has funded us and under what terms? | BE64: 0 | BF64: Legacy Capital | BG64: Earth | BH64: Is our financial vision grounded in a structure of permanence? | BI64: Creation of an Endowment / Foundation | BJ64: ↑ | BK64: 1 | BL64: 1 | BM64: N/A | BN64: N/A | BO64: A binary milestone. Have we created a legal and financial structure designed to carry the mission forward for generations? | BP64: 0 | BQ64: Capital as a Field of Grace | BR64: Earth | BS64: Is our financial body a self-sustaining, permanent gift to the world? | BT64: The Venture as a Permanent Endowment | BU64: ↑ | BV64: 0 | BW64: 1 | BX64: N/A | BY64: N/A | BZ64: The milestone of becoming a fully endowed, self-sustaining foundation that exists purely for its mission. | CA64: 0
A65: Funding Pipeline (F11) | B65: Pipeline Viability & Coherence | C65: Water | D65: Are we building relationships? | E65: Strength of Relationship with Top Prospects (1-5) | F65: ↑ | G65: 2 | H65: 1 | I65: 4 | J65: N/A | K65: N/A | L65: A 1-5 score for the quality of the relationship with the top 3-5 prospects. | M65: =MAX(0,MIN(1,(G65-H65)/(Octave_1_KPIs[[#This Row],[Healthy_Min]]-Octave_1_KPIs[[#This Row],[Target_Min]]))) -> 0.33333333 | N65: Financial System Integrity | O65: Water | P65: How accurate is our financial forecasting? | Q65: Predictability of Financial Projections | R65: ↑ | S65: 0.5 | T65: 0.85 | U65: N/A | V65: N/A | W65: Measures the forecast variance. How well do we understand the financial flow of our own venture? | X65: 0 | Y65: Investor Relationships | Z65: Water | AA65: Is there a healthy, transparent flow of information? | AB65: Flow of Communication with Investors | AC65: Band | AD65: 1 | AE65: 2 | AF65: 4 | AG65: 8 | AH65: A sustainable rhythm of updates and conversations per quarter. Not too much, not too little. | AI65: 0 | AJ65: Creative Capital | AK65: Water | AL65: Is there a liquid pool of capital for pure experimentation? | AM65: Funding for Experimental "Crazy Ideas" | AN65: ↑ | AO65: 0 | AP65: 0.1 | AQ65: N/A | AR65: N/A | AS65: What percentage of the R&D budget is explicitly "un--pegged," available for high-risk, high-reward explorations? | AT65: 0 | AU65: Capital as Communication | AV65: Water | AW65: Do our investors feel a deep connection to our narrative? | AX65: Investor's "Felt Resonance" with our Story | AY65: ↑ | AZ65: 1 | BA65: 4.5 | BB65: N/A | BC65: N/A | BD65: A qualitative score. Do our capital partners feel like true co-authors of our story? | BE65: 0 | BF65: Legacy Capital | BG65: Water | BH65: What is the emotional time-horizon of our funders? | BI65: "Patient Capital" Ratio | BJ65: ↑ | BK65: 1y | BL65: 20y | BM65: N/A | BN65: N/A | BO65: The weighted-average time horizon of our primary capital partners. The goal is to be funded by "cathedral-builders." | BP65: 0 | BQ65: Capital as a Field of Grace | BR65: Water | BS65: Does capital and energy flow to us, and through us, without resistance or fear? | BT65: The Effortless Flow of Abundance | BU65: ↑ | BV65: 1 | BW65: 5 | BX65: N/A | BY65: N/A | BZ65: The final state of economic flow, where "fundraising" is replaced by the magnetic attraction of resonant resources. | CA65: 0
A66: Funding Pipeline (F11) | B66: Pipeline Viability & Coherence | C66: Fire | D66: Are we making the ask? | E66: # of Funding Opportunities Pursued | F66: Band | G66: 0 | H66: 0 | I66: 1 | J66: 4 | K66: 10 | L66: The rhythm of action. We have already perfected the logic of this plateau. | M66: =IF(AND(Octave_1_KPIs[[#This Row],[Value]] >= Octave_1_KPIs[[#This Row],[Healthy_Min]], Octave_1_KPIs[[#This Row],[Value]] <= Octave_1_KPIs[[#This Row],[Healthy_Max]]), 1, IF(Octave_1_KPIs[[#This Row],[Value]] < Octave_1_KPIs[[#This Row],[Healthy_Min]], MAX(0, (Octave_1_KPIs[[#This Row],[Value]] - Octave_1_KPIs[[#This Row],[Target_Min]]) / (Octave_1_KPIs[[#This Row],[Healthy_Min]] - Octave_1_KPIs[[#This Row],[Target_Min]])), MAX(0, 1 - (Octave_1_KPIs[[#This Row],[Value]] - Octave_1_KPIs[[#This Row],[Healthy_Max]]) / (Octave_1_KPIs[[#This Row],[Absolute_Max]] - Octave_1_KPIs[[#This Row],[Healthy_Max]])))) -> 0 | N66: Financial System Integrity | O66: Fire | P66: How quickly can we close our books? | Q66: Speed of Financial Reporting | R66: ↓ | S66: 15d | T66: 3d | U66: N/A | V66: N/A | W66: The speed and efficiency of the core accounting process at the end of each month. | X66: 0 | Y66: Investor Relationships | Z66: Fire | AA66: Are we actively serving our financial partners? | AB66: Speed of Response to Investor Queries | AC66: ↓ | AD66: 72h | AE66: 24h | AF66: N/A | AG66: N/A | AH66: The speed and quality of response to investor questions and needs. | AI66: 0 | AJ66: Creative Capital | AK66: Fire | AL66: Are we actively attracting capital that understands innovation? | AM66: Venture Capital / "Smart Money" Attraction | AN66: ↑ | AO66: 1 | AP66: 4.5 | AQ66: N/A | AR66: N/A | AS66: A 1-5 score on the quality of the venture's relationships with investors who specialize in deep tech or paradigm-shifting ideas. | AT66: 0 | AU66: Capital as Communication | AV66: Fire | AW66: Are we actively nurturing the narrative with our investors? | AX66: # of Proactive Investor Updates | AY66: Band | AZ66: 1 | BA66: 2 | BB66: 4 | BC66: 8 | BD66: A healthy, rhythmic flow of deep and authentic updates to financial partners per quarter. | BE66: 0 | BF66: Legacy Capital | BG66: Fire | BH66: Are we actively funding research that may not pay off for decades? | BI66: Investment in "Deep Future" R&D | BJ66: ↑ | BK66: 0 | BL66: 0.05 | BM66: N/A | BN66: N/A | BO66: The percentage of the R&D budget allocated to pure, foundational research with a 20+ year time horizon. | BP66: 0 | BQ66: Capital as a Field of Grace | BR66: Fire | BS66: Does our capital actively and continuously seed new, independent, coherent ventures? | BT66: The Spontaneous Generation of New Worlds | BU66: ↑ | BV66: Low | BW66: High | BX66: N/A | BY66: N/A | BZ66: The ultimate act of generativity: our surplus is the soil for a thousand new forests. | CA66: 0
A67: Funding Pipeline (F11) | B67: Pipeline Viability & Coherence | C67: Air | D67: Is our ask clear and compelling? | E67: Clarity of Financial Ask (1-5) | F67: ↑ | G67: 1.5 | H67: 1 | I67: 4.5 | J67: N/A | K67: N/A | L67: A 1-5 score for the quality of the pitch deck and financial model. | M67: =MAX(0,MIN(1,(G67-H67)/(Octave_1_KPIs[[#This Row],[Healthy_Min]]-Octave_1_KPIs[[#This Row],[Target_Min]]))) -> 0.14285714 | N67: Financial System Integrity | O67: Air | P67: Is our business model clear and defensible? | Q67: Clarity of Financial Model | R67: ↑ | S67: 1 | T67: 4.5 | U67: N/A | V67: N/A | W67: A 1-5 score for the clarity and logic of your financial projections. | X67: 0 | Y67: Investor Relationships | Z67: Air | AA67: Are our reports to investors clear, honest, and holistic? | AB67: Clarity of Investor Reporting | AC67: ↑ | AD67: 1 | AE67: 5 | AF67: N/A | AG67: N/A | AH67: To what degree does our reporting go beyond simple financials to share the true, coherent story of the venture? | AI67: 0 | AJ67: Creative Capital | AK67: Air | AL67: Is our strategy for funding innovation clear and compelling? | AM67: Clarity of Innovation Funding Thesis | AN67: ↑ | AO67: 1 | AP67: 4.8 | AQ67: N/A | AR67: N/A | AS67: How clearly can we articulate our long-term plan for funding the evolution of our product and vision? | AT67: 0 | AU67: Capital as Communication | AV67: Air | AW67: Is the story of our future funding needs clear and compelling? | AX67: Clarity of our Financial "Ask" | AY67: ↑ | AZ67: 1 | BA67: 4.8 | BB67: N/A | BC67: N/A | BD67: How clearly can we articulate what we need next, why we need it, and what it will create? | BE67: 0 | BF67: Legacy Capital | BG67: Air | BH67: Is our long, long-term vision for value creation clear? | BI67: Clarity of our "100-Year Plan" | BJ67: ↑ | BK67: 1 | BL67: 4.5 | BM67: N/A | BN67: N/A | BO67: How vividly can we articulate the story of the venture's role in the world a century from now? | BP67: 0 | BQ67: Capital as a Field of Grace | BR67: Air | BS67: Is the concept of ownership clear and yet totally fluid? | BT67: The Dissolution of "Ours" and "Theirs" | BU67: ↑ | BV67: 1 | BW67: 5 | BX67: N/A | BY67: N/A | BZ67: The state where resources are understood to be stewarded, not owned, and flow to wherever they can create the most coherence for the whole. | CA67: 0
A68: Funding Pipeline (F11) | B68: Pipeline Viability & Coherence | C68: Ether | D68: Is this the right money? | E68: Funding Alignment Index (from Edge KPIs) | F68: ↑ | G68: 1.5 | H68: 1 | I68: 4.5 | J68: N/A | K68: N/A | L68: The ultimate filter. A 1-5 measure of soul-level alignment with potential funders. | M68: =MAX(0,MIN(1,(G68-H68)/(Octave_1_KPIs[[#This Row],[Healthy_Min]]-Octave_1_KPIs[[#This Row],[Target_Min]]))) -> 0.14285714 | N68: Financial System Integrity | O68: Ether | P68: Is our funding strategy aligned with our soul? | Q68: Funding Alignment Index | R68: ↑ | S68: 1 | T68: 4.5 | U68: N/A | V68: N/A | W68: The Edge KPI. The ultimate check that your financial structure serves your purpose. | X68: 0 | Y68: Investor Relationships | Z68: Ether | AA68: Do our investors truly share our 'why'? | AB68: Investor-Mission Resonance | AC68: ↑ | AD68: 1 | AE68: 4.8 | AF68: N/A | AG68: N/A | AH68: A deep, qualitative assessment of the soul-level alignment with your capital partners. | AI68: 0 | AJ68: Creative Capital | AK68: Ether | AL68: Is our funding model itself an act of creative purpose? | AM68: Capital as a Fuel for Planetary Transformation | AN68: ↑ | AO68: 1 | AP68: 4.5 | AQ68: N/A | AR68: N/A | AS68: Do our investors share our deepest, Monad-level vision for what this capital is here to create? | AT68: 0 | AU68: Capital as Communication | AV68: Ether | AW68: Does how we are funded become a story that inspires others? | AX68: Our Funding Model as an Inspiring Story | AY68: ↑ | AZ68: 1 | BA68: 4.5 | BB68: N/A | BC68: N/A | BD68: Does our approach to "conscious capital" itself become an influential piece of our brand? | BE68: 0 | BF68: Legacy Capital | BG68: Ether | BH68: Do we see our capital not as ours, but as a trust for the future? | BI68: Capital as a Generational Trust | BJ68: ↑ | BK68: 1 | BL68: 5 | BM68: N/A | BN68: N/A | BO68: The ultimate shift in the consciousness of capital. | BP68: 0 | BQ68: Capital as a Field of Grace | BR68: Ether | BS68: Have we become a living embodiment of a new, more beautiful economic paradigm? | BT68: The Economy of the Gift | BU68: ↑ | BV68: 1 | BW68: 5 | BX68: N/A | BY68: N/A | BZ68: The final state, where all financial transactions are experienced as a joyful, sacred, and continuous exchange of gifts. | CA68: 0
A69: Risk & Resilience (F12) | B69: Systemic Fragility Assessment | C69: Earth | D69: Are we structurally fragile? | E69: Bus Factor | F69: ↑ | G69: 1.5 | H69: 1 | I69: 2 | J69: N/A | K69: N/A | L69: The ultimate measure of stability. We have perfected the logic of this metric. | M69: =MAX(0,MIN(1,(G69-H69)/(Octave_1_KPIs[[#This Row],[Healthy_Min]]-Octave_1_KPIs[[#This Row],[Target_Min]]))) -> 0.5 | N69: Risk Management Systems | O69: Earth | P69: Are our core systems protected? | Q69: Operational Risk Shield | R69: ↑ | S69: 1 | T69: 4.5 | U69: N/A | V69: N/A | W69: The Edge KPI. A measure of the robustness of your operational safeguards. | X69: 0 | Y69: Relational Resilience | Z69: Earth | AA69: Are we grounded in a strong support system? | AB69: "Strength of Support Network" | AC69: ↑ | AD69: 1 | AE69: 4.5 | AF69: N/A | AG69: N/A | AH69: A 1-5 qualitative score of the strength, diversity, and reliability of the founder's and team's support network. | AI69: 0 | AJ69: Innovative Resilience | AK69: Earth | AL69: Are our creative bets grounded in a resilient strategy? | AM69: Diversity of Innovation Portfolio | AN69: ↑ | AO69: 1 | AP69: 4 | AQ69: N/A | AR69: N/A | AS69: A 1-5 score. Are we balancing incremental improvements with radical new ideas, creating a resilient portfolio of innovation? | AT69: 0 | AU69: Resilience through Story | AV69: Earth | AW69: Are we grounded enough to share our biggest failures? | AX69: Publication of a "Failure Report" | AY69: ↑ | AZ69: 0 | BA69: 1 | BB69: N/A | BC69: N/A | BD69: A binary milestone. Have we had the courage to publish an annual, honest report of our biggest mistakes and learnings? | BE69: 0 | BF69: "Anti-Fragile" Vision | BG69: Earth | BH69: Is the vision held by a resilient group, not a single individual? | BI69: Redundancy of Core Vision | BJ69: ↑ | BK69: 1 | BL69: 3 | BM69: N/A | BN69: N/A | BO69: A "Bus Factor" for the vision itself. How many people in the organization are true "culture carriers" who could steward the vision? | BP69: 0 | BQ69: Resilience as Being | BR69: Earth | BS69: Is our structure so fundamentally sound it is like an eternal, beautiful knot in the fabric of spacetime? | BT69: The Organization as an Eternal Knot | BU69: ↑ | BV69: 1 | BW69: 5 | BX69: N/A | BY69: N/A | BZ69: A measure of the timeless, archetypal integrity of the venture's very form. | CA69: 0
A70: Risk & Resilience (F12) | B70: Systemic Fragility Assessment | C70: Water | D70: Are we emotionally resilient? | E70: Founder's Psychological Resilience Score (1-5) | F70: ↑ | G70: 3.33 | H70: 1 | I70: 4 | J70: N/A | K70: N/A | L70: A 1-5 self-assessment of the ability to stay centered and calm under pressure. | M70: =MAX(0,MIN(1,(G70-H70)/(Octave_1_KPIs[[#This Row],[Healthy_Min]]-Octave_1_KPIs[[#This Row],[Target_Min]]))) -> 0.77666667 | N70: Risk Management Systems | O70: Water | P70: Can the team handle pressure with grace? | Q70: Team's Psychological Resilience | R70: ↑ | S70: 1 | T70: 4 | U70: N/A | V70: N/A | W70: A qualitative assessment of the team's ability to navigate stress and uncertainty. | X70: 0 | Y70: Relational Resilience | Z70: Water | AA70: Can the team navigate stress with grace and flow? | AB70: Team's Emotional Regulation Capacity | AC70: ↑ | AD70: 1 | AE70: 4 | AF70: N/A | AG70: N/A | AH70: A qualitative assessment of the team's ability to stay centered during a crisis. | AI70: 0 | AJ70: Innovative Resilience | AK70: Water | AL70: How quickly and gracefully do we pivot from what isn't working? | AM70: Speed of Learning from Failed Experiments | AN70: ↓ | AO70: 30d | AP70: 3d | AQ70: N/A | AR70: N/A | AS70: The "pivot velocity." The time it takes from declaring an experiment a "noble failure" to fully integrating the learnings and reallocating the resources. | AT70: 0 | AU70: Resilience through Story | AV70: Water | AW70: When things go wrong, do we speak from the heart? | AX70: Emotional Honesty in Crisis Comms. | AY70: ↑ | AZ70: 1 | BA70: 5 | BB70: N/A | BC70: N/A | BD70: A score for the authenticity, speed, and compassion of communication during a crisis. | BE70: 0 | BF70: "Anti-Fragile" Vision | BG70: Water | BH70: Can we remain in a state of creative flow amidst profound, long-term ambiguity? | BI70: "Flow State" in the Face of Deep Uncertainty | BJ70: ↑ | BK70: 1 | BL70: 4.5 | BM70: N/A | BN70: N/A | BO70: The team's ability to dance with the unknown without needing to collapse into rigid, certain plans. | BP70: 0 | BQ70: Resilience as Being | BR70: Water | BS70: Is the core of our being a state of unshakable, profound peace, even in the midst of cosmic storms? | BT70: The Ocean of Calm | BU70: ↑ | BV70: 1 | BW70: 5 | BX70: N/A | BY70: N/A | BZ70: The ultimate state of organizational consciousness. | CA70: 0
A71: Risk & Resilience (F12) | B71: Systemic Fragility Assessment | C71: Fire | D71: Are we preparing for the future? | E71: Hours Spent in Scenario Planning | F71: Band | G71: 1 | H71: 0 | I71: 1 | J71: 2 | K71: 5 | L71: The active practice of "wargaming" against potential threats. A healthy rhythm of 1-2 hours/quarter. | M71: =IF(AND(Octave_1_KPIs[[#This Row],[Value]] >= Octave_1_KPIs[[#This Row],[Healthy_Min]], Octave_1_KPIs[[#This Row],[Value]] <= Octave_1_KPIs[[#This Row],[Healthy_Max]]), 1, IF(Octave_1_KPIs[[#This Row],[Value]] < Octave_1_KPIs[[#This Row],[Healthy_Min]], MAX(0, (Octave_1_KPIs[[#This Row],[Value]] - Octave_1_KPIs[[#This Row],[Target_Min]]) / (Octave_1_KPIs[[#This Row],[Healthy_Min]] - Octave_1_KPIs[[#This Row],[Target_Min]])), MAX(0, 1 - (Octave_1_KPIs[[#This Row],[Value]] - Octave_1_KPIs[[#This Row],[Healthy_Max]]) / (Octave_1_KPIs[[#This Row],[Absolute_Max]] - Octave_1_KPIs[[#This Row],[Healthy_Max]])))) -> 1 | N71: Risk Management Systems | O71: Fire | P71: Are we actively preparing for threats? | Q71: # of Risk Scenarios Modeled | R71: Band | S71: 0 | T71: 1 | U71: 3 | V71: 5 | W71: A sustainable rhythm of proactive "wargaming" sessions per quarter. | X71: 0 | Y71: Relational Resilience | Z71: Fire | AA71: How quickly and effectively do we repair trust when it is broken? | AB71: Speed of Relational Repair | AC71: ↓ | AD71: 14d | AE71: 1d | AF71: N/A | AG71: N/A | AH71: The mean time to resolve a significant interpersonal or inter-team conflict. | AI71: 0 | AJ71: Innovative Resilience | AK71: Fire | AL71: Are we actively using innovation to get stronger from shocks? | AM71: "Anti-Fragility" through Innovation | AN71: ↑ | AO71: 1 | AP71: 4.5 | AQ71: N/A | AR71: N/A | AS71: Do we respond to a crisis or a market shift with a creative, innovative response that makes us more resilient than we were before? | AT71: 0 | AU71: Resilience through Story | AV71: Fire | AW71: Are we actively and openly stress-testing our own ideas? | AX71: # of Proactive "Red Team" Exercises Shared | AY71: Band | AZ71: 0 | BA71: 1 | BB71: 2 | BC71: 3 | BD71: A rhythm of publicly sharing the results of exercises where we invite others to challenge our most cherished assumptions. | BE71: 0 | BF71: "Anti-Fragile" Vision | BG71: Fire | BH71: Are we actively preparing for deep, systemic shocks? | BI71: Active "Wargaming" of Civilizational Shifts | BJ71: Band | BK71: 0 | BL71: 1 | BM71: 1 | BN71: 2 | BO71: A rhythm of holding one or two deep, strategic "wargaming" sessions per year focused on major planetary shifts. | BP71: 0 | BQ71: Resilience as Being | BR71: Fire | BS71: Do we joyfully and consciously embrace the cycles of death and rebirth to emerge ever more coherent? | BT71: The Phoenix | BU71: ↑ | BV71: 1 | BW71: 5 | BX71: N/A | BY71: N/A | BZ71: The mastery of "Anti-Fragility." The system not only withstands shocks, but uses them as the very fuel for its own magnificent evolution. | CA71: 0
A72: Risk & Resilience (F12) | B72: Systemic Fragility Assessment | C72: Air | D72: Do we understand out risks? | E72: Clarity of Risk Documentation (1-5) | F72: ↑ | G72: 1.5 | H72: 1 | I72: 4 | J72: N/A | K72: N/A | L72: A 1-5 score. Have we honestly and clearly written down what could go wrong? | M72: =MAX(0,MIN(1,(G72-H72)/(Octave_1_KPIs[[#This Row],[Healthy_Min]]-Octave_1_KPIs[[#This Row],[Target_Min]]))) -> 0.16666667 | N72: Risk Management Systems | O72: Air | P72: Have we clearly documented our known risks? | Q72: Clarity of Risk Register | R72: ↑ | S72: 1 | T72: 5 | U72: N/A | V72: N/A | W72: A perfectly clear, written log of the top 5-10 risks facing the venture. | X72: 0 | Y72: Relational Resilience | Z72: Air | AA72: Do we have a clear, agreed-upon process for healing? | AB72: Clarity of Conflict Resolution Protocols | AC72: ↑ | AD72: 1 | AE72: 5 | AF72: N/A | AG72: N/A | AH72: Is there a written, understood, and trusted process for navigating conflict? | AI72: 0 | AJ72: Innovative Resilience | AK72: Air | AL72: Are we crystal clear about what we need to prove? | AM72: Clarity on "Riskiest Assumptions" | AN72: ↑ | AO72: 1 | AP72: 5 | AQ72: N/A | AR72: N/A | AS72: How clearly has the team identified and documented the biggest assumptions in its business model that need to be tested and validated? | AT72: 0 | AU72: Resilience through Story | AV72: Air | AW72: Are we radically transparent about the risks we face? | AX72: Clarity of Risk & Mitigation Comms. | AY72: ↑ | AZ72: 1 | BA72: 4.8 | BB72: N/A | BC72: N/A | BD72: How clearly do we communicate our known risks and our plans to mitigate them to our stakeholders? | BE72: 0 | BF72: "Anti-Fragile" Vision | BG72: Air | BH72: Is the plan for how leadership evolves clear and transparent? | BI72: Clarity of "Succession Triggers" | BJ72: ↑ | BK72: 1 | BL72: 5 | BM72: N/A | BN72: N/A | BO72: Is it perfectly clear under what conditions and through what process the current leadership would pass the baton? | BP72: 0 | BQ72: Resilience as Being | BR72: Air | BS72: Have we transcended the need for "risk management" because our every action is an expression of perfect, intuitive alignment? | BT72: The Silence of Perfect Knowing | BU72: ↑ | BV72: 1 | BW72: 5 | BX72: N/A | BY72: N/A | BZ72: The clarity that comes when the inner compass and the outer path are one. | CA72: 0
A73: Risk & Resilience (F12) | B73: Systemic Fragility Assessment | C73: Ether | D73: Will we hold to our values under ultimate pressure? | E73: Ethical Resilience Score (from Edge KPIs) | F73: ↑ | G73: 4 | H73: 1 | I73: 4.5 | J73: N/A | K73: N/A | L73: From the Edge KPIs. The measure of the soul's resilience. | M73: =MAX(0,MIN(1,(G73-H73)/(Octave_1_KPIs[[#This Row],[Healthy_Min]]-Octave_1_KPIs[[#This Row],[Target_Min]]))) -> 0.85714286 | N73: Risk Management Systems | O73: Ether | P73: Will our values hold up under extreme pressure? | Q73: Ethical Resilience Score | R73: ↑ | S73: 1 | T73: 4.5 | U73: N/A | V73: N/A | W73: The Edge KPI. The measure of the soul's ability to maintain integrity in a crisis. | X73: 0 | Y73: Relational Resilience | Z73: Ether | AA73: Does our culture get stronger from facing challenges? | AB73: "Anti-Fragility" of Culture | AC73: ↑ | AD73: 1 | AE73: 4.5 | AF73: N/A | AG73: N/A | AH73: A qualitative score. Do we learn, grow, and become more coherent after a crisis, or are we weakened by it? | AI73: 0 | AJ73: Innovative Resilience | AK73: Ether | AL73: Do we see that the greatest risk is not innovating? | AM73: Innovation as the Ultimate Risk Mitigation | AN73: ↑ | AO73: 1 | AP73: 5 | AQ73: N/A | AR73: N/A | AS73: A cultural score. To what degree does the organization understand that in a complex world, the only true safety lies in continuous, conscious evolution? | AT73: 0 | AU73: Resilience through Story | AV73: Ether | AW73: Does our open honesty become our greatest source of resilience? | AX73: Our Vulnerability as a Source of Strength | AY73: ↑ | AZ73: 1 | BA73: 5 | BB73: N/A | BC73: N/A | BD73: The ultimate paradox of authentic expression: does our willingness to be vulnerable make us invincible? | BE73: 0 | BF73: "Anti-Fragile" Vision | BG73: Ether | BH73: Is our vision itself a living, evolving, anti-fragile entity? | BI73: The Vision's Ability to Self-Correct | BJ73: ↑ | BK73: 1 | BL73: 5 | BM73: N/A | BN73: N/A | BO73: The ultimate measure of a resilient vision: is it designed to learn, adapt, and even transcend its own origins? | BP73: 0 | BQ73: Resilience as Being | BR73: Ether | BS73: Have we dissolved the illusion that we are "building" coherence, and realized that we are an expression of the universe's own coherence? | BT73: We are Coherence | BU73: ↑ | BV73: 1 | BW73: 5 | BX73: N/A | BY73: N/A | BZ73: The final, beautiful, and total surrender to the music that was always and already playing. | CA73: 0
A78: The Shadow Penalty Rules: The Conscience of the Instrument
A80: Rule Name | B80: The Story (Archetypal Dissonance) | C80: Trigger Condition (The "IF") | D80: Target of Penalty | E80: Penalty (S) | F80: The animating principle: A high score is only a true score if it does not create a "shadow"—a corresponding, hidden cost in another part of the system. When a shadow is detected, a penalty is applied, making the dissonance visible and forcing the organization to confront its own hypocris
A81: "Brittle Profit" | B81: The organization is financially successful but is fragile and on the verge of collapse. It is a tree with fruit but no roots. | C81: High Coherence in Financial Capital (F1) AND Low Coherence in Risk & Resilience (F12). | D81: Financial Capital (F1) | E81: 0.25
A82: "Extractive Growth" | B82: The organization grows its revenue by depleting the natural or social ecosystems it depends on. It is "sawing off the branch it is sitting on." | C82: High Coherence in Financial Capital (F1) OR Funding Pipeline (F11) AND Low Coherence in Regenerative Flow (F9). | D82: The Face with the high score (F1 or F11) | E82: 0.3 | F82: During your weekly or monthly calibration loops, you, the conductor, will look at the dashboard. You will then look at this table of rules. You will ask the profound, challenging questions:
A83: "The Experience Gap" (Trust Theater) | B83: The organization has a brilliant marketing story and a strong brand, but the actual experience of its product or culture is poor. The "say-do" gap. | C83: High Coherence in Brand & Reputation (F7) OR Market Resonance (F5) AND Low Coherence in Core Operations (F8) OR Human Capital (F3). | D83: The Face with the high score (F7 or F5) | E83: 0.35
A84: "The Burnout Engine" | B84: The organization is incredibly efficient and productive, but it achieves this by burning out its people. The machine is running perfectly, but the operators are collapsing. | C84: High Coherence in Core Operations (F8) AND Low Coherence in Human Capital (F3). | D84: Core Operations (F8) | E84: 0.4 | F84: "Our Brand score is high, but our Founder Energy is low. Are we creating an 'Experience Gap'? Are we telling a story of coherence that we are not living?" | V84: You can see how a domain like Financial Capital evolves from the simple, desperate question of "Do we have money?" (O1) to the profound, generative question of "Is our use of money itself an act of healing the world?" (O7).
A85: "Hollow Governance" | B85: The organization has many formal rules and well-drafted documents, but it lacks a true culture of integrity and lived values. The "bones" have no soul. | C85: High Coherence in Structural Capital (F4) AND Low Coherence in Foundational Values (F10). | D85: Structural Capital (F4) | E85: 0.2 | F85: "Our profits are stable, but our Bus Factor is still 1. Are we in a state of 'Brittle Profit'?" | V85: You can see how Human Capital evolves from the basic need to avoid burnout (O1) to the ultimate state of a culture defined by joy and play (O7).
A86: "The Lonely Hero" | B86: The venture's vision and IP are brilliant, but it relies entirely on a single person or a fragile network, making it un-investable and un-scalable. | C86: High Coherence in Intellectual Capital (F2) AND a Bus Factor of 1 (Risk & Resilience (F12) is low). | D86: Intellectual Capital (F2) | E86: 0.3
F87: If the answer is yes, you make the courageous decision to activate the penalty. You go to your DODECA_ENGINE (or a dedicated "Penalty Log" sheet) and you manually log the penalty for that cycle.
A88: The Mechanics in the Spreadsheet:
A90: The Shadow Penalty is a number (S) between 0 and 1 (e.g., 0.2 for a 20% penalty). The final Face Energy formula we designed will be upgraded to include it:
A92: Final_E_f = ((γ * Self_Coherence) + ((1-γ) * Relational_Coherence)) * (1 - Total_Shadow_Penalty_for_this_Face)
A94: The "Total Shadow Penalty" will be calculated with a SUMIFS formula that looks up all applicable penalties from the master table we are about to build.
A96: Earth (Stability): Is it grounded? ->
A97: Water (Flow): Is it managed? ->
A98: Fire: Are we adding to it? ->
A99: Air: Is it understood? ->
A100: Ether: Is it aligned? ->

Sheet SYSTEM_COHERENCE
A1: Department | B1: Dodecahedron's Face | C1: O1 | D1: O2 | E1: O3 | F1: O4 | G1: O5 | H1: O6 | I1: O7 | J1: Department Mean (μ) | K1: Dept. Variance (σ²) | L1: Department Coherence
A2: =DODECA_ENGINE!B6 -> Market Resonance | B2: Face 5 | C2: =IFERROR(AVERAGEIFS(KPI_DATABASE!$M:$M, KPI_DATABASE!$D:$D, $B2, KPI_DATABASE!$E:$E, C$1), "") -> 0 | D2: =IFERROR(AVERAGEIFS(KPI_DATABASE!$M:$M, KPI_DATABASE!$D:$D, $B2, KPI_DATABASE!$E:$E, D$1), "") | E2: =IFERROR(AVERAGEIFS(KPI_DATABASE!$M:$M, KPI_DATABASE!$D:$D, $B2, KPI_DATABASE!$E:$E, E$1), "") | F2: =IFERROR(AVERAGEIFS(KPI_DATABASE!$M:$M, KPI_DATABASE!$D:$D, $B2, KPI_DATABASE!$E:$E, F$1), "") | G2: =IFERROR(AVERAGEIFS(KPI_DATABASE!$M:$M, KPI_DATABASE!$D:$D, $B2, KPI_DATABASE!$E:$E, G$1), "") | H2: =IFERROR(AVERAGEIFS(KPI_DATABASE!$M:$M, KPI_DATABASE!$D:$D, $B2, KPI_DATABASE!$E:$E, H$1), "") | I2: =IFERROR(AVERAGEIFS(KPI_DATABASE!$M:$M, KPI_DATABASE!$D:$D, $B2, KPI_DATABASE!$E:$E, I$1), "") | J2: =AVERAGE(C2:I2) -> 0 | K2: =_xlfn.VAR.P(C2:I2) -> 0 | L2: =J2 - (0.3 * K2) -> 0
A3: =DODECA_ENGINE!B2 -> Financial Capital | B3: Face 1 | C3: =IFERROR(AVERAGEIFS(KPI_DATABASE!$M:$M, KPI_DATABASE!$D:$D, $B3, KPI_DATABASE!$E:$E, C$1), "") -> 0.39297662 | D3: =IFERROR(AVERAGEIFS(KPI_DATABASE!$M:$M, KPI_DATABASE!$D:$D, $B3, KPI_DATABASE!$E:$E, D$1), "") | E3: =IFERROR(AVERAGEIFS(KPI_DATABASE!$M:$M, KPI_DATABASE!$D:$D, $B3, KPI_DATABASE!$E:$E, E$1), "") | F3: =IFERROR(AVERAGEIFS(KPI_DATABASE!$M:$M, KPI_DATABASE!$D:$D, $B3, KPI_DATABASE!$E:$E, F$1), "") | G3: =IFERROR(AVERAGEIFS(KPI_DATABASE!$M:$M, KPI_DATABASE!$D:$D, $B3, KPI_DATABASE!$E:$E, G$1), "") | H3: =IFERROR(AVERAGEIFS(KPI_DATABASE!$M:$M, KPI_DATABASE!$D:$D, $B3, KPI_DATABASE!$E:$E, H$1), "") | I3: =IFERROR(AVERAGEIFS(KPI_DATABASE!$M:$M, KPI_DATABASE!$D:$D, $B3, KPI_DATABASE!$E:$E, I$1), "") | J3: =AVERAGE(C3:I3) -> 0.39297662 | K3: =_xlfn.VAR.P(C3:I3) -> 0 | L3: =J3 - (0.3 * K3) -> 0.39297662
A4: =DODECA_ENGINE!B4 -> Human Capital | B4: Face 3 | C4: =IFERROR(AVERAGEIFS(KPI_DATABASE!$M:$M, KPI_DATABASE!$D:$D, $B4, KPI_DATABASE!$E:$E, C$1), "") -> 0.1872 | D4: =IFERROR(AVERAGEIFS(KPI_DATABASE!$M:$M, KPI_DATABASE!$D:$D, $B4, KPI_DATABASE!$E:$E, D$1), "") | E4: =IFERROR(AVERAGEIFS(KPI_DATABASE!$M:$M, KPI_DATABASE!$D:$D, $B4, KPI_DATABASE!$E:$E, E$1), "") | F4: =IFERROR(AVERAGEIFS(KPI_DATABASE!$M:$M, KPI_DATABASE!$D:$D, $B4, KPI_DATABASE!$E:$E, F$1), "") | G4: =IFERROR(AVERAGEIFS(KPI_DATABASE!$M:$M, KPI_DATABASE!$D:$D, $B4, KPI_DATABASE!$E:$E, G$1), "") | H4: =IFERROR(AVERAGEIFS(KPI_DATABASE!$M:$M, KPI_DATABASE!$D:$D, $B4, KPI_DATABASE!$E:$E, H$1), "") | I4: =IFERROR(AVERAGEIFS(KPI_DATABASE!$M:$M, KPI_DATABASE!$D:$D, $B4, KPI_DATABASE!$E:$E, I$1), "") | J4: =AVERAGE(C4:I4) -> 0.1872 | K4: =_xlfn.VAR.P(C4:I4) -> 0 | L4: =J4 - (0.3 * K4) -> 0.1872
A5: =DODECA_ENGINE!B11 -> Foundational Values | B5: Face 10 | C5: =IFERROR(AVERAGEIFS(KPI_DATABASE!$M:$M, KPI_DATABASE!$D:$D, $B5, KPI_DATABASE!$E:$E, C$1), "") -> 0.67021333 | D5: =IFERROR(AVERAGEIFS(KPI_DATABASE!$M:$M, KPI_DATABASE!$D:$D, $B5, KPI_DATABASE!$E:$E, D$1), "") | E5: =IFERROR(AVERAGEIFS(KPI_DATABASE!$M:$M, KPI_DATABASE!$D:$D, $B5, KPI_DATABASE!$E:$E, E$1), "") | F5: =IFERROR(AVERAGEIFS(KPI_DATABASE!$M:$M, KPI_DATABASE!$D:$D, $B5, KPI_DATABASE!$E:$E, F$1), "") | G5: =IFERROR(AVERAGEIFS(KPI_DATABASE!$M:$M, KPI_DATABASE!$D:$D, $B5, KPI_DATABASE!$E:$E, G$1), "") | H5: =IFERROR(AVERAGEIFS(KPI_DATABASE!$M:$M, KPI_DATABASE!$D:$D, $B5, KPI_DATABASE!$E:$E, H$1), "") | I5: =IFERROR(AVERAGEIFS(KPI_DATABASE!$M:$M, KPI_DATABASE!$D:$D, $B5, KPI_DATABASE!$E:$E, I$1), "") | J5: =AVERAGE(C5:I5) -> 0.67021333 | K5: =_xlfn.VAR.P(C5:I5) -> 0 | L5: =J5 - (0.3 * K5) -> 0.67021333
A6: =DODECA_ENGINE!B5 -> Structural Capital | B6: Face 4 | C6: =IFERROR(AVERAGEIFS(KPI_DATABASE!$M:$M, KPI_DATABASE!$D:$D, $B6, KPI_DATABASE!$E:$E, C$1), "") -> 0.372 | D6: =IFERROR(AVERAGEIFS(KPI_DATABASE!$M:$M, KPI_DATABASE!$D:$D, $B6, KPI_DATABASE!$E:$E, D$1), "") | E6: =IFERROR(AVERAGEIFS(KPI_DATABASE!$M:$M, KPI_DATABASE!$D:$D, $B6, KPI_DATABASE!$E:$E, E$1), "") | F6: =IFERROR(AVERAGEIFS(KPI_DATABASE!$M:$M, KPI_DATABASE!$D:$D, $B6, KPI_DATABASE!$E:$E, F$1), "") | G6: =IFERROR(AVERAGEIFS(KPI_DATABASE!$M:$M, KPI_DATABASE!$D:$D, $B6, KPI_DATABASE!$E:$E, G$1), "") | H6: =IFERROR(AVERAGEIFS(KPI_DATABASE!$M:$M, KPI_DATABASE!$D:$D, $B6, KPI_DATABASE!$E:$E, H$1), "") | I6: =IFERROR(AVERAGEIFS(KPI_DATABASE!$M:$M, KPI_DATABASE!$D:$D, $B6, KPI_DATABASE!$E:$E, I$1), "") | J6: =AVERAGE(C6:I6) -> 0.372 | K6: =_xlfn.VAR.P(C6:I6) -> 0 | L6: =J6 - (0.3 * K6) -> 0.372
A7: =DODECA_ENGINE!B8 -> Brand & Reputation | B7: Face 7 | C7: =IFERROR(AVERAGEIFS(KPI_DATABASE!$M:$M, KPI_DATABASE!$D:$D, $B7, KPI_DATABASE!$E:$E, C$1), "") -> 0.3132381 | D7: =IFERROR(AVERAGEIFS(KPI_DATABASE!$M:$M, KPI_DATABASE!$D:$D, $B7, KPI_DATABASE!$E:$E, D$1), "") | E7: =IFERROR(AVERAGEIFS(KPI_DATABASE!$M:$M, KPI_DATABASE!$D:$D, $B7, KPI_DATABASE!$E:$E, E$1), "") | F7: =IFERROR(AVERAGEIFS(KPI_DATABASE!$M:$M, KPI_DATABASE!$D:$D, $B7, KPI_DATABASE!$E:$E, F$1), "") | G7: =IFERROR(AVERAGEIFS(KPI_DATABASE!$M:$M, KPI_DATABASE!$D:$D, $B7, KPI_DATABASE!$E:$E, G$1), "") | H7: =IFERROR(AVERAGEIFS(KPI_DATABASE!$M:$M, KPI_DATABASE!$D:$D, $B7, KPI_DATABASE!$E:$E, H$1), "") | I7: =IFERROR(AVERAGEIFS(KPI_DATABASE!$M:$M, KPI_DATABASE!$D:$D, $B7, KPI_DATABASE!$E:$E, I$1), "") | J7: =AVERAGE(C7:I7) -> 0.3132381 | K7: =_xlfn.VAR.P(C7:I7) -> 0 | L7: =J7 - (0.3 * K7) -> 0.3132381
A8: =DODECA_ENGINE!B10 -> Regenerative Flow | B8: Face 9 | C8: =IFERROR(AVERAGEIFS(KPI_DATABASE!$M:$M, KPI_DATABASE!$D:$D, $B8, KPI_DATABASE!$E:$E, C$1), "") -> 0.67021333 | D8: =IFERROR(AVERAGEIFS(KPI_DATABASE!$M:$M, KPI_DATABASE!$D:$D, $B8, KPI_DATABASE!$E:$E, D$1), "") | E8: =IFERROR(AVERAGEIFS(KPI_DATABASE!$M:$M, KPI_DATABASE!$D:$D, $B8, KPI_DATABASE!$E:$E, E$1), "") | F8: =IFERROR(AVERAGEIFS(KPI_DATABASE!$M:$M, KPI_DATABASE!$D:$D, $B8, KPI_DATABASE!$E:$E, F$1), "") | G8: =IFERROR(AVERAGEIFS(KPI_DATABASE!$M:$M, KPI_DATABASE!$D:$D, $B8, KPI_DATABASE!$E:$E, G$1), "") | H8: =IFERROR(AVERAGEIFS(KPI_DATABASE!$M:$M, KPI_DATABASE!$D:$D, $B8, KPI_DATABASE!$E:$E, H$1), "") | I8: =IFERROR(AVERAGEIFS(KPI_DATABASE!$M:$M, KPI_DATABASE!$D:$D, $B8, KPI_DATABASE!$E:$E, I$1), "") | J8: =AVERAGE(C8:I8) -> 0.67021333 | K8: =_xlfn.VAR.P(C8:I8) -> 0 | L8: =J8 - (0.3 * K8) -> 0.67021333
A9: =DODECA_ENGINE!B12 -> Funding Pipeline | B9: Face 11 | C9: =IFERROR(AVERAGEIFS(KPI_DATABASE!$M:$M, KPI_DATABASE!$D:$D, $B9, KPI_DATABASE!$E:$E, C$1), "") -> 0.19246095 | D9: =IFERROR(AVERAGEIFS(KPI_DATABASE!$M:$M, KPI_DATABASE!$D:$D, $B9, KPI_DATABASE!$E:$E, D$1), "") | E9: =IFERROR(AVERAGEIFS(KPI_DATABASE!$M:$M, KPI_DATABASE!$D:$D, $B9, KPI_DATABASE!$E:$E, E$1), "") | F9: =IFERROR(AVERAGEIFS(KPI_DATABASE!$M:$M, KPI_DATABASE!$D:$D, $B9, KPI_DATABASE!$E:$E, F$1), "") | G9: =IFERROR(AVERAGEIFS(KPI_DATABASE!$M:$M, KPI_DATABASE!$D:$D, $B9, KPI_DATABASE!$E:$E, G$1), "") | H9: =IFERROR(AVERAGEIFS(KPI_DATABASE!$M:$M, KPI_DATABASE!$D:$D, $B9, KPI_DATABASE!$E:$E, H$1), "") | I9: =IFERROR(AVERAGEIFS(KPI_DATABASE!$M:$M, KPI_DATABASE!$D:$D, $B9, KPI_DATABASE!$E:$E, I$1), "") | J9: =AVERAGE(C9:I9) -> 0.19246095 | K9: =_xlfn.VAR.P(C9:I9) -> 0 | L9: =J9 - (0.3 * K9) -> 0.19246095
A10: =DODECA_ENGINE!B7 -> Community & Partners | B10: Face 6 | C10: =IFERROR(AVERAGEIFS(KPI_DATABASE!$M:$M, KPI_DATABASE!$D:$D, $B10, KPI_DATABASE!$E:$E, C$1), "") -> 0.40247619 | D10: =IFERROR(AVERAGEIFS(KPI_DATABASE!$M:$M, KPI_DATABASE!$D:$D, $B10, KPI_DATABASE!$E:$E, D$1), "") | E10: =IFERROR(AVERAGEIFS(KPI_DATABASE!$M:$M, KPI_DATABASE!$D:$D, $B10, KPI_DATABASE!$E:$E, E$1), "") | F10: =IFERROR(AVERAGEIFS(KPI_DATABASE!$M:$M, KPI_DATABASE!$D:$D, $B10, KPI_DATABASE!$E:$E, F$1), "") | G10: =IFERROR(AVERAGEIFS(KPI_DATABASE!$M:$M, KPI_DATABASE!$D:$D, $B10, KPI_DATABASE!$E:$E, G$1), "") | H10: =IFERROR(AVERAGEIFS(KPI_DATABASE!$M:$M, KPI_DATABASE!$D:$D, $B10, KPI_DATABASE!$E:$E, H$1), "") | I10: =IFERROR(AVERAGEIFS(KPI_DATABASE!$M:$M, KPI_DATABASE!$D:$D, $B10, KPI_DATABASE!$E:$E, I$1), "") | J10: =AVERAGE(C10:I10) -> 0.40247619 | K10: =_xlfn.VAR.P(C10:I10) -> 0 | L10: =J10 - (0.3 * K10) -> 0.40247619
